Workbook

Sheet Trip
A1: Trip Costing — Client name - Destination
A2: Yellow cells with blue text are inputs. Everything else is calculated — don't type over it.
D3: Exchange rates
A4: Trip name | B4: Client name - Destination | D4: Currency | E4: ₹ per 1 unit | F4: Note
A5: Client | D5: INR | E5: 1
A6: Destination | D6: USD | F6: Bank / supplier ROE used for this trip
A7: Travel dates | D7: EUR
A8: No. of pax | B8: 2 | D8: GBP
A9: Rooms required | B9: 1 DBL | D9: CHF
A10: Costing currency | B10: USD | D10: AED
A11: Default markup % | B11: 0.15 | D11: LKR
A12: GST % | B12: 0.05 | D12: THB
A13: TCS % | B13: 0.02 | D13: SGD
A14: Notes | D14: JPY
A17: How this workbook works
A18: 1. Fill in the trip details and today's exchange rates (₹ per 1 unit) above.
A19: 2. Quotes tab: one row per price you receive — hotel, room, meal, source, currency and the amount for ONE room for the WHOLE stay (incl. taxes).
A20: 3. The sheet converts everything to the costing currency, flags ⭐ the cheapest source for each hotel/room/meal and shows the difference vs Booking.com.
A21: 4. Compare tab: every hotel/room with all sources side by side; the best price is highlighted green.
A22: 5. Land tab: transfers, tours, passes, trains, flights, visa — amount + 'Total' or 'Per pax'.
A23: 6. Put Y in the Pkg A / B / C columns for the rows each option uses. The Final tab adds them up with markup, GST and TCS, in the costing currency and in ₹.

Sheet Quotes
A1: Hotel quotes
A2: Amount = price for ONE room for the WHOLE stay, incl. taxes, in the currency quoted. Grey columns are calculated.
L3: Red amount = exchange rate missing on Trip tab
A4: # | B4: City | C4: Check-in | D4: Nights | E4: Hotel | F4: Stars | G4: Room type | H4: Meal | I4: Rooms | J4: Source | K4: Currency | L4: Amount quoted (1 room, whole stay) | M4: Cost / room (costing ccy) | N4: Cost / room / night | O4: Total cost (all rooms) | P4: Free cancel until | Q4: Days left | R4: Status | S4: Booking ref | T4: Label (Base / Upg) | U4: Markup % (blank = default) | V4: Sell / room | W4: Sell total (all rooms) | X4: Best price? | Y4: Booking.com price | Z4: Saving vs Booking.com | AA4: Pkg A | AB4: Pkg B | AC4: Pkg C | AD4: Notes
A5: 1 | B5: Example: Kandy | C5: 46378 | D5: 1 | E5: Example Hotel | F5: 5 | G5: Deluxe Room | H5: BB | I5: 1 | J5: Ottila | K5: INR | L5: 23563 | M5: =IF(L5="","",IFERROR(L5*INDEX(Trip!$E$5:$E$14,MATCH(K5,Trip!$D$5:$D$14,0))/INDEX(Trip!$E$5:$E$14,MATCH(Trip!$B$10,Trip!$D$5:$D$14,0)),"")) | N5: =IF(OR(M5="",D5=""),"",M5/D5) | O5: =IF(M5="","",M5*I5) | P5: 46367 | Q5: =IF(ISNUMBER(P5),P5-TODAY(),IF(P5="","",P5)) -> 65 | R5: Quote | T5: Base | V5: =IF(M5="","",M5*(1+IF(U5="",Trip!$B$11,U5))) | W5: =IF(V5="","",V5*I5) | X5: =IF(OR(M5="",R5="Unavailable"),"",IF(M5=_xlfn.MINIFS($M$5:$M$604,$E$5:$E$604,E5,$G$5:$G$604,G5,$H$5:$H$604,H5,$R$5:$R$604,"<>Unavailable"),"⭐ Cheapest","")) | Y5: =IF(COUNTIFS($E$5:$E$604,E5,$G$5:$G$604,G5,$J$5:$J$604,"Booking.com")=0,"",_xlfn.MINIFS($M$5:$M$604,$E$5:$E$604,E5,$G$5:$G$604,G5,$J$5:$J$604,"Booking.com")) -> 0 | Z5: =IF(OR(Y5="",M5="",J5="Booking.com"),"",Y5-M5) | AA5: Y | AD5: EXAMPLE ROW – overwrite or delete
A6: 2 | B6: Example: Kandy | C6: 46378 | D6: 1 | E6: Example Hotel | F6: 5 | G6: Deluxe Room | H6: BB | I6: 1 | J6: Booking.com | K6: USD | L6: 325 | M6: =IF(L6="","",IFERROR(L6*INDEX(Trip!$E$5:$E$14,MATCH(K6,Trip!$D$5:$D$14,0))/INDEX(Trip!$E$5:$E$14,MATCH(Trip!$B$10,Trip!$D$5:$D$14,0)),"")) | N6: =IF(OR(M6="",D6=""),"",M6/D6) | O6: =IF(M6="","",M6*I6) | P6: 46370 | Q6: =IF(ISNUMBER(P6),P6-TODAY(),IF(P6="","",P6)) -> 68 | R6: Quote | V6: =IF(M6="","",M6*(1+IF(U6="",Trip!$B$11,U6))) | W6: =IF(V6="","",V6*I6) | X6: =IF(OR(M6="",R6="Unavailable"),"",IF(M6=_xlfn.MINIFS($M$5:$M$604,$E$5:$E$604,E6,$G$5:$G$604,G6,$H$5:$H$604,H6,$R$5:$R$604,"<>Unavailable"),"⭐ Cheapest","")) | Y6: =IF(COUNTIFS($E$5:$E$604,E6,$G$5:$G$604,G6,$J$5:$J$604,"Booking.com")=0,"",_xlfn.MINIFS($M$5:$M$604,$E$5:$E$604,E6,$G$5:$G$604,G6,$J$5:$J$604,"Booking.com")) -> 0 | Z6: =IF(OR(Y6="",M6="",J6="Booking.com"),"",Y6-M6) | AD6: EXAMPLE ROW – Booking.com price to compare

Sheet Compare
A1: Price comparison — cost per room for the whole stay (costing currency)
A2: Built from the Quotes tab. Green = cheapest. Add a row here (copy the one above) if you add a new hotel/room on Quotes.
A4: City | B4: Hotel | C4: Room type | D4: Meal | E4: Ottila | F4: Booking.com | G4: Best price | H4: Best source | I4: Booking.com vs best
A5: Example: Kandy | B5: Example Hotel | C5: Deluxe Room | D5: BB | E5: =IF(COUNTIFS(Quotes!$E$5:$E$604,$B5,Quotes!$G$5:$G$604,$C5,Quotes!$H$5:$H$604,$D5,Quotes!$J$5:$J$604,E$4,Quotes!$R$5:$R$604,"<>Unavailable")=0,"",_xlfn.MINIFS(Quotes!$M$5:$M$604,Quotes!$E$5:$E$604,$B5,Quotes!$G$5:$G$604,$C5,Quotes!$H$5:$H$604,$D5,Quotes!$J$5:$J$604,E$4,Quotes!$R$5:$R$604,"<>Unavailable")) -> 0 | F5: =IF(COUNTIFS(Quotes!$E$5:$E$604,$B5,Quotes!$G$5:$G$604,$C5,Quotes!$H$5:$H$604,$D5,Quotes!$J$5:$J$604,F$4,Quotes!$R$5:$R$604,"<>Unavailable")=0,"",_xlfn.MINIFS(Quotes!$M$5:$M$604,Quotes!$E$5:$E$604,$B5,Quotes!$G$5:$G$604,$C5,Quotes!$H$5:$H$604,$D5,Quotes!$J$5:$J$604,F$4,Quotes!$R$5:$R$604,"<>Unavailable")) -> 0 | G5: =IF(COUNT(E5:F5)=0,"",MIN(E5:F5)) -> 0 | H5: =IF(G5="","",INDEX($E$4:$F$4,MATCH(G5,E5:F5,0))) -> Ottila | I5: =IF(OR(F5="",COUNT(E5:E5)=0),"",F5-MIN(E5:E5)) -> 0

Sheet Land
A1: Land, transport & other services
A2: Basis 'Total' = amount is for the whole group; 'Per pax' = amount × Pax/Qty.
A4: # | B4: Date | C4: Service | D4: Type | E4: Source | F4: Currency | G4: Amount | H4: Basis | I4: Pax / Qty | J4: Total cost (costing ccy) | K4: Markup % (blank = default) | L4: Sell total | M4: Pkg A | N4: Pkg B | O4: Pkg C | P4: Notes
A5: 1 | B5: 46375 | C5: Example: Airport to hotel private transfer | D5: Transfer | E5: DMC | F5: USD | G5: 45 | H5: Total | I5: 1 | J5: =IF(G5="","",IFERROR(G5*INDEX(Trip!$E$5:$E$14,MATCH(F5,Trip!$D$5:$D$14,0))/INDEX(Trip!$E$5:$E$14,MATCH(Trip!$B$10,Trip!$D$5:$D$14,0))*IF(H5="Per pax",I5,1),"")) | L5: =IF(J5="","",J5*(1+IF(K5="",Trip!$B$11,K5))) | M5: Y | N5: Y | O5: Y | P5: EXAMPLE ROW

Sheet Final
A1: Final costing
A2: Adds up every Quotes / Land row marked Y for each package. Change the package names and pax freely.
B4: Pkg A | C4: Pkg B | D4: Pkg C | E4: How it's calculated
A5: Package name | B5: Per couple (DBL) | C5: Single (SGL) | D5: Per couple – upgrade | E5: Type your own name
A6: Pax covered by this price | B6: 2 | C6: 1 | D6: 2 | E6: e.g. 2 for a couple, 1 for a single
A7: Price basis | B7: Per room | C7: Per room | D7: Per room | E7: Per room = 1 room of each hotel row (per couple / per single quote). All rooms = whole group (uses the Rooms column)
A8: Hotels — cost to us | B8: =IF(B7="All rooms",SUMIFS(Quotes!$O$5:$O$604,Quotes!$AA$5:$AA$604,"Y"),SUMIFS(Quotes!$M$5:$M$604,Quotes!$AA$5:$AA$604,"Y")) -> 0 | C8: =IF(C7="All rooms",SUMIFS(Quotes!$O$5:$O$604,Quotes!$AB$5:$AB$604,"Y"),SUMIFS(Quotes!$M$5:$M$604,Quotes!$AB$5:$AB$604,"Y")) -> 0 | D8: =IF(D7="All rooms",SUMIFS(Quotes!$O$5:$O$604,Quotes!$AC$5:$AC$604,"Y"),SUMIFS(Quotes!$M$5:$M$604,Quotes!$AC$5:$AC$604,"Y")) -> 0 | E8: Quotes rows with Y
A9: Land & other — cost to us | B9: =SUMIFS(Land!$J$5:$J$204,Land!$M$5:$M$204,"Y") -> 0 | C9: =SUMIFS(Land!$J$5:$J$204,Land!$N$5:$N$204,"Y") -> 0 | D9: =SUMIFS(Land!$J$5:$J$204,Land!$O$5:$O$204,"Y") -> 0 | E9: Land rows with Y
A10: Total cost to us | B10: =B8+B9 -> 0 | C10: =C8+C9 -> 0 | D10: =D8+D9 -> 0 | E10: Hotels + land
A11: Markup | B11: =IF(B7="All rooms",SUMIFS(Quotes!$W$5:$W$604,Quotes!$AA$5:$AA$604,"Y"),SUMIFS(Quotes!$V$5:$V$604,Quotes!$AA$5:$AA$604,"Y"))+SUMIFS(Land!$L$5:$L$204,Land!$M$5:$M$204,"Y")-B10 -> 0 | C11: =IF(C7="All rooms",SUMIFS(Quotes!$W$5:$W$604,Quotes!$AB$5:$AB$604,"Y"),SUMIFS(Quotes!$V$5:$V$604,Quotes!$AB$5:$AB$604,"Y"))+SUMIFS(Land!$L$5:$L$204,Land!$N$5:$N$204,"Y")-C10 -> 0 | D11: =IF(D7="All rooms",SUMIFS(Quotes!$W$5:$W$604,Quotes!$AC$5:$AC$604,"Y"),SUMIFS(Quotes!$V$5:$V$604,Quotes!$AC$5:$AC$604,"Y"))+SUMIFS(Land!$L$5:$L$204,Land!$O$5:$O$204,"Y")-D10 -> 0 | E11: Sell price − cost (row-level markups)
A12: Cost to client | B12: =B10+B11 -> 0 | C12: =C10+C11 -> 0 | D12: =D10+D11 -> 0 | E12: Cost + markup
A13: GST | B13: =B12*Trip!$B$12 -> 0 | C13: =C12*Trip!$B$12 -> 0 | D13: =D12*Trip!$B$12 -> 0 | E13: GST % from Trip tab × cost to client
A14: TCS | B14: =(B12+B13)*Trip!$B$13 -> 0 | C14: =(C12+C13)*Trip!$B$13 -> 0 | D14: =(D12+D13)*Trip!$B$13 -> 0 | E14: TCS % from Trip tab × (client cost + GST)
A15: Payable (costing currency) | B15: =B12+B13+B14 -> 0 | C15: =C12+C13+C14 -> 0 | D15: =D12+D13+D14 -> 0 | E15: Client cost + GST + TCS
A16: Exchange rate (₹ per 1 unit) | B16: =IFERROR(INDEX(Trip!$E$5:$E$14,MATCH(Trip!$B$10,Trip!$D$5:$D$14,0)),0) -> 0 | C16: =IFERROR(INDEX(Trip!$E$5:$E$14,MATCH(Trip!$B$10,Trip!$D$5:$D$14,0)),0) -> 0 | D16: =IFERROR(INDEX(Trip!$E$5:$E$14,MATCH(Trip!$B$10,Trip!$D$5:$D$14,0)),0) -> 0 | E16: From Trip tab
A17: Payable in ₹ | B17: =B15*B16 -> 0 | C17: =C15*C16 -> 0 | D17: =D15*D16 -> 0 | E17: Payable × rate
A18: Payable in ₹ — rounded up | B18: =ROUNDUP(B17,-2) -> 0 | C18: =ROUNDUP(C17,-2) -> 0 | D18: =ROUNDUP(D17,-2) -> 0 | E18: Rounded up to the next ₹100
A19: Per pax in ₹ | B19: =IF(B6>0,B18/B6,"") -> 0 | C19: =IF(C6>0,C18/C6,"") -> 0 | D19: =IF(D6>0,D18/D6,"") -> 0 | E19: Rounded payable ÷ pax covered
A20: Markup % on cost | B20: =IF(B10>0,B11/B10,"") | C20: =IF(C10>0,C11/C10,"") | D20: =IF(D10>0,D11/D10,"") | E20: Check: is the margin right?
A21: Earliest free-cancel deadline | B21: =IF(COUNTIFS(Quotes!$AA$5:$AA$604,"Y",Quotes!$P$5:$P$604,">0")=0,"—",_xlfn.MINIFS(Quotes!$P$5:$P$604,Quotes!$AA$5:$AA$604,"Y")) -> 46367 | C21: =IF(COUNTIFS(Quotes!$AB$5:$AB$604,"Y",Quotes!$P$5:$P$604,">0")=0,"—",_xlfn.MINIFS(Quotes!$P$5:$P$604,Quotes!$AB$5:$AB$604,"Y")) -> — | D21: =IF(COUNTIFS(Quotes!$AC$5:$AC$604,"Y",Quotes!$P$5:$P$604,">0")=0,"—",_xlfn.MINIFS(Quotes!$P$5:$P$604,Quotes!$AC$5:$AC$604,"Y")) -> — | E21: Book or cancel before this date
A22: Rows included (hotels / land) | B22: =COUNTIF(Quotes!$AA$5:$AA$604,"Y")&" / "&COUNTIF(Land!$M$5:$M$204,"Y") -> 1 / 1 | C22: =COUNTIF(Quotes!$AB$5:$AB$604,"Y")&" / "&COUNTIF(Land!$N$5:$N$204,"Y") -> 0 / 1 | D22: =COUNTIF(Quotes!$AC$5:$AC$604,"Y")&" / "&COUNTIF(Land!$O$5:$O$204,"Y") -> 0 / 1 | E22: Quick check nothing is missing
A24: Costing currency: | B24: =Trip!$B$10 -> USD

Sheet Lists
A1: Sources | B1: Meal | C1: Status | D1: LandType | E1: Basis | F1: YN
A2: Ottila | B2: RO | C2: Quote | D2: Transport | E2: Total | F2: Y
A3: TBO | B3: BB | C3: Requested | D3: Transfer | E3: Per pax
A4: BTR | B4: HB | C4: Blocked | D4: Tour
A5: Helanka | B5: FB | C5: Booked | D5: Activity
A6: Direct | B6: AI | C6: Unavailable | D6: Train
A7: DMC | B7: N/A | D7: Pass
A8: Booking.com | D8: Guide
A9: Hotel website | D9: Flight
A10: Agoda | D10: Visa
A11: Expedia | D11: Insurance
A12: Tourfox | D12: Other
A13: Weshare
A14: Online
A15: Other
