Workbook

Sheet Trip
A1: Trip Costing — Kunj - Sri Lanka
A2: Yellow cells with blue text are inputs. Everything else is calculated — don't type over it.
D3: Exchange rates
A4: Trip name | B4: Kunj - Sri Lanka | D4: Currency | E4: ₹ per 1 unit | F4: Note
A5: Client | B5: Kunj | D5: INR | E5: 1
A6: Destination | B6: Sri Lanka | D6: USD | E6: 94.3 | F6: Bank / supplier ROE used for this trip
A7: Travel dates | B7: 19 Dec 2026 – 01 Jan 2027 (14N/15D) | D7: EUR
A8: No. of pax | B8: 9 | D8: GBP
A9: Rooms required | B9: 5 rooms (4 DBL + 1 SGL) | D9: CHF
A10: Costing currency | B10: USD | D10: AED
A11: Default markup % | B11: 0.15 | D11: LKR
A12: GST % | B12: 0.05 | D12: THB
A13: TCS % | B13: 0.02 | D13: SGD
A14: Notes | B14: Galle booked by client on own. | D14: JPY
A17: How this workbook works
A18: 1. Fill in the trip details and today's exchange rates (₹ per 1 unit) above.
A19: 2. Quotes tab: one row per price you receive — hotel, room, meal, source, currency and the amount for ONE room for the WHOLE stay (incl. taxes).
A20: 3. The sheet converts everything to the costing currency, flags ⭐ the cheapest source for each hotel/room/meal and shows the difference vs Booking.com.
A21: 4. Compare tab: every hotel/room with all sources side by side; the best price is highlighted green.
A22: 5. Land tab: transfers, tours, passes, trains, flights, visa — amount + 'Total' or 'Per pax'.
A23: 6. Put Y in the Pkg A / B / C columns for the rows each option uses. The Final tab adds them up with markup, GST and TCS, in the costing currency and in ₹.

Sheet Quotes
A1: Hotel quotes
A2: Amount = price for ONE room for the WHOLE stay, incl. taxes, in the currency quoted. Grey columns are calculated.
L3: Red amount = exchange rate missing on Trip tab
A4: # | B4: City | C4: Check-in | D4: Nights | E4: Hotel | F4: Stars | G4: Room type | H4: Meal | I4: Rooms | J4: Source | K4: Currency | L4: Amount quoted (1 room, whole stay) | M4: Cost / room (costing ccy) | N4: Cost / room / night | O4: Total cost (all rooms) | P4: Free cancel until | Q4: Days left | R4: Status | S4: Booking ref | T4: Label (Base / Upg) | U4: Markup % (blank = default) | V4: Sell / room | W4: Sell total (all rooms) | X4: Best price? | Y4: Booking.com price | Z4: Saving vs Booking.com | AA4: Pkg A | AB4: Pkg B | AC4: Pkg C | AD4: Notes
A5: 1 | B5: Negombo | C5: 46375 | D5: 1 | E5: Regal Reseau Hotel And Spa | F5: 4 | G5: Super, Deluxe, King Bed, Sea View 28m2 | H5: BB | I5: 1 | J5: Ottila | K5: INR | L5: 14213 | M5: =IF(L5="","",IFERROR(L5*INDEX(Trip!$E$5:$E$14,MATCH(K5,Trip!$D$5:$D$14,0))/INDEX(Trip!$E$5:$E$14,MATCH(Trip!$B$10,Trip!$D$5:$D$14,0)),"")) -> 150.7211 | N5: =IF(OR(M5="",D5=""),"",M5/D5) -> 150.7211 | O5: =IF(M5="","",M5*I5) -> 150.7211 | P5: 46369 | Q5: =IF(ISNUMBER(P5),P5-TODAY(),IF(P5="","",P5)) -> 67 | R5: Quote | V5: =IF(M5="","",M5*(1+IF(U5="",Trip!$B$11,U5))) -> 173.32927 | W5: =IF(V5="","",V5*I5) -> 173.32927 | X5: =IF(OR(M5="",R5="Unavailable"),"",IF(M5=_xlfn.MINIFS($M$5:$M$604,$E$5:$E$604,E5,$G$5:$G$604,G5,$H$5:$H$604,H5,$R$5:$R$604,"<>Unavailable"),"⭐ Cheapest","")) | Y5: =IF(COUNTIFS($E$5:$E$604,E5,$G$5:$G$604,G5,$J$5:$J$604,"Booking.com")=0,"",_xlfn.MINIFS($M$5:$M$604,$E$5:$E$604,E5,$G$5:$G$604,G5,$J$5:$J$604,"Booking.com")) -> 139.14104 | Z5: =IF(OR(Y5="",M5="",J5="Booking.com"),"",Y5-M5) -> -11.580064
A6: 2 | B6: Negombo | C6: 46375 | D6: 1 | E6: Regal Reseau Hotel And Spa | F6: 4 | G6: Super, Deluxe, King Bed, Sea View 28m2 | H6: BB | I6: 1 | J6: Booking.com | K6: INR | L6: 13121 | M6: =IF(L6="","",IFERROR(L6*INDEX(Trip!$E$5:$E$14,MATCH(K6,Trip!$D$5:$D$14,0))/INDEX(Trip!$E$5:$E$14,MATCH(Trip!$B$10,Trip!$D$5:$D$14,0)),"")) -> 139.14104 | N6: =IF(OR(M6="",D6=""),"",M6/D6) -> 139.14104 | O6: =IF(M6="","",M6*I6) -> 139.14104 | P6: 46372 | Q6: =IF(ISNUMBER(P6),P6-TODAY(),IF(P6="","",P6)) -> 70 | R6: Quote | V6: =IF(M6="","",M6*(1+IF(U6="",Trip!$B$11,U6))) -> 160.0122 | W6: =IF(V6="","",V6*I6) -> 160.0122 | X6: =IF(OR(M6="",R6="Unavailable"),"",IF(M6=_xlfn.MINIFS($M$5:$M$604,$E$5:$E$604,E6,$G$5:$G$604,G6,$H$5:$H$604,H6,$R$5:$R$604,"<>Unavailable"),"⭐ Cheapest","")) -> ⭐ Cheapest | Y6: =IF(COUNTIFS($E$5:$E$604,E6,$G$5:$G$604,G6,$J$5:$J$604,"Booking.com")=0,"",_xlfn.MINIFS($M$5:$M$604,$E$5:$E$604,E6,$G$5:$G$604,G6,$J$5:$J$604,"Booking.com")) -> 139.14104 | Z6: =IF(OR(Y6="",M6="",J6="Booking.com"),"",Y6-M6)
A7: 3 | B7: Negombo | C7: 46375 | D7: 1 | E7: Jetwing Sea Hotel | F7: 4 | G7: Standard Double Sea View | H7: BB | I7: 1 | J7: Ottila | K7: INR | L7: 10318 | M7: =IF(L7="","",IFERROR(L7*INDEX(Trip!$E$5:$E$14,MATCH(K7,Trip!$D$5:$D$14,0))/INDEX(Trip!$E$5:$E$14,MATCH(Trip!$B$10,Trip!$D$5:$D$14,0)),"")) -> 109.41676 | N7: =IF(OR(M7="",D7=""),"",M7/D7) -> 109.41676 | O7: =IF(M7="","",M7*I7) -> 109.41676 | P7: 46357 | Q7: =IF(ISNUMBER(P7),P7-TODAY(),IF(P7="","",P7)) -> 55 | R7: Quote | V7: =IF(M7="","",M7*(1+IF(U7="",Trip!$B$11,U7))) -> 125.82927 | W7: =IF(V7="","",V7*I7) -> 125.82927 | X7: =IF(OR(M7="",R7="Unavailable"),"",IF(M7=_xlfn.MINIFS($M$5:$M$604,$E$5:$E$604,E7,$G$5:$G$604,G7,$H$5:$H$604,H7,$R$5:$R$604,"<>Unavailable"),"⭐ Cheapest","")) -> ⭐ Cheapest | Y7: =IF(COUNTIFS($E$5:$E$604,E7,$G$5:$G$604,G7,$J$5:$J$604,"Booking.com")=0,"",_xlfn.MINIFS($M$5:$M$604,$E$5:$E$604,E7,$G$5:$G$604,G7,$J$5:$J$604,"Booking.com")) | Z7: =IF(OR(Y7="",M7="",J7="Booking.com"),"",Y7-M7)
A8: 4 | B8: Negombo | C8: 46375 | D8: 1 | E8: Jetwing Blue | F8: 5 | G8: Deluxe Room | H8: BB | I8: 1 | J8: Ottila | K8: INR | L8: 15158 | M8: =IF(L8="","",IFERROR(L8*INDEX(Trip!$E$5:$E$14,MATCH(K8,Trip!$D$5:$D$14,0))/INDEX(Trip!$E$5:$E$14,MATCH(Trip!$B$10,Trip!$D$5:$D$14,0)),"")) -> 160.74231 | N8: =IF(OR(M8="",D8=""),"",M8/D8) -> 160.74231 | O8: =IF(M8="","",M8*I8) -> 160.74231 | P8: 46348 | Q8: =IF(ISNUMBER(P8),P8-TODAY(),IF(P8="","",P8)) -> 46 | R8: Quote | T8: Base | V8: =IF(M8="","",M8*(1+IF(U8="",Trip!$B$11,U8))) -> 184.85366 | W8: =IF(V8="","",V8*I8) -> 184.85366 | X8: =IF(OR(M8="",R8="Unavailable"),"",IF(M8=_xlfn.MINIFS($M$5:$M$604,$E$5:$E$604,E8,$G$5:$G$604,G8,$H$5:$H$604,H8,$R$5:$R$604,"<>Unavailable"),"⭐ Cheapest","")) -> ⭐ Cheapest | Y8: =IF(COUNTIFS($E$5:$E$604,E8,$G$5:$G$604,G8,$J$5:$J$604,"Booking.com")=0,"",_xlfn.MINIFS($M$5:$M$604,$E$5:$E$604,E8,$G$5:$G$604,G8,$J$5:$J$604,"Booking.com")) -> 179 | Z8: =IF(OR(Y8="",M8="",J8="Booking.com"),"",Y8-M8) -> 18.257688
A9: 5 | B9: Negombo | C9: 46375 | D9: 1 | E9: Jetwing Blue | F9: 5 | G9: Deluxe Room | H9: BB | I9: 1 | J9: Booking.com | K9: USD | L9: 179 | M9: =IF(L9="","",IFERROR(L9*INDEX(Trip!$E$5:$E$14,MATCH(K9,Trip!$D$5:$D$14,0))/INDEX(Trip!$E$5:$E$14,MATCH(Trip!$B$10,Trip!$D$5:$D$14,0)),"")) -> 179 | N9: =IF(OR(M9="",D9=""),"",M9/D9) -> 179 | O9: =IF(M9="","",M9*I9) -> 179 | Q9: =IF(ISNUMBER(P9),P9-TODAY(),IF(P9="","",P9)) | R9: Quote | V9: =IF(M9="","",M9*(1+IF(U9="",Trip!$B$11,U9))) -> 205.85 | W9: =IF(V9="","",V9*I9) -> 205.85 | X9: =IF(OR(M9="",R9="Unavailable"),"",IF(M9=_xlfn.MINIFS($M$5:$M$604,$E$5:$E$604,E9,$G$5:$G$604,G9,$H$5:$H$604,H9,$R$5:$R$604,"<>Unavailable"),"⭐ Cheapest","")) | Y9: =IF(COUNTIFS($E$5:$E$604,E9,$G$5:$G$604,G9,$J$5:$J$604,"Booking.com")=0,"",_xlfn.MINIFS($M$5:$M$604,$E$5:$E$604,E9,$G$5:$G$604,G9,$J$5:$J$604,"Booking.com")) -> 179 | Z9: =IF(OR(Y9="",M9="",J9="Booking.com"),"",Y9-M9)
A10: 6 | B10: Negombo | C10: 46375 | D10: 1 | E10: The Wallawwa | G10: Walawwa Bedrom (1 King Bed) 35sqmr | H10: BB | I10: 1 | J10: Ottila | K10: INR | L10: 50279 | M10: =IF(L10="","",IFERROR(L10*INDEX(Trip!$E$5:$E$14,MATCH(K10,Trip!$D$5:$D$14,0))/INDEX(Trip!$E$5:$E$14,MATCH(Trip!$B$10,Trip!$D$5:$D$14,0)),"")) -> 533.18134 | N10: =IF(OR(M10="",D10=""),"",M10/D10) -> 533.18134 | O10: =IF(M10="","",M10*I10) -> 533.18134 | P10: 46342 | Q10: =IF(ISNUMBER(P10),P10-TODAY(),IF(P10="","",P10)) -> 40 | R10: Quote | V10: =IF(M10="","",M10*(1+IF(U10="",Trip!$B$11,U10))) -> 613.15854 | W10: =IF(V10="","",V10*I10) -> 613.15854 | X10: =IF(OR(M10="",R10="Unavailable"),"",IF(M10=_xlfn.MINIFS($M$5:$M$604,$E$5:$E$604,E10,$G$5:$G$604,G10,$H$5:$H$604,H10,$R$5:$R$604,"<>Unavailable"),"⭐ Cheapest","")) -> ⭐ Cheapest | Y10: =IF(COUNTIFS($E$5:$E$604,E10,$G$5:$G$604,G10,$J$5:$J$604,"Booking.com")=0,"",_xlfn.MINIFS($M$5:$M$604,$E$5:$E$604,E10,$G$5:$G$604,G10,$J$5:$J$604,"Booking.com")) -> 580 | Z10: =IF(OR(Y10="",M10="",J10="Booking.com"),"",Y10-M10) -> 46.818664
A11: 7 | B11: Negombo | C11: 46375 | D11: 1 | E11: The Wallawwa | G11: Walawwa Bedrom (1 King Bed) 35sqmr | H11: BB | I11: 1 | J11: Booking.com | K11: USD | L11: 580 | M11: =IF(L11="","",IFERROR(L11*INDEX(Trip!$E$5:$E$14,MATCH(K11,Trip!$D$5:$D$14,0))/INDEX(Trip!$E$5:$E$14,MATCH(Trip!$B$10,Trip!$D$5:$D$14,0)),"")) -> 580 | N11: =IF(OR(M11="",D11=""),"",M11/D11) -> 580 | O11: =IF(M11="","",M11*I11) -> 580 | Q11: =IF(ISNUMBER(P11),P11-TODAY(),IF(P11="","",P11)) | R11: Quote | V11: =IF(M11="","",M11*(1+IF(U11="",Trip!$B$11,U11))) -> 667 | W11: =IF(V11="","",V11*I11) -> 667 | X11: =IF(OR(M11="",R11="Unavailable"),"",IF(M11=_xlfn.MINIFS($M$5:$M$604,$E$5:$E$604,E11,$G$5:$G$604,G11,$H$5:$H$604,H11,$R$5:$R$604,"<>Unavailable"),"⭐ Cheapest","")) | Y11: =IF(COUNTIFS($E$5:$E$604,E11,$G$5:$G$604,G11,$J$5:$J$604,"Booking.com")=0,"",_xlfn.MINIFS($M$5:$M$604,$E$5:$E$604,E11,$G$5:$G$604,G11,$J$5:$J$604,"Booking.com")) -> 580 | Z11: =IF(OR(Y11="",M11="",J11="Booking.com"),"",Y11-M11)
A12: 8 | B12: Negombo | C12: 46375 | D12: 1 | E12: Wattura Resort And Spa | G12: Suite With River View (1 King Bed) 72sqmt | H12: BB | I12: 1 | J12: Ottila | K12: INR | L12: 22291 | M12: =IF(L12="","",IFERROR(L12*INDEX(Trip!$E$5:$E$14,MATCH(K12,Trip!$D$5:$D$14,0))/INDEX(Trip!$E$5:$E$14,MATCH(Trip!$B$10,Trip!$D$5:$D$14,0)),"")) -> 236.38388 | N12: =IF(OR(M12="",D12=""),"",M12/D12) -> 236.38388 | O12: =IF(M12="","",M12*I12) -> 236.38388 | P12: 46369 | Q12: =IF(ISNUMBER(P12),P12-TODAY(),IF(P12="","",P12)) -> 67 | R12: Quote | V12: =IF(M12="","",M12*(1+IF(U12="",Trip!$B$11,U12))) -> 271.84146 | W12: =IF(V12="","",V12*I12) -> 271.84146 | X12: =IF(OR(M12="",R12="Unavailable"),"",IF(M12=_xlfn.MINIFS($M$5:$M$604,$E$5:$E$604,E12,$G$5:$G$604,G12,$H$5:$H$604,H12,$R$5:$R$604,"<>Unavailable"),"⭐ Cheapest","")) -> ⭐ Cheapest | Y12: =IF(COUNTIFS($E$5:$E$604,E12,$G$5:$G$604,G12,$J$5:$J$604,"Booking.com")=0,"",_xlfn.MINIFS($M$5:$M$604,$E$5:$E$604,E12,$G$5:$G$604,G12,$J$5:$J$604,"Booking.com")) -> 250 | Z12: =IF(OR(Y12="",M12="",J12="Booking.com"),"",Y12-M12) -> 13.616119
A13: 9 | B13: Negombo | C13: 46375 | D13: 1 | E13: Wattura Resort And Spa | G13: Suite With River View (1 King Bed) 72sqmt | H13: BB | I13: 1 | J13: Booking.com | K13: USD | L13: 250 | M13: =IF(L13="","",IFERROR(L13*INDEX(Trip!$E$5:$E$14,MATCH(K13,Trip!$D$5:$D$14,0))/INDEX(Trip!$E$5:$E$14,MATCH(Trip!$B$10,Trip!$D$5:$D$14,0)),"")) -> 250 | N13: =IF(OR(M13="",D13=""),"",M13/D13) -> 250 | O13: =IF(M13="","",M13*I13) -> 250 | Q13: =IF(ISNUMBER(P13),P13-TODAY(),IF(P13="","",P13)) | R13: Quote | V13: =IF(M13="","",M13*(1+IF(U13="",Trip!$B$11,U13))) -> 287.5 | W13: =IF(V13="","",V13*I13) -> 287.5 | X13: =IF(OR(M13="",R13="Unavailable"),"",IF(M13=_xlfn.MINIFS($M$5:$M$604,$E$5:$E$604,E13,$G$5:$G$604,G13,$H$5:$H$604,H13,$R$5:$R$604,"<>Unavailable"),"⭐ Cheapest","")) | Y13: =IF(COUNTIFS($E$5:$E$604,E13,$G$5:$G$604,G13,$J$5:$J$604,"Booking.com")=0,"",_xlfn.MINIFS($M$5:$M$604,$E$5:$E$604,E13,$G$5:$G$604,G13,$J$5:$J$604,"Booking.com")) -> 250 | Z13: =IF(OR(Y13="",M13="",J13="Booking.com"),"",Y13-M13)
A14: 10 | B14: Negombo | C14: 46375 | D14: 1 | E14: Sentido Heritance Negombo | G14: Deluxe King 40sqmt | H14: BB | I14: 2 | J14: Ottila | K14: INR | L14: 17754 | M14: =IF(L14="","",IFERROR(L14*INDEX(Trip!$E$5:$E$14,MATCH(K14,Trip!$D$5:$D$14,0))/INDEX(Trip!$E$5:$E$14,MATCH(Trip!$B$10,Trip!$D$5:$D$14,0)),"")) -> 188.27147 | N14: =IF(OR(M14="",D14=""),"",M14/D14) -> 188.27147 | O14: =IF(M14="","",M14*I14) -> 376.54295 | P14: 46358 | Q14: =IF(ISNUMBER(P14),P14-TODAY(),IF(P14="","",P14)) -> 56 | R14: Blocked | S14: 101-26160290/1 | U14: 0.2588 | V14: =IF(M14="","",M14*(1+IF(U14="",Trip!$B$11,U14))) -> 236.99613 | W14: =IF(V14="","",V14*I14) -> 473.99226 | X14: =IF(OR(M14="",R14="Unavailable"),"",IF(M14=_xlfn.MINIFS($M$5:$M$604,$E$5:$E$604,E14,$G$5:$G$604,G14,$H$5:$H$604,H14,$R$5:$R$604,"<>Unavailable"),"⭐ Cheapest","")) | Y14: =IF(COUNTIFS($E$5:$E$604,E14,$G$5:$G$604,G14,$J$5:$J$604,"Booking.com")=0,"",_xlfn.MINIFS($M$5:$M$604,$E$5:$E$604,E14,$G$5:$G$604,G14,$J$5:$J$604,"Booking.com")) -> 329 | Z14: =IF(OR(Y14="",M14="",J14="Booking.com"),"",Y14-M14) -> 140.72853 | AA14: Y | AB14: Y | AC14: Y
A15: 11 | B15: Negombo | C15: 46375 | D15: 1 | E15: Sentido Heritance Negombo | G15: Deluxe King 40sqmt | H15: BB | I15: 2 | J15: Booking.com | K15: USD | L15: 329 | M15: =IF(L15="","",IFERROR(L15*INDEX(Trip!$E$5:$E$14,MATCH(K15,Trip!$D$5:$D$14,0))/INDEX(Trip!$E$5:$E$14,MATCH(Trip!$B$10,Trip!$D$5:$D$14,0)),"")) -> 329 | N15: =IF(OR(M15="",D15=""),"",M15/D15) -> 329 | O15: =IF(M15="","",M15*I15) -> 658 | Q15: =IF(ISNUMBER(P15),P15-TODAY(),IF(P15="","",P15)) | R15: Quote | V15: =IF(M15="","",M15*(1+IF(U15="",Trip!$B$11,U15))) -> 378.35 | W15: =IF(V15="","",V15*I15) -> 756.7 | X15: =IF(OR(M15="",R15="Unavailable"),"",IF(M15=_xlfn.MINIFS($M$5:$M$604,$E$5:$E$604,E15,$G$5:$G$604,G15,$H$5:$H$604,H15,$R$5:$R$604,"<>Unavailable"),"⭐ Cheapest","")) | Y15: =IF(COUNTIFS($E$5:$E$604,E15,$G$5:$G$604,G15,$J$5:$J$604,"Booking.com")=0,"",_xlfn.MINIFS($M$5:$M$604,$E$5:$E$604,E15,$G$5:$G$604,G15,$J$5:$J$604,"Booking.com")) -> 329 | Z15: =IF(OR(Y15="",M15="",J15="Booking.com"),"",Y15-M15)
A16: 12 | B16: Negombo | C16: 46375 | D16: 1 | E16: Sentido Heritance Negombo | G16: Deluxe King 40sqmt | H16: BB | I16: 1 | J16: Ottila | K16: INR | L16: 17189 | M16: =IF(L16="","",IFERROR(L16*INDEX(Trip!$E$5:$E$14,MATCH(K16,Trip!$D$5:$D$14,0))/INDEX(Trip!$E$5:$E$14,MATCH(Trip!$B$10,Trip!$D$5:$D$14,0)),"")) -> 182.27996 | N16: =IF(OR(M16="",D16=""),"",M16/D16) -> 182.27996 | O16: =IF(M16="","",M16*I16) -> 182.27996 | P16: 46369 | Q16: =IF(ISNUMBER(P16),P16-TODAY(),IF(P16="","",P16)) -> 67 | R16: Blocked | S16: 101-26160603/1 | V16: =IF(M16="","",M16*(1+IF(U16="",Trip!$B$11,U16))) -> 209.62195 | W16: =IF(V16="","",V16*I16) -> 209.62195 | X16: =IF(OR(M16="",R16="Unavailable"),"",IF(M16=_xlfn.MINIFS($M$5:$M$604,$E$5:$E$604,E16,$G$5:$G$604,G16,$H$5:$H$604,H16,$R$5:$R$604,"<>Unavailable"),"⭐ Cheapest","")) -> ⭐ Cheapest | Y16: =IF(COUNTIFS($E$5:$E$604,E16,$G$5:$G$604,G16,$J$5:$J$604,"Booking.com")=0,"",_xlfn.MINIFS($M$5:$M$604,$E$5:$E$604,E16,$G$5:$G$604,G16,$J$5:$J$604,"Booking.com")) -> 329 | Z16: =IF(OR(Y16="",M16="",J16="Booking.com"),"",Y16-M16) -> 146.72004
A17: 13 | B17: Negombo | C17: 46375 | D17: 1 | E17: Jetwing Blue | G17: TWIN DELUXE SEA VIEW( 2 Adults ) 59sqmt | H17: BB | I17: 1 | J17: Ottila | K17: INR | L17: 16050 | M17: =IF(L17="","",IFERROR(L17*INDEX(Trip!$E$5:$E$14,MATCH(K17,Trip!$D$5:$D$14,0))/INDEX(Trip!$E$5:$E$14,MATCH(Trip!$B$10,Trip!$D$5:$D$14,0)),"")) -> 170.20148 | N17: =IF(OR(M17="",D17=""),"",M17/D17) -> 170.20148 | O17: =IF(M17="","",M17*I17) -> 170.20148 | Q17: =IF(ISNUMBER(P17),P17-TODAY(),IF(P17="","",P17)) | R17: Quote | V17: =IF(M17="","",M17*(1+IF(U17="",Trip!$B$11,U17))) -> 195.73171 | W17: =IF(V17="","",V17*I17) -> 195.73171 | X17: =IF(OR(M17="",R17="Unavailable"),"",IF(M17=_xlfn.MINIFS($M$5:$M$604,$E$5:$E$604,E17,$G$5:$G$604,G17,$H$5:$H$604,H17,$R$5:$R$604,"<>Unavailable"),"⭐ Cheapest","")) -> ⭐ Cheapest | Y17: =IF(COUNTIFS($E$5:$E$604,E17,$G$5:$G$604,G17,$J$5:$J$604,"Booking.com")=0,"",_xlfn.MINIFS($M$5:$M$604,$E$5:$E$604,E17,$G$5:$G$604,G17,$J$5:$J$604,"Booking.com")) | Z17: =IF(OR(Y17="",M17="",J17="Booking.com"),"",Y17-M17)
A18: 14 | B18: Dambulla / Sigiriya | C18: 46376 | D18: 2 | E18: Habarana Village By Cinnamon | F18: 4 | G18: Superior Room 30m2 | H18: BB | I18: 1 | J18: Ottila | K18: INR | L18: 25708 | M18: =IF(L18="","",IFERROR(L18*INDEX(Trip!$E$5:$E$14,MATCH(K18,Trip!$D$5:$D$14,0))/INDEX(Trip!$E$5:$E$14,MATCH(Trip!$B$10,Trip!$D$5:$D$14,0)),"")) -> 272.6193 | N18: =IF(OR(M18="",D18=""),"",M18/D18) -> 136.30965 | O18: =IF(M18="","",M18*I18) -> 272.6193 | P18: 46358 | Q18: =IF(ISNUMBER(P18),P18-TODAY(),IF(P18="","",P18)) -> 56 | R18: Quote | T18: Base | V18: =IF(M18="","",M18*(1+IF(U18="",Trip!$B$11,U18))) -> 313.5122 | W18: =IF(V18="","",V18*I18) -> 313.5122 | X18: =IF(OR(M18="",R18="Unavailable"),"",IF(M18=_xlfn.MINIFS($M$5:$M$604,$E$5:$E$604,E18,$G$5:$G$604,G18,$H$5:$H$604,H18,$R$5:$R$604,"<>Unavailable"),"⭐ Cheapest","")) -> ⭐ Cheapest | Y18: =IF(COUNTIFS($E$5:$E$604,E18,$G$5:$G$604,G18,$J$5:$J$604,"Booking.com")=0,"",_xlfn.MINIFS($M$5:$M$604,$E$5:$E$604,E18,$G$5:$G$604,G18,$J$5:$J$604,"Booking.com")) -> 347.40191 | Z18: =IF(OR(Y18="",M18="",J18="Booking.com"),"",Y18-M18) -> 74.782609
A19: 15 | B19: Dambulla / Sigiriya | C19: 46376 | D19: 2 | E19: Habarana Village By Cinnamon | F19: 4 | G19: Superior Room 30m2 | H19: BB | I19: 1 | J19: Booking.com | K19: INR | L19: 32760 | M19: =IF(L19="","",IFERROR(L19*INDEX(Trip!$E$5:$E$14,MATCH(K19,Trip!$D$5:$D$14,0))/INDEX(Trip!$E$5:$E$14,MATCH(Trip!$B$10,Trip!$D$5:$D$14,0)),"")) -> 347.40191 | N19: =IF(OR(M19="",D19=""),"",M19/D19) -> 173.70095 | O19: =IF(M19="","",M19*I19) -> 347.40191 | P19: 46368 | Q19: =IF(ISNUMBER(P19),P19-TODAY(),IF(P19="","",P19)) -> 66 | R19: Quote | V19: =IF(M19="","",M19*(1+IF(U19="",Trip!$B$11,U19))) -> 399.5122 | W19: =IF(V19="","",V19*I19) -> 399.5122 | X19: =IF(OR(M19="",R19="Unavailable"),"",IF(M19=_xlfn.MINIFS($M$5:$M$604,$E$5:$E$604,E19,$G$5:$G$604,G19,$H$5:$H$604,H19,$R$5:$R$604,"<>Unavailable"),"⭐ Cheapest","")) | Y19: =IF(COUNTIFS($E$5:$E$604,E19,$G$5:$G$604,G19,$J$5:$J$604,"Booking.com")=0,"",_xlfn.MINIFS($M$5:$M$604,$E$5:$E$604,E19,$G$5:$G$604,G19,$J$5:$J$604,"Booking.com")) -> 347.40191 | Z19: =IF(OR(Y19="",M19="",J19="Booking.com"),"",Y19-M19)
A20: 16 | B20: Dambulla / Sigiriya | C20: 46376 | D20: 2 | E20: Sigiriya Jungles Resort & Spa | G20: Deluxe room | H20: BB | I20: 1 | J20: Ottila | K20: INR | L20: 39204.2 | M20: =IF(L20="","",IFERROR(L20*INDEX(Trip!$E$5:$E$14,MATCH(K20,Trip!$D$5:$D$14,0))/INDEX(Trip!$E$5:$E$14,MATCH(Trip!$B$10,Trip!$D$5:$D$14,0)),"")) -> 415.73913 | N20: =IF(OR(M20="",D20=""),"",M20/D20) -> 207.86957 | O20: =IF(M20="","",M20*I20) -> 415.73913 | P20: 46365 | Q20: =IF(ISNUMBER(P20),P20-TODAY(),IF(P20="","",P20)) -> 63 | R20: Blocked | S20: 101-26157689/1 | U20: 0.0006 | V20: =IF(M20="","",M20*(1+IF(U20="",Trip!$B$11,U20))) -> 415.98857 | W20: =IF(V20="","",V20*I20) -> 415.98857 | X20: =IF(OR(M20="",R20="Unavailable"),"",IF(M20=_xlfn.MINIFS($M$5:$M$604,$E$5:$E$604,E20,$G$5:$G$604,G20,$H$5:$H$604,H20,$R$5:$R$604,"<>Unavailable"),"⭐ Cheapest","")) -> ⭐ Cheapest | Y20: =IF(COUNTIFS($E$5:$E$604,E20,$G$5:$G$604,G20,$J$5:$J$604,"Booking.com")=0,"",_xlfn.MINIFS($M$5:$M$604,$E$5:$E$604,E20,$G$5:$G$604,G20,$J$5:$J$604,"Booking.com")) | Z20: =IF(OR(Y20="",M20="",J20="Booking.com"),"",Y20-M20) | AA20: Y | AB20: Y | AC20: Y
A21: 17 | B21: Dambulla / Sigiriya | C21: 46376 | D21: 2 | E21: Sigiriya Jungles Resort & Spa | G21: Deluxe room | H21: BB | I21: 1 | J21: Hotel website | K21: USD | L21: 416 | M21: =IF(L21="","",IFERROR(L21*INDEX(Trip!$E$5:$E$14,MATCH(K21,Trip!$D$5:$D$14,0))/INDEX(Trip!$E$5:$E$14,MATCH(Trip!$B$10,Trip!$D$5:$D$14,0)),"")) -> 416 | N21: =IF(OR(M21="",D21=""),"",M21/D21) -> 208 | O21: =IF(M21="","",M21*I21) -> 416 | Q21: =IF(ISNUMBER(P21),P21-TODAY(),IF(P21="","",P21)) | R21: Quote | V21: =IF(M21="","",M21*(1+IF(U21="",Trip!$B$11,U21))) -> 478.4 | W21: =IF(V21="","",V21*I21) -> 478.4 | X21: =IF(OR(M21="",R21="Unavailable"),"",IF(M21=_xlfn.MINIFS($M$5:$M$604,$E$5:$E$604,E21,$G$5:$G$604,G21,$H$5:$H$604,H21,$R$5:$R$604,"<>Unavailable"),"⭐ Cheapest","")) | Y21: =IF(COUNTIFS($E$5:$E$604,E21,$G$5:$G$604,G21,$J$5:$J$604,"Booking.com")=0,"",_xlfn.MINIFS($M$5:$M$604,$E$5:$E$604,E21,$G$5:$G$604,G21,$J$5:$J$604,"Booking.com")) | Z21: =IF(OR(Y21="",M21="",J21="Booking.com"),"",Y21-M21)
A22: 18 | B22: Dambulla / Sigiriya | C22: 46376 | D22: 2 | E22: Cinnamon Lodge -Habarana | F22: 5 | G22: Superior room | H22: HB | I22: 1 | J22: BTR | K22: USD | L22: 340 | M22: =IF(L22="","",IFERROR(L22*INDEX(Trip!$E$5:$E$14,MATCH(K22,Trip!$D$5:$D$14,0))/INDEX(Trip!$E$5:$E$14,MATCH(Trip!$B$10,Trip!$D$5:$D$14,0)),"")) -> 340 | N22: =IF(OR(M22="",D22=""),"",M22/D22) -> 170 | O22: =IF(M22="","",M22*I22) -> 340 | Q22: =IF(ISNUMBER(P22),P22-TODAY(),IF(P22="","",P22)) | R22: Quote | T22: Upg 2 | V22: =IF(M22="","",M22*(1+IF(U22="",Trip!$B$11,U22))) -> 391 | W22: =IF(V22="","",V22*I22) -> 391 | X22: =IF(OR(M22="",R22="Unavailable"),"",IF(M22=_xlfn.MINIFS($M$5:$M$604,$E$5:$E$604,E22,$G$5:$G$604,G22,$H$5:$H$604,H22,$R$5:$R$604,"<>Unavailable"),"⭐ Cheapest","")) -> ⭐ Cheapest | Y22: =IF(COUNTIFS($E$5:$E$604,E22,$G$5:$G$604,G22,$J$5:$J$604,"Booking.com")=0,"",_xlfn.MINIFS($M$5:$M$604,$E$5:$E$604,E22,$G$5:$G$604,G22,$J$5:$J$604,"Booking.com")) -> 438.17603 | Z22: =IF(OR(Y22="",M22="",J22="Booking.com"),"",Y22-M22) -> 98.176034
A23: 19 | B23: Dambulla / Sigiriya | C23: 46376 | D23: 2 | E23: Cinnamon Lodge -Habarana | F23: 5 | G23: Superior room | H23: HB | I23: 1 | J23: Booking.com | K23: INR | L23: 41320 | M23: =IF(L23="","",IFERROR(L23*INDEX(Trip!$E$5:$E$14,MATCH(K23,Trip!$D$5:$D$14,0))/INDEX(Trip!$E$5:$E$14,MATCH(Trip!$B$10,Trip!$D$5:$D$14,0)),"")) -> 438.17603 | N23: =IF(OR(M23="",D23=""),"",M23/D23) -> 219.08802 | O23: =IF(M23="","",M23*I23) -> 438.17603 | P23: 46368 | Q23: =IF(ISNUMBER(P23),P23-TODAY(),IF(P23="","",P23)) -> 66 | R23: Quote | V23: =IF(M23="","",M23*(1+IF(U23="",Trip!$B$11,U23))) -> 503.90244 | W23: =IF(V23="","",V23*I23) -> 503.90244 | X23: =IF(OR(M23="",R23="Unavailable"),"",IF(M23=_xlfn.MINIFS($M$5:$M$604,$E$5:$E$604,E23,$G$5:$G$604,G23,$H$5:$H$604,H23,$R$5:$R$604,"<>Unavailable"),"⭐ Cheapest","")) | Y23: =IF(COUNTIFS($E$5:$E$604,E23,$G$5:$G$604,G23,$J$5:$J$604,"Booking.com")=0,"",_xlfn.MINIFS($M$5:$M$604,$E$5:$E$604,E23,$G$5:$G$604,G23,$J$5:$J$604,"Booking.com")) -> 438.17603 | Z23: =IF(OR(Y23="",M23="",J23="Booking.com"),"",Y23-M23)
A24: 20 | B24: Dambulla / Sigiriya | C24: 46376 | D24: 2 | E24: EKHO Sigiriya | G24: Deluxe Room 22 SQM | H24: BB | I24: 1 | J24: Ottila | K24: INR | L24: 26817 | M24: =IF(L24="","",IFERROR(L24*INDEX(Trip!$E$5:$E$14,MATCH(K24,Trip!$D$5:$D$14,0))/INDEX(Trip!$E$5:$E$14,MATCH(Trip!$B$10,Trip!$D$5:$D$14,0)),"")) -> 284.37964 | N24: =IF(OR(M24="",D24=""),"",M24/D24) -> 142.18982 | O24: =IF(M24="","",M24*I24) -> 284.37964 | P24: 46362 | Q24: =IF(ISNUMBER(P24),P24-TODAY(),IF(P24="","",P24)) -> 60 | R24: Quote | T24: Upg 3 | V24: =IF(M24="","",M24*(1+IF(U24="",Trip!$B$11,U24))) -> 327.03659 | W24: =IF(V24="","",V24*I24) -> 327.03659 | X24: =IF(OR(M24="",R24="Unavailable"),"",IF(M24=_xlfn.MINIFS($M$5:$M$604,$E$5:$E$604,E24,$G$5:$G$604,G24,$H$5:$H$604,H24,$R$5:$R$604,"<>Unavailable"),"⭐ Cheapest","")) -> ⭐ Cheapest | Y24: =IF(COUNTIFS($E$5:$E$604,E24,$G$5:$G$604,G24,$J$5:$J$604,"Booking.com")=0,"",_xlfn.MINIFS($M$5:$M$604,$E$5:$E$604,E24,$G$5:$G$604,G24,$J$5:$J$604,"Booking.com")) | Z24: =IF(OR(Y24="",M24="",J24="Booking.com"),"",Y24-M24)
A25: 21 | B25: Dambulla / Sigiriya | C25: 46376 | D25: 2 | E25: EKHO Sigiriya | G25: suite room | H25: HB | I25: 1 | J25: Direct | K25: INR | L25: 49108 | M25: =IF(L25="","",IFERROR(L25*INDEX(Trip!$E$5:$E$14,MATCH(K25,Trip!$D$5:$D$14,0))/INDEX(Trip!$E$5:$E$14,MATCH(Trip!$B$10,Trip!$D$5:$D$14,0)),"")) -> 520.76352 | N25: =IF(OR(M25="",D25=""),"",M25/D25) -> 260.38176 | O25: =IF(M25="","",M25*I25) -> 520.76352 | P25: 46372 | Q25: =IF(ISNUMBER(P25),P25-TODAY(),IF(P25="","",P25)) -> 70 | R25: Quote | V25: =IF(M25="","",M25*(1+IF(U25="",Trip!$B$11,U25))) -> 598.87805 | W25: =IF(V25="","",V25*I25) -> 598.87805 | X25: =IF(OR(M25="",R25="Unavailable"),"",IF(M25=_xlfn.MINIFS($M$5:$M$604,$E$5:$E$604,E25,$G$5:$G$604,G25,$H$5:$H$604,H25,$R$5:$R$604,"<>Unavailable"),"⭐ Cheapest","")) -> ⭐ Cheapest | Y25: =IF(COUNTIFS($E$5:$E$604,E25,$G$5:$G$604,G25,$J$5:$J$604,"Booking.com")=0,"",_xlfn.MINIFS($M$5:$M$604,$E$5:$E$604,E25,$G$5:$G$604,G25,$J$5:$J$604,"Booking.com")) | Z25: =IF(OR(Y25="",M25="",J25="Booking.com"),"",Y25-M25)
A26: 22 | B26: Kandy | C26: 46378 | D26: 1 | E26: Amaya Hills Kandy | G26: Deluxe Room 21-22sqm | H26: BB | I26: 1 | J26: Ottila | K26: INR | L26: 23563 | M26: =IF(L26="","",IFERROR(L26*INDEX(Trip!$E$5:$E$14,MATCH(K26,Trip!$D$5:$D$14,0))/INDEX(Trip!$E$5:$E$14,MATCH(Trip!$B$10,Trip!$D$5:$D$14,0)),"")) -> 249.87275 | N26: =IF(OR(M26="",D26=""),"",M26/D26) -> 249.87275 | O26: =IF(M26="","",M26*I26) -> 249.87275 | P26: 46367 | Q26: =IF(ISNUMBER(P26),P26-TODAY(),IF(P26="","",P26)) -> 65 | R26: Quote | T26: Base | V26: =IF(M26="","",M26*(1+IF(U26="",Trip!$B$11,U26))) -> 287.35366 | W26: =IF(V26="","",V26*I26) -> 287.35366 | X26: =IF(OR(M26="",R26="Unavailable"),"",IF(M26=_xlfn.MINIFS($M$5:$M$604,$E$5:$E$604,E26,$G$5:$G$604,G26,$H$5:$H$604,H26,$R$5:$R$604,"<>Unavailable"),"⭐ Cheapest","")) -> ⭐ Cheapest | Y26: =IF(COUNTIFS($E$5:$E$604,E26,$G$5:$G$604,G26,$J$5:$J$604,"Booking.com")=0,"",_xlfn.MINIFS($M$5:$M$604,$E$5:$E$604,E26,$G$5:$G$604,G26,$J$5:$J$604,"Booking.com")) -> 325 | Z26: =IF(OR(Y26="",M26="",J26="Booking.com"),"",Y26-M26) -> 75.127253
A27: 23 | B27: Kandy | C27: 46378 | D27: 1 | E27: Amaya Hills Kandy | G27: Deluxe Room 21-22sqm | H27: BB | I27: 1 | J27: Booking.com | K27: USD | L27: 325 | M27: =IF(L27="","",IFERROR(L27*INDEX(Trip!$E$5:$E$14,MATCH(K27,Trip!$D$5:$D$14,0))/INDEX(Trip!$E$5:$E$14,MATCH(Trip!$B$10,Trip!$D$5:$D$14,0)),"")) -> 325 | N27: =IF(OR(M27="",D27=""),"",M27/D27) -> 325 | O27: =IF(M27="","",M27*I27) -> 325 | P27: 46370 | Q27: =IF(ISNUMBER(P27),P27-TODAY(),IF(P27="","",P27)) -> 68 | R27: Quote | V27: =IF(M27="","",M27*(1+IF(U27="",Trip!$B$11,U27))) -> 373.75 | W27: =IF(V27="","",V27*I27) -> 373.75 | X27: =IF(OR(M27="",R27="Unavailable"),"",IF(M27=_xlfn.MINIFS($M$5:$M$604,$E$5:$E$604,E27,$G$5:$G$604,G27,$H$5:$H$604,H27,$R$5:$R$604,"<>Unavailable"),"⭐ Cheapest","")) | Y27: =IF(COUNTIFS($E$5:$E$604,E27,$G$5:$G$604,G27,$J$5:$J$604,"Booking.com")=0,"",_xlfn.MINIFS($M$5:$M$604,$E$5:$E$604,E27,$G$5:$G$604,G27,$J$5:$J$604,"Booking.com")) -> 325 | Z27: =IF(OR(Y27="",M27="",J27="Booking.com"),"",Y27-M27)
A28: 24 | B28: Kandy | C28: 46378 | D28: 1 | E28: Santani Wellness Kandy | F28: 5 | G28: Chalet, Garden View DBL | H28: AI | I28: 1 | J28: Ottila | K28: INR | L28: 105906 | M28: =IF(L28="","",IFERROR(L28*INDEX(Trip!$E$5:$E$14,MATCH(K28,Trip!$D$5:$D$14,0))/INDEX(Trip!$E$5:$E$14,MATCH(Trip!$B$10,Trip!$D$5:$D$14,0)),"")) -> 1123.0753 | N28: =IF(OR(M28="",D28=""),"",M28/D28) -> 1123.0753 | O28: =IF(M28="","",M28*I28) -> 1123.0753 | P28: 46345 | Q28: =IF(ISNUMBER(P28),P28-TODAY(),IF(P28="","",P28)) -> 43 | R28: Quote | T28: Upg 3 | V28: =IF(M28="","",M28*(1+IF(U28="",Trip!$B$11,U28))) -> 1291.5366 | W28: =IF(V28="","",V28*I28) -> 1291.5366 | X28: =IF(OR(M28="",R28="Unavailable"),"",IF(M28=_xlfn.MINIFS($M$5:$M$604,$E$5:$E$604,E28,$G$5:$G$604,G28,$H$5:$H$604,H28,$R$5:$R$604,"<>Unavailable"),"⭐ Cheapest","")) -> ⭐ Cheapest | Y28: =IF(COUNTIFS($E$5:$E$604,E28,$G$5:$G$604,G28,$J$5:$J$604,"Booking.com")=0,"",_xlfn.MINIFS($M$5:$M$604,$E$5:$E$604,E28,$G$5:$G$604,G28,$J$5:$J$604,"Booking.com")) | Z28: =IF(OR(Y28="",M28="",J28="Booking.com"),"",Y28-M28)
A29: 25 | B29: Kandy | C29: 46378 | D29: 1 | E29: Santani Wellness Kandy | F29: 5 | G29: Chalet, Garden View SGL | H29: AI | I29: 1 | J29: Ottila | K29: INR | L29: 80156 | M29: =IF(L29="","",IFERROR(L29*INDEX(Trip!$E$5:$E$14,MATCH(K29,Trip!$D$5:$D$14,0))/INDEX(Trip!$E$5:$E$14,MATCH(Trip!$B$10,Trip!$D$5:$D$14,0)),"")) -> 850.0106 | N29: =IF(OR(M29="",D29=""),"",M29/D29) -> 850.0106 | O29: =IF(M29="","",M29*I29) -> 850.0106 | P29: 46345 | Q29: =IF(ISNUMBER(P29),P29-TODAY(),IF(P29="","",P29)) -> 43 | R29: Quote | T29: Upg 3 | V29: =IF(M29="","",M29*(1+IF(U29="",Trip!$B$11,U29))) -> 977.5122 | W29: =IF(V29="","",V29*I29) -> 977.5122 | X29: =IF(OR(M29="",R29="Unavailable"),"",IF(M29=_xlfn.MINIFS($M$5:$M$604,$E$5:$E$604,E29,$G$5:$G$604,G29,$H$5:$H$604,H29,$R$5:$R$604,"<>Unavailable"),"⭐ Cheapest","")) -> ⭐ Cheapest | Y29: =IF(COUNTIFS($E$5:$E$604,E29,$G$5:$G$604,G29,$J$5:$J$604,"Booking.com")=0,"",_xlfn.MINIFS($M$5:$M$604,$E$5:$E$604,E29,$G$5:$G$604,G29,$J$5:$J$604,"Booking.com")) | Z29: =IF(OR(Y29="",M29="",J29="Booking.com"),"",Y29-M29)
A30: 26 | B30: Kandy | C30: 46378 | D30: 1 | E30: W15 Hanthana Estate Kandy | F30: 5 | G30: Deluxe Room, 1 King Bed (1 King Bed) DBL/SGL 30sqm | H30: AI | I30: 1 | J30: Ottila | K30: INR | L30: 171688 | M30: =IF(L30="","",IFERROR(L30*INDEX(Trip!$E$5:$E$14,MATCH(K30,Trip!$D$5:$D$14,0))/INDEX(Trip!$E$5:$E$14,MATCH(Trip!$B$10,Trip!$D$5:$D$14,0)),"")) -> 1820.6575 | N30: =IF(OR(M30="",D30=""),"",M30/D30) -> 1820.6575 | O30: =IF(M30="","",M30*I30) -> 1820.6575 | P30: 46346 | Q30: =IF(ISNUMBER(P30),P30-TODAY(),IF(P30="","",P30)) -> 44 | R30: Quote | T30: Upg 4 | V30: =IF(M30="","",M30*(1+IF(U30="",Trip!$B$11,U30))) -> 2093.7561 | W30: =IF(V30="","",V30*I30) -> 2093.7561 | X30: =IF(OR(M30="",R30="Unavailable"),"",IF(M30=_xlfn.MINIFS($M$5:$M$604,$E$5:$E$604,E30,$G$5:$G$604,G30,$H$5:$H$604,H30,$R$5:$R$604,"<>Unavailable"),"⭐ Cheapest","")) -> ⭐ Cheapest | Y30: =IF(COUNTIFS($E$5:$E$604,E30,$G$5:$G$604,G30,$J$5:$J$604,"Booking.com")=0,"",_xlfn.MINIFS($M$5:$M$604,$E$5:$E$604,E30,$G$5:$G$604,G30,$J$5:$J$604,"Booking.com")) -> 1307.0732 | Z30: =IF(OR(Y30="",M30="",J30="Booking.com"),"",Y30-M30) -> -513.58431
A31: 27 | B31: Kandy | C31: 46378 | D31: 1 | E31: W15 Hanthana Estate Kandy | F31: 5 | G31: Deluxe Room, 1 King Bed (1 King Bed) DBL/SGL 30sqm | H31: BB | I31: 1 | J31: Booking.com | K31: INR | L31: 123257 | M31: =IF(L31="","",IFERROR(L31*INDEX(Trip!$E$5:$E$14,MATCH(K31,Trip!$D$5:$D$14,0))/INDEX(Trip!$E$5:$E$14,MATCH(Trip!$B$10,Trip!$D$5:$D$14,0)),"")) -> 1307.0732 | N31: =IF(OR(M31="",D31=""),"",M31/D31) -> 1307.0732 | O31: =IF(M31="","",M31*I31) -> 1307.0732 | P31: 46347 | Q31: =IF(ISNUMBER(P31),P31-TODAY(),IF(P31="","",P31)) -> 45 | R31: Quote | V31: =IF(M31="","",M31*(1+IF(U31="",Trip!$B$11,U31))) -> 1503.1341 | W31: =IF(V31="","",V31*I31) -> 1503.1341 | X31: =IF(OR(M31="",R31="Unavailable"),"",IF(M31=_xlfn.MINIFS($M$5:$M$604,$E$5:$E$604,E31,$G$5:$G$604,G31,$H$5:$H$604,H31,$R$5:$R$604,"<>Unavailable"),"⭐ Cheapest","")) -> ⭐ Cheapest | Y31: =IF(COUNTIFS($E$5:$E$604,E31,$G$5:$G$604,G31,$J$5:$J$604,"Booking.com")=0,"",_xlfn.MINIFS($M$5:$M$604,$E$5:$E$604,E31,$G$5:$G$604,G31,$J$5:$J$604,"Booking.com")) -> 1307.0732 | Z31: =IF(OR(Y31="",M31="",J31="Booking.com"),"",Y31-M31)
A32: 28 | B32: Kandy | C32: 46378 | D32: 1 | E32: Taru Villas | G32: Deluxe Room DBL/SGL 27sqm | H32: BB | I32: 1 | J32: Ottila | K32: INR | L32: 40298 | M32: =IF(L32="","",IFERROR(L32*INDEX(Trip!$E$5:$E$14,MATCH(K32,Trip!$D$5:$D$14,0))/INDEX(Trip!$E$5:$E$14,MATCH(Trip!$B$10,Trip!$D$5:$D$14,0)),"")) -> 427.33828 | N32: =IF(OR(M32="",D32=""),"",M32/D32) -> 427.33828 | O32: =IF(M32="","",M32*I32) -> 427.33828 | P32: 46314 | Q32: =IF(ISNUMBER(P32),P32-TODAY(),IF(P32="","",P32)) -> 12 | R32: Quote | V32: =IF(M32="","",M32*(1+IF(U32="",Trip!$B$11,U32))) -> 491.43902 | W32: =IF(V32="","",V32*I32) -> 491.43902 | X32: =IF(OR(M32="",R32="Unavailable"),"",IF(M32=_xlfn.MINIFS($M$5:$M$604,$E$5:$E$604,E32,$G$5:$G$604,G32,$H$5:$H$604,H32,$R$5:$R$604,"<>Unavailable"),"⭐ Cheapest","")) -> ⭐ Cheapest | Y32: =IF(COUNTIFS($E$5:$E$604,E32,$G$5:$G$604,G32,$J$5:$J$604,"Booking.com")=0,"",_xlfn.MINIFS($M$5:$M$604,$E$5:$E$604,E32,$G$5:$G$604,G32,$J$5:$J$604,"Booking.com")) -> 368.8017 | Z32: =IF(OR(Y32="",M32="",J32="Booking.com"),"",Y32-M32) -> -58.536585
A33: 29 | B33: Kandy | C33: 46378 | D33: 1 | E33: Taru Villas | G33: Deluxe Room DBL/SGL 27sqm | H33: HB | I33: 1 | J33: Booking.com | K33: INR | L33: 38486 | M33: =IF(L33="","",IFERROR(L33*INDEX(Trip!$E$5:$E$14,MATCH(K33,Trip!$D$5:$D$14,0))/INDEX(Trip!$E$5:$E$14,MATCH(Trip!$B$10,Trip!$D$5:$D$14,0)),"")) -> 408.12301 | N33: =IF(OR(M33="",D33=""),"",M33/D33) -> 408.12301 | O33: =IF(M33="","",M33*I33) -> 408.12301 | P33: 46317 | Q33: =IF(ISNUMBER(P33),P33-TODAY(),IF(P33="","",P33)) -> 15 | R33: Quote | V33: =IF(M33="","",M33*(1+IF(U33="",Trip!$B$11,U33))) -> 469.34146 | W33: =IF(V33="","",V33*I33) -> 469.34146 | X33: =IF(OR(M33="",R33="Unavailable"),"",IF(M33=_xlfn.MINIFS($M$5:$M$604,$E$5:$E$604,E33,$G$5:$G$604,G33,$H$5:$H$604,H33,$R$5:$R$604,"<>Unavailable"),"⭐ Cheapest","")) | Y33: =IF(COUNTIFS($E$5:$E$604,E33,$G$5:$G$604,G33,$J$5:$J$604,"Booking.com")=0,"",_xlfn.MINIFS($M$5:$M$604,$E$5:$E$604,E33,$G$5:$G$604,G33,$J$5:$J$604,"Booking.com")) -> 368.8017 | Z33: =IF(OR(Y33="",M33="",J33="Booking.com"),"",Y33-M33)
A34: 30 | B34: Kandy | C34: 46378 | D34: 1 | E34: Taru Villas | G34: Deluxe Room DBL/SGL 27sqm | H34: HB | I34: 1 | J34: Ottila | K34: INR | L34: 33071 | M34: =IF(L34="","",IFERROR(L34*INDEX(Trip!$E$5:$E$14,MATCH(K34,Trip!$D$5:$D$14,0))/INDEX(Trip!$E$5:$E$14,MATCH(Trip!$B$10,Trip!$D$5:$D$14,0)),"")) -> 350.69989 | N34: =IF(OR(M34="",D34=""),"",M34/D34) -> 350.69989 | O34: =IF(M34="","",M34*I34) -> 350.69989 | P34: 46314 | Q34: =IF(ISNUMBER(P34),P34-TODAY(),IF(P34="","",P34)) -> 12 | R34: Blocked | S34: 101-26161087/1 | U34: 0.1149 | V34: =IF(M34="","",M34*(1+IF(U34="",Trip!$B$11,U34))) -> 390.99531 | W34: =IF(V34="","",V34*I34) -> 390.99531 | X34: =IF(OR(M34="",R34="Unavailable"),"",IF(M34=_xlfn.MINIFS($M$5:$M$604,$E$5:$E$604,E34,$G$5:$G$604,G34,$H$5:$H$604,H34,$R$5:$R$604,"<>Unavailable"),"⭐ Cheapest","")) -> ⭐ Cheapest | Y34: =IF(COUNTIFS($E$5:$E$604,E34,$G$5:$G$604,G34,$J$5:$J$604,"Booking.com")=0,"",_xlfn.MINIFS($M$5:$M$604,$E$5:$E$604,E34,$G$5:$G$604,G34,$J$5:$J$604,"Booking.com")) -> 368.8017 | Z34: =IF(OR(Y34="",M34="",J34="Booking.com"),"",Y34-M34) -> 18.101803 | AD34: 2 room on this price
A35: 31 | B35: Kandy | C35: 46378 | D35: 1 | E35: Taru Villas | G35: Deluxe Room DBL/SGL 27sqm | H35: HB | I35: 1 | J35: Booking.com | K35: INR | L35: 34778 | M35: =IF(L35="","",IFERROR(L35*INDEX(Trip!$E$5:$E$14,MATCH(K35,Trip!$D$5:$D$14,0))/INDEX(Trip!$E$5:$E$14,MATCH(Trip!$B$10,Trip!$D$5:$D$14,0)),"")) -> 368.8017 | N35: =IF(OR(M35="",D35=""),"",M35/D35) -> 368.8017 | O35: =IF(M35="","",M35*I35) -> 368.8017 | P35: 46317 | Q35: =IF(ISNUMBER(P35),P35-TODAY(),IF(P35="","",P35)) -> 15 | R35: Quote | V35: =IF(M35="","",M35*(1+IF(U35="",Trip!$B$11,U35))) -> 424.12195 | W35: =IF(V35="","",V35*I35) -> 424.12195 | X35: =IF(OR(M35="",R35="Unavailable"),"",IF(M35=_xlfn.MINIFS($M$5:$M$604,$E$5:$E$604,E35,$G$5:$G$604,G35,$H$5:$H$604,H35,$R$5:$R$604,"<>Unavailable"),"⭐ Cheapest","")) | Y35: =IF(COUNTIFS($E$5:$E$604,E35,$G$5:$G$604,G35,$J$5:$J$604,"Booking.com")=0,"",_xlfn.MINIFS($M$5:$M$604,$E$5:$E$604,E35,$G$5:$G$604,G35,$J$5:$J$604,"Booking.com")) -> 368.8017 | Z35: =IF(OR(Y35="",M35="",J35="Booking.com"),"",Y35-M35)
A36: 32 | B36: Kandy | C36: 46378 | D36: 1 | E36: Taru Villas | G36: Superior Double Room SGL 27sqm | H36: HB | I36: 1 | J36: Ottila | K36: INR | L36: 34480 | M36: =IF(L36="","",IFERROR(L36*INDEX(Trip!$E$5:$E$14,MATCH(K36,Trip!$D$5:$D$14,0))/INDEX(Trip!$E$5:$E$14,MATCH(Trip!$B$10,Trip!$D$5:$D$14,0)),"")) -> 365.64157 | N36: =IF(OR(M36="",D36=""),"",M36/D36) -> 365.64157 | O36: =IF(M36="","",M36*I36) -> 365.64157 | P36: 46314 | Q36: =IF(ISNUMBER(P36),P36-TODAY(),IF(P36="","",P36)) -> 12 | R36: Blocked | S36: 101-26161095/1 | V36: =IF(M36="","",M36*(1+IF(U36="",Trip!$B$11,U36))) -> 420.4878 | W36: =IF(V36="","",V36*I36) -> 420.4878 | X36: =IF(OR(M36="",R36="Unavailable"),"",IF(M36=_xlfn.MINIFS($M$5:$M$604,$E$5:$E$604,E36,$G$5:$G$604,G36,$H$5:$H$604,H36,$R$5:$R$604,"<>Unavailable"),"⭐ Cheapest","")) -> ⭐ Cheapest | Y36: =IF(COUNTIFS($E$5:$E$604,E36,$G$5:$G$604,G36,$J$5:$J$604,"Booking.com")=0,"",_xlfn.MINIFS($M$5:$M$604,$E$5:$E$604,E36,$G$5:$G$604,G36,$J$5:$J$604,"Booking.com")) | Z36: =IF(OR(Y36="",M36="",J36="Booking.com"),"",Y36-M36) | AD36: 1 room on this price
A37: 33 | B37: Kandy | C37: 46378 | D37: 1 | E37: Jetwing Kandy Gallery | G37: Luxury room DBL | H37: HB | I37: 1 | J37: Direct | K37: USD | L37: 315 | M37: =IF(L37="","",IFERROR(L37*INDEX(Trip!$E$5:$E$14,MATCH(K37,Trip!$D$5:$D$14,0))/INDEX(Trip!$E$5:$E$14,MATCH(Trip!$B$10,Trip!$D$5:$D$14,0)),"")) -> 315 | N37: =IF(OR(M37="",D37=""),"",M37/D37) -> 315 | O37: =IF(M37="","",M37*I37) -> 315 | P37: 46287 | Q37: =IF(ISNUMBER(P37),P37-TODAY(),IF(P37="","",P37)) -> -15 | R37: Blocked | U37: 0.0921 | V37: =IF(M37="","",M37*(1+IF(U37="",Trip!$B$11,U37))) -> 344.0115 | W37: =IF(V37="","",V37*I37) -> 344.0115 | X37: =IF(OR(M37="",R37="Unavailable"),"",IF(M37=_xlfn.MINIFS($M$5:$M$604,$E$5:$E$604,E37,$G$5:$G$604,G37,$H$5:$H$604,H37,$R$5:$R$604,"<>Unavailable"),"⭐ Cheapest","")) -> ⭐ Cheapest | Y37: =IF(COUNTIFS($E$5:$E$604,E37,$G$5:$G$604,G37,$J$5:$J$604,"Booking.com")=0,"",_xlfn.MINIFS($M$5:$M$604,$E$5:$E$604,E37,$G$5:$G$604,G37,$J$5:$J$604,"Booking.com")) | Z37: =IF(OR(Y37="",M37="",J37="Booking.com"),"",Y37-M37) | AA37: Y | AC37: Y
A38: 34 | B38: Kandy | C38: 46378 | D38: 1 | E38: Jetwing Kandy Gallery | G38: Luxury room SGL | H38: HB | I38: 1 | J38: Direct | K38: USD | L38: 265 | M38: =IF(L38="","",IFERROR(L38*INDEX(Trip!$E$5:$E$14,MATCH(K38,Trip!$D$5:$D$14,0))/INDEX(Trip!$E$5:$E$14,MATCH(Trip!$B$10,Trip!$D$5:$D$14,0)),"")) -> 265 | N38: =IF(OR(M38="",D38=""),"",M38/D38) -> 265 | O38: =IF(M38="","",M38*I38) -> 265 | P38: 46287 | Q38: =IF(ISNUMBER(P38),P38-TODAY(),IF(P38="","",P38)) -> -15 | R38: Blocked | U38: 0.1396 | V38: =IF(M38="","",M38*(1+IF(U38="",Trip!$B$11,U38))) -> 301.994 | W38: =IF(V38="","",V38*I38) -> 301.994 | X38: =IF(OR(M38="",R38="Unavailable"),"",IF(M38=_xlfn.MINIFS($M$5:$M$604,$E$5:$E$604,E38,$G$5:$G$604,G38,$H$5:$H$604,H38,$R$5:$R$604,"<>Unavailable"),"⭐ Cheapest","")) -> ⭐ Cheapest | Y38: =IF(COUNTIFS($E$5:$E$604,E38,$G$5:$G$604,G38,$J$5:$J$604,"Booking.com")=0,"",_xlfn.MINIFS($M$5:$M$604,$E$5:$E$604,E38,$G$5:$G$604,G38,$J$5:$J$604,"Booking.com")) | Z38: =IF(OR(Y38="",M38="",J38="Booking.com"),"",Y38-M38) | AB38: Y
A39: 35 | B39: Kandy | C39: 46378 | D39: 1 | E39: Jetwing Kandy Gallery | G39: Deluxe Room DBL/SGL 27sqm | H39: HB | I39: 1 | J39: Direct | K39: USD | L39: 409 | M39: =IF(L39="","",IFERROR(L39*INDEX(Trip!$E$5:$E$14,MATCH(K39,Trip!$D$5:$D$14,0))/INDEX(Trip!$E$5:$E$14,MATCH(Trip!$B$10,Trip!$D$5:$D$14,0)),"")) -> 409 | N39: =IF(OR(M39="",D39=""),"",M39/D39) -> 409 | O39: =IF(M39="","",M39*I39) -> 409 | P39: NRF | Q39: =IF(ISNUMBER(P39),P39-TODAY(),IF(P39="","",P39)) -> NRF | R39: Quote | V39: =IF(M39="","",M39*(1+IF(U39="",Trip!$B$11,U39))) -> 470.35 | W39: =IF(V39="","",V39*I39) -> 470.35 | X39: =IF(OR(M39="",R39="Unavailable"),"",IF(M39=_xlfn.MINIFS($M$5:$M$604,$E$5:$E$604,E39,$G$5:$G$604,G39,$H$5:$H$604,H39,$R$5:$R$604,"<>Unavailable"),"⭐ Cheapest","")) -> ⭐ Cheapest | Y39: =IF(COUNTIFS($E$5:$E$604,E39,$G$5:$G$604,G39,$J$5:$J$604,"Booking.com")=0,"",_xlfn.MINIFS($M$5:$M$604,$E$5:$E$604,E39,$G$5:$G$604,G39,$J$5:$J$604,"Booking.com")) | Z39: =IF(OR(Y39="",M39="",J39="Booking.com"),"",Y39-M39)
A40: 36 | B40: Kandy | C40: 46378 | D40: 1 | E40: Taru Villas Levita | F40: 5 | G40: Superior room 35M2 DBL/SGL | H40: BB | I40: 1 | J40: TBO | K40: INR | L40: 30414 | M40: =IF(L40="","",IFERROR(L40*INDEX(Trip!$E$5:$E$14,MATCH(K40,Trip!$D$5:$D$14,0))/INDEX(Trip!$E$5:$E$14,MATCH(Trip!$B$10,Trip!$D$5:$D$14,0)),"")) -> 322.52386 | N40: =IF(OR(M40="",D40=""),"",M40/D40) -> 322.52386 | O40: =IF(M40="","",M40*I40) -> 322.52386 | P40: 46345 | Q40: =IF(ISNUMBER(P40),P40-TODAY(),IF(P40="","",P40)) -> 43 | R40: Quote | V40: =IF(M40="","",M40*(1+IF(U40="",Trip!$B$11,U40))) -> 370.90244 | W40: =IF(V40="","",V40*I40) -> 370.90244 | X40: =IF(OR(M40="",R40="Unavailable"),"",IF(M40=_xlfn.MINIFS($M$5:$M$604,$E$5:$E$604,E40,$G$5:$G$604,G40,$H$5:$H$604,H40,$R$5:$R$604,"<>Unavailable"),"⭐ Cheapest","")) -> ⭐ Cheapest | Y40: =IF(COUNTIFS($E$5:$E$604,E40,$G$5:$G$604,G40,$J$5:$J$604,"Booking.com")=0,"",_xlfn.MINIFS($M$5:$M$604,$E$5:$E$604,E40,$G$5:$G$604,G40,$J$5:$J$604,"Booking.com")) -> 375.88547 | Z40: =IF(OR(Y40="",M40="",J40="Booking.com"),"",Y40-M40) -> 53.361612
A41: 37 | B41: Kandy | C41: 46378 | D41: 1 | E41: Taru Villas Levita | F41: 5 | G41: Superior room 35M2 DBL/SGL | H41: BB | I41: 1 | J41: Booking.com | K41: INR | L41: 35446 | M41: =IF(L41="","",IFERROR(L41*INDEX(Trip!$E$5:$E$14,MATCH(K41,Trip!$D$5:$D$14,0))/INDEX(Trip!$E$5:$E$14,MATCH(Trip!$B$10,Trip!$D$5:$D$14,0)),"")) -> 375.88547 | N41: =IF(OR(M41="",D41=""),"",M41/D41) -> 375.88547 | O41: =IF(M41="","",M41*I41) -> 375.88547 | P41: 46317 | Q41: =IF(ISNUMBER(P41),P41-TODAY(),IF(P41="","",P41)) -> 15 | R41: Quote | V41: =IF(M41="","",M41*(1+IF(U41="",Trip!$B$11,U41))) -> 432.26829 | W41: =IF(V41="","",V41*I41) -> 432.26829 | X41: =IF(OR(M41="",R41="Unavailable"),"",IF(M41=_xlfn.MINIFS($M$5:$M$604,$E$5:$E$604,E41,$G$5:$G$604,G41,$H$5:$H$604,H41,$R$5:$R$604,"<>Unavailable"),"⭐ Cheapest","")) | Y41: =IF(COUNTIFS($E$5:$E$604,E41,$G$5:$G$604,G41,$J$5:$J$604,"Booking.com")=0,"",_xlfn.MINIFS($M$5:$M$604,$E$5:$E$604,E41,$G$5:$G$604,G41,$J$5:$J$604,"Booking.com")) -> 375.88547 | Z41: =IF(OR(Y41="",M41="",J41="Booking.com"),"",Y41-M41)
A42: 38 | B42: Kandy | C42: 46378 | D42: 1 | E42: Taru Villas Levita | F42: 5 | G42: Premier room 79M2 DBL/SGL | H42: BB | I42: 1 | J42: TBO | K42: INR | L42: 34593 | M42: =IF(L42="","",IFERROR(L42*INDEX(Trip!$E$5:$E$14,MATCH(K42,Trip!$D$5:$D$14,0))/INDEX(Trip!$E$5:$E$14,MATCH(Trip!$B$10,Trip!$D$5:$D$14,0)),"")) -> 366.83987 | N42: =IF(OR(M42="",D42=""),"",M42/D42) -> 366.83987 | O42: =IF(M42="","",M42*I42) -> 366.83987 | P42: 46345 | Q42: =IF(ISNUMBER(P42),P42-TODAY(),IF(P42="","",P42)) -> 43 | R42: Quote | V42: =IF(M42="","",M42*(1+IF(U42="",Trip!$B$11,U42))) -> 421.86585 | W42: =IF(V42="","",V42*I42) -> 421.86585 | X42: =IF(OR(M42="",R42="Unavailable"),"",IF(M42=_xlfn.MINIFS($M$5:$M$604,$E$5:$E$604,E42,$G$5:$G$604,G42,$H$5:$H$604,H42,$R$5:$R$604,"<>Unavailable"),"⭐ Cheapest","")) -> ⭐ Cheapest | Y42: =IF(COUNTIFS($E$5:$E$604,E42,$G$5:$G$604,G42,$J$5:$J$604,"Booking.com")=0,"",_xlfn.MINIFS($M$5:$M$604,$E$5:$E$604,E42,$G$5:$G$604,G42,$J$5:$J$604,"Booking.com")) -> 427.40191 | Z42: =IF(OR(Y42="",M42="",J42="Booking.com"),"",Y42-M42) -> 60.562036
A43: 39 | B43: Kandy | C43: 46378 | D43: 1 | E43: Taru Villas Levita | F43: 5 | G43: Premier room 79M2 DBL/SGL | H43: BB | I43: 1 | J43: Booking.com | K43: INR | L43: 40304 | M43: =IF(L43="","",IFERROR(L43*INDEX(Trip!$E$5:$E$14,MATCH(K43,Trip!$D$5:$D$14,0))/INDEX(Trip!$E$5:$E$14,MATCH(Trip!$B$10,Trip!$D$5:$D$14,0)),"")) -> 427.40191 | N43: =IF(OR(M43="",D43=""),"",M43/D43) -> 427.40191 | O43: =IF(M43="","",M43*I43) -> 427.40191 | P43: 46317 | Q43: =IF(ISNUMBER(P43),P43-TODAY(),IF(P43="","",P43)) -> 15 | R43: Quote | V43: =IF(M43="","",M43*(1+IF(U43="",Trip!$B$11,U43))) -> 491.5122 | W43: =IF(V43="","",V43*I43) -> 491.5122 | X43: =IF(OR(M43="",R43="Unavailable"),"",IF(M43=_xlfn.MINIFS($M$5:$M$604,$E$5:$E$604,E43,$G$5:$G$604,G43,$H$5:$H$604,H43,$R$5:$R$604,"<>Unavailable"),"⭐ Cheapest","")) | Y43: =IF(COUNTIFS($E$5:$E$604,E43,$G$5:$G$604,G43,$J$5:$J$604,"Booking.com")=0,"",_xlfn.MINIFS($M$5:$M$604,$E$5:$E$604,E43,$G$5:$G$604,G43,$J$5:$J$604,"Booking.com")) -> 427.40191 | Z43: =IF(OR(Y43="",M43="",J43="Booking.com"),"",Y43-M43)
A44: 40 | B44: Kandy | C44: 46378 | D44: 1 | E44: Jetwing Kandy Gallery | G44: Luxury Queen Room 52 sqmt | H44: BB | I44: 1 | J44: Ottila | K44: INR | L44: 34517.48 | M44: =IF(L44="","",IFERROR(L44*INDEX(Trip!$E$5:$E$14,MATCH(K44,Trip!$D$5:$D$14,0))/INDEX(Trip!$E$5:$E$14,MATCH(Trip!$B$10,Trip!$D$5:$D$14,0)),"")) -> 366.03902 | N44: =IF(OR(M44="",D44=""),"",M44/D44) -> 366.03902 | O44: =IF(M44="","",M44*I44) -> 366.03902 | P44: 46361 | Q44: =IF(ISNUMBER(P44),P44-TODAY(),IF(P44="","",P44)) -> 59 | R44: Quote | T44: Upg 1 | V44: =IF(M44="","",M44*(1+IF(U44="",Trip!$B$11,U44))) -> 420.94488 | W44: =IF(V44="","",V44*I44) -> 420.94488 | X44: =IF(OR(M44="",R44="Unavailable"),"",IF(M44=_xlfn.MINIFS($M$5:$M$604,$E$5:$E$604,E44,$G$5:$G$604,G44,$H$5:$H$604,H44,$R$5:$R$604,"<>Unavailable"),"⭐ Cheapest","")) | Y44: =IF(COUNTIFS($E$5:$E$604,E44,$G$5:$G$604,G44,$J$5:$J$604,"Booking.com")=0,"",_xlfn.MINIFS($M$5:$M$604,$E$5:$E$604,E44,$G$5:$G$604,G44,$J$5:$J$604,"Booking.com")) -> 315 | Z44: =IF(OR(Y44="",M44="",J44="Booking.com"),"",Y44-M44) -> -51.039024
A45: 41 | B45: Kandy | C45: 46378 | D45: 1 | E45: Jetwing Kandy Gallery | G45: Luxury Queen Room 52 sqmt | H45: BB | I45: 1 | J45: Booking.com | K45: USD | L45: 315 | M45: =IF(L45="","",IFERROR(L45*INDEX(Trip!$E$5:$E$14,MATCH(K45,Trip!$D$5:$D$14,0))/INDEX(Trip!$E$5:$E$14,MATCH(Trip!$B$10,Trip!$D$5:$D$14,0)),"")) -> 315 | N45: =IF(OR(M45="",D45=""),"",M45/D45) -> 315 | O45: =IF(M45="","",M45*I45) -> 315 | P45: NRF | Q45: =IF(ISNUMBER(P45),P45-TODAY(),IF(P45="","",P45)) -> NRF | R45: Quote | V45: =IF(M45="","",M45*(1+IF(U45="",Trip!$B$11,U45))) -> 362.25 | W45: =IF(V45="","",V45*I45) -> 362.25 | X45: =IF(OR(M45="",R45="Unavailable"),"",IF(M45=_xlfn.MINIFS($M$5:$M$604,$E$5:$E$604,E45,$G$5:$G$604,G45,$H$5:$H$604,H45,$R$5:$R$604,"<>Unavailable"),"⭐ Cheapest","")) -> ⭐ Cheapest | Y45: =IF(COUNTIFS($E$5:$E$604,E45,$G$5:$G$604,G45,$J$5:$J$604,"Booking.com")=0,"",_xlfn.MINIFS($M$5:$M$604,$E$5:$E$604,E45,$G$5:$G$604,G45,$J$5:$J$604,"Booking.com")) -> 315 | Z45: =IF(OR(Y45="",M45="",J45="Booking.com"),"",Y45-M45)
A46: 42 | B46: Kandy | C46: 46378 | D46: 1 | E46: Earls Regency | G46: Deluxe King Room 37sqmt | H46: BB | I46: 1 | J46: Ottila | K46: INR | L46: 18149.86 | M46: =IF(L46="","",IFERROR(L46*INDEX(Trip!$E$5:$E$14,MATCH(K46,Trip!$D$5:$D$14,0))/INDEX(Trip!$E$5:$E$14,MATCH(Trip!$B$10,Trip!$D$5:$D$14,0)),"")) -> 192.46935 | N46: =IF(OR(M46="",D46=""),"",M46/D46) -> 192.46935 | O46: =IF(M46="","",M46*I46) -> 192.46935 | P46: 46368 | Q46: =IF(ISNUMBER(P46),P46-TODAY(),IF(P46="","",P46)) -> 66 | R46: Quote | T46: Base | V46: =IF(M46="","",M46*(1+IF(U46="",Trip!$B$11,U46))) -> 221.33976 | W46: =IF(V46="","",V46*I46) -> 221.33976 | X46: =IF(OR(M46="",R46="Unavailable"),"",IF(M46=_xlfn.MINIFS($M$5:$M$604,$E$5:$E$604,E46,$G$5:$G$604,G46,$H$5:$H$604,H46,$R$5:$R$604,"<>Unavailable"),"⭐ Cheapest","")) -> ⭐ Cheapest | Y46: =IF(COUNTIFS($E$5:$E$604,E46,$G$5:$G$604,G46,$J$5:$J$604,"Booking.com")=0,"",_xlfn.MINIFS($M$5:$M$604,$E$5:$E$604,E46,$G$5:$G$604,G46,$J$5:$J$604,"Booking.com")) -> 230 | Z46: =IF(OR(Y46="",M46="",J46="Booking.com"),"",Y46-M46) -> 37.530647
A47: 43 | B47: Kandy | C47: 46378 | D47: 1 | E47: Earls Regency | G47: Deluxe King Room 37sqmt | H47: BB | I47: 1 | J47: Booking.com | K47: USD | L47: 230 | M47: =IF(L47="","",IFERROR(L47*INDEX(Trip!$E$5:$E$14,MATCH(K47,Trip!$D$5:$D$14,0))/INDEX(Trip!$E$5:$E$14,MATCH(Trip!$B$10,Trip!$D$5:$D$14,0)),"")) -> 230 | N47: =IF(OR(M47="",D47=""),"",M47/D47) -> 230 | O47: =IF(M47="","",M47*I47) -> 230 | Q47: =IF(ISNUMBER(P47),P47-TODAY(),IF(P47="","",P47)) | R47: Quote | V47: =IF(M47="","",M47*(1+IF(U47="",Trip!$B$11,U47))) -> 264.5 | W47: =IF(V47="","",V47*I47) -> 264.5 | X47: =IF(OR(M47="",R47="Unavailable"),"",IF(M47=_xlfn.MINIFS($M$5:$M$604,$E$5:$E$604,E47,$G$5:$G$604,G47,$H$5:$H$604,H47,$R$5:$R$604,"<>Unavailable"),"⭐ Cheapest","")) | Y47: =IF(COUNTIFS($E$5:$E$604,E47,$G$5:$G$604,G47,$J$5:$J$604,"Booking.com")=0,"",_xlfn.MINIFS($M$5:$M$604,$E$5:$E$604,E47,$G$5:$G$604,G47,$J$5:$J$604,"Booking.com")) -> 230 | Z47: =IF(OR(Y47="",M47="",J47="Booking.com"),"",Y47-M47)
A48: 44 | B48: Nuwara Eliya | C48: 46379 | D48: 2 | E48: The Golden Ridge Hotel | F48: 5 | G48: Deluxe Room DBL/SGL 23m2 | H48: BB | I48: 1 | J48: Ottila | K48: INR | L48: 120321 | M48: =IF(L48="","",IFERROR(L48*INDEX(Trip!$E$5:$E$14,MATCH(K48,Trip!$D$5:$D$14,0))/INDEX(Trip!$E$5:$E$14,MATCH(Trip!$B$10,Trip!$D$5:$D$14,0)),"")) -> 1275.9385 | N48: =IF(OR(M48="",D48=""),"",M48/D48) -> 637.96925 | O48: =IF(M48="","",M48*I48) -> 1275.9385 | P48: 46372 | Q48: =IF(ISNUMBER(P48),P48-TODAY(),IF(P48="","",P48)) -> 70 | R48: Quote | T48: Upg 3 | V48: =IF(M48="","",M48*(1+IF(U48="",Trip!$B$11,U48))) -> 1467.3293 | W48: =IF(V48="","",V48*I48) -> 1467.3293 | X48: =IF(OR(M48="",R48="Unavailable"),"",IF(M48=_xlfn.MINIFS($M$5:$M$604,$E$5:$E$604,E48,$G$5:$G$604,G48,$H$5:$H$604,H48,$R$5:$R$604,"<>Unavailable"),"⭐ Cheapest","")) | Y48: =IF(COUNTIFS($E$5:$E$604,E48,$G$5:$G$604,G48,$J$5:$J$604,"Booking.com")=0,"",_xlfn.MINIFS($M$5:$M$604,$E$5:$E$604,E48,$G$5:$G$604,G48,$J$5:$J$604,"Booking.com")) -> 771.09226 | Z48: =IF(OR(Y48="",M48="",J48="Booking.com"),"",Y48-M48) -> -504.84624
A49: 45 | B49: Nuwara Eliya | C49: 46379 | D49: 2 | E49: The Golden Ridge Hotel | F49: 5 | G49: Deluxe Room DBL/SGL 23m2 | H49: BB | I49: 1 | J49: Booking.com | K49: INR | L49: 72714 | M49: =IF(L49="","",IFERROR(L49*INDEX(Trip!$E$5:$E$14,MATCH(K49,Trip!$D$5:$D$14,0))/INDEX(Trip!$E$5:$E$14,MATCH(Trip!$B$10,Trip!$D$5:$D$14,0)),"")) -> 771.09226 | N49: =IF(OR(M49="",D49=""),"",M49/D49) -> 385.54613 | O49: =IF(M49="","",M49*I49) -> 771.09226 | P49: 46371 | Q49: =IF(ISNUMBER(P49),P49-TODAY(),IF(P49="","",P49)) -> 69 | R49: Quote | V49: =IF(M49="","",M49*(1+IF(U49="",Trip!$B$11,U49))) -> 886.7561 | W49: =IF(V49="","",V49*I49) -> 886.7561 | X49: =IF(OR(M49="",R49="Unavailable"),"",IF(M49=_xlfn.MINIFS($M$5:$M$604,$E$5:$E$604,E49,$G$5:$G$604,G49,$H$5:$H$604,H49,$R$5:$R$604,"<>Unavailable"),"⭐ Cheapest","")) -> ⭐ Cheapest | Y49: =IF(COUNTIFS($E$5:$E$604,E49,$G$5:$G$604,G49,$J$5:$J$604,"Booking.com")=0,"",_xlfn.MINIFS($M$5:$M$604,$E$5:$E$604,E49,$G$5:$G$604,G49,$J$5:$J$604,"Booking.com")) -> 771.09226 | Z49: =IF(OR(Y49="",M49="",J49="Booking.com"),"",Y49-M49)
A50: 46 | B50: Nuwara Eliya | C50: 46379 | D50: 2 | E50: The Golden Ridge Hotel | F50: 5 | G50: Family Room Standard 38sqm DBL/SGL | H50: BB | I50: 1 | J50: Ottila | K50: INR | L50: 145908 | M50: =IF(L50="","",IFERROR(L50*INDEX(Trip!$E$5:$E$14,MATCH(K50,Trip!$D$5:$D$14,0))/INDEX(Trip!$E$5:$E$14,MATCH(Trip!$B$10,Trip!$D$5:$D$14,0)),"")) -> 1547.2747 | N50: =IF(OR(M50="",D50=""),"",M50/D50) -> 773.63733 | O50: =IF(M50="","",M50*I50) -> 1547.2747 | P50: 46374 | Q50: =IF(ISNUMBER(P50),P50-TODAY(),IF(P50="","",P50)) -> 72 | R50: Quote | T50: Upg 3 | V50: =IF(M50="","",M50*(1+IF(U50="",Trip!$B$11,U50))) -> 1779.3659 | W50: =IF(V50="","",V50*I50) -> 1779.3659 | X50: =IF(OR(M50="",R50="Unavailable"),"",IF(M50=_xlfn.MINIFS($M$5:$M$604,$E$5:$E$604,E50,$G$5:$G$604,G50,$H$5:$H$604,H50,$R$5:$R$604,"<>Unavailable"),"⭐ Cheapest","")) | Y50: =IF(COUNTIFS($E$5:$E$604,E50,$G$5:$G$604,G50,$J$5:$J$604,"Booking.com")=0,"",_xlfn.MINIFS($M$5:$M$604,$E$5:$E$604,E50,$G$5:$G$604,G50,$J$5:$J$604,"Booking.com")) -> 771.09226 | Z50: =IF(OR(Y50="",M50="",J50="Booking.com"),"",Y50-M50) -> -776.1824
A51: 47 | B51: Nuwara Eliya | C51: 46379 | D51: 2 | E51: The Golden Ridge Hotel | F51: 5 | G51: Family Room Standard 38sqm DBL/SGL | H51: BB | I51: 1 | J51: Booking.com | K51: INR | L51: 72714 | M51: =IF(L51="","",IFERROR(L51*INDEX(Trip!$E$5:$E$14,MATCH(K51,Trip!$D$5:$D$14,0))/INDEX(Trip!$E$5:$E$14,MATCH(Trip!$B$10,Trip!$D$5:$D$14,0)),"")) -> 771.09226 | N51: =IF(OR(M51="",D51=""),"",M51/D51) -> 385.54613 | O51: =IF(M51="","",M51*I51) -> 771.09226 | P51: 46371 | Q51: =IF(ISNUMBER(P51),P51-TODAY(),IF(P51="","",P51)) -> 69 | R51: Quote | V51: =IF(M51="","",M51*(1+IF(U51="",Trip!$B$11,U51))) -> 886.7561 | W51: =IF(V51="","",V51*I51) -> 886.7561 | X51: =IF(OR(M51="",R51="Unavailable"),"",IF(M51=_xlfn.MINIFS($M$5:$M$604,$E$5:$E$604,E51,$G$5:$G$604,G51,$H$5:$H$604,H51,$R$5:$R$604,"<>Unavailable"),"⭐ Cheapest","")) -> ⭐ Cheapest | Y51: =IF(COUNTIFS($E$5:$E$604,E51,$G$5:$G$604,G51,$J$5:$J$604,"Booking.com")=0,"",_xlfn.MINIFS($M$5:$M$604,$E$5:$E$604,E51,$G$5:$G$604,G51,$J$5:$J$604,"Booking.com")) -> 771.09226 | Z51: =IF(OR(Y51="",M51="",J51="Booking.com"),"",Y51-M51)
A52: 48 | B52: Nuwara Eliya | C52: 46379 | D52: 2 | E52: The Golden Ridge Hotel | F52: 5 | G52: Bedroom Standard Family Room | H52: HB | I52: 1 | J52: Ottila | K52: INR | L52: 82090 | M52: =IF(L52="","",IFERROR(L52*INDEX(Trip!$E$5:$E$14,MATCH(K52,Trip!$D$5:$D$14,0))/INDEX(Trip!$E$5:$E$14,MATCH(Trip!$B$10,Trip!$D$5:$D$14,0)),"")) -> 870.51962 | N52: =IF(OR(M52="",D52=""),"",M52/D52) -> 435.25981 | O52: =IF(M52="","",M52*I52) -> 870.51962 | P52: NRF | Q52: =IF(ISNUMBER(P52),P52-TODAY(),IF(P52="","",P52)) -> NRF | R52: Quote | V52: =IF(M52="","",M52*(1+IF(U52="",Trip!$B$11,U52))) -> 1001.0976 | W52: =IF(V52="","",V52*I52) -> 1001.0976 | X52: =IF(OR(M52="",R52="Unavailable"),"",IF(M52=_xlfn.MINIFS($M$5:$M$604,$E$5:$E$604,E52,$G$5:$G$604,G52,$H$5:$H$604,H52,$R$5:$R$604,"<>Unavailable"),"⭐ Cheapest","")) -> ⭐ Cheapest | Y52: =IF(COUNTIFS($E$5:$E$604,E52,$G$5:$G$604,G52,$J$5:$J$604,"Booking.com")=0,"",_xlfn.MINIFS($M$5:$M$604,$E$5:$E$604,E52,$G$5:$G$604,G52,$J$5:$J$604,"Booking.com")) -> 928.61082 | Z52: =IF(OR(Y52="",M52="",J52="Booking.com"),"",Y52-M52) -> 58.091198
A53: 49 | B53: Nuwara Eliya | C53: 46379 | D53: 2 | E53: The Golden Ridge Hotel | F53: 5 | G53: Bedroom Standard Family Room | H53: HB | I53: 1 | J53: Booking.com | K53: INR | L53: 87568 | M53: =IF(L53="","",IFERROR(L53*INDEX(Trip!$E$5:$E$14,MATCH(K53,Trip!$D$5:$D$14,0))/INDEX(Trip!$E$5:$E$14,MATCH(Trip!$B$10,Trip!$D$5:$D$14,0)),"")) -> 928.61082 | N53: =IF(OR(M53="",D53=""),"",M53/D53) -> 464.30541 | O53: =IF(M53="","",M53*I53) -> 928.61082 | P53: 46371 | Q53: =IF(ISNUMBER(P53),P53-TODAY(),IF(P53="","",P53)) -> 69 | R53: Quote | V53: =IF(M53="","",M53*(1+IF(U53="",Trip!$B$11,U53))) -> 1067.9024 | W53: =IF(V53="","",V53*I53) -> 1067.9024 | X53: =IF(OR(M53="",R53="Unavailable"),"",IF(M53=_xlfn.MINIFS($M$5:$M$604,$E$5:$E$604,E53,$G$5:$G$604,G53,$H$5:$H$604,H53,$R$5:$R$604,"<>Unavailable"),"⭐ Cheapest","")) | Y53: =IF(COUNTIFS($E$5:$E$604,E53,$G$5:$G$604,G53,$J$5:$J$604,"Booking.com")=0,"",_xlfn.MINIFS($M$5:$M$604,$E$5:$E$604,E53,$G$5:$G$604,G53,$J$5:$J$604,"Booking.com")) -> 928.61082 | Z53: =IF(OR(Y53="",M53="",J53="Booking.com"),"",Y53-M53)
A54: 50 | B54: Nuwara Eliya | C54: 46379 | D54: 2 | E54: The Golden Ridge Hotel | F54: 5 | G54: Deluxe Room DBL/SGL 23m2 | H54: HB | I54: 1 | J54: Ottila | K54: INR | L54: 72893 | M54: =IF(L54="","",IFERROR(L54*INDEX(Trip!$E$5:$E$14,MATCH(K54,Trip!$D$5:$D$14,0))/INDEX(Trip!$E$5:$E$14,MATCH(Trip!$B$10,Trip!$D$5:$D$14,0)),"")) -> 772.99046 | N54: =IF(OR(M54="",D54=""),"",M54/D54) -> 386.49523 | O54: =IF(M54="","",M54*I54) -> 772.99046 | P54: NRF | Q54: =IF(ISNUMBER(P54),P54-TODAY(),IF(P54="","",P54)) -> NRF | R54: Quote | V54: =IF(M54="","",M54*(1+IF(U54="",Trip!$B$11,U54))) -> 888.93902 | W54: =IF(V54="","",V54*I54) -> 888.93902 | X54: =IF(OR(M54="",R54="Unavailable"),"",IF(M54=_xlfn.MINIFS($M$5:$M$604,$E$5:$E$604,E54,$G$5:$G$604,G54,$H$5:$H$604,H54,$R$5:$R$604,"<>Unavailable"),"⭐ Cheapest","")) -> ⭐ Cheapest | Y54: =IF(COUNTIFS($E$5:$E$604,E54,$G$5:$G$604,G54,$J$5:$J$604,"Booking.com")=0,"",_xlfn.MINIFS($M$5:$M$604,$E$5:$E$604,E54,$G$5:$G$604,G54,$J$5:$J$604,"Booking.com")) -> 771.09226 | Z54: =IF(OR(Y54="",M54="",J54="Booking.com"),"",Y54-M54) -> -1.8981972
A55: 51 | B55: Nuwara Eliya | C55: 46379 | D55: 2 | E55: The Golden Ridge Hotel | F55: 5 | G55: Deluxe Room DBL/SGL 23m2 | H55: HB | I55: 1 | J55: Booking.com | K55: INR | L55: 77757 | M55: =IF(L55="","",IFERROR(L55*INDEX(Trip!$E$5:$E$14,MATCH(K55,Trip!$D$5:$D$14,0))/INDEX(Trip!$E$5:$E$14,MATCH(Trip!$B$10,Trip!$D$5:$D$14,0)),"")) -> 824.57052 | N55: =IF(OR(M55="",D55=""),"",M55/D55) -> 412.28526 | O55: =IF(M55="","",M55*I55) -> 824.57052 | P55: 46371 | Q55: =IF(ISNUMBER(P55),P55-TODAY(),IF(P55="","",P55)) -> 69 | R55: Quote | V55: =IF(M55="","",M55*(1+IF(U55="",Trip!$B$11,U55))) -> 948.2561 | W55: =IF(V55="","",V55*I55) -> 948.2561 | X55: =IF(OR(M55="",R55="Unavailable"),"",IF(M55=_xlfn.MINIFS($M$5:$M$604,$E$5:$E$604,E55,$G$5:$G$604,G55,$H$5:$H$604,H55,$R$5:$R$604,"<>Unavailable"),"⭐ Cheapest","")) | Y55: =IF(COUNTIFS($E$5:$E$604,E55,$G$5:$G$604,G55,$J$5:$J$604,"Booking.com")=0,"",_xlfn.MINIFS($M$5:$M$604,$E$5:$E$604,E55,$G$5:$G$604,G55,$J$5:$J$604,"Booking.com")) -> 771.09226 | Z55: =IF(OR(Y55="",M55="",J55="Booking.com"),"",Y55-M55)
A56: 52 | B56: Nuwara Eliya | C56: 46379 | D56: 2 | E56: The Golden Ridge Hotel | F56: 5 | G56: Bedroom Standard Family Room | H56: HB | I56: 1 | J56: Direct | K56: USD | L56: 937 | M56: =IF(L56="","",IFERROR(L56*INDEX(Trip!$E$5:$E$14,MATCH(K56,Trip!$D$5:$D$14,0))/INDEX(Trip!$E$5:$E$14,MATCH(Trip!$B$10,Trip!$D$5:$D$14,0)),"")) -> 937 | N56: =IF(OR(M56="",D56=""),"",M56/D56) -> 468.5 | O56: =IF(M56="","",M56*I56) -> 937 | P56: 50% NRF | Q56: =IF(ISNUMBER(P56),P56-TODAY(),IF(P56="","",P56)) -> 50% NRF | R56: Quote | V56: =IF(M56="","",M56*(1+IF(U56="",Trip!$B$11,U56))) -> 1077.55 | W56: =IF(V56="","",V56*I56) -> 1077.55 | X56: =IF(OR(M56="",R56="Unavailable"),"",IF(M56=_xlfn.MINIFS($M$5:$M$604,$E$5:$E$604,E56,$G$5:$G$604,G56,$H$5:$H$604,H56,$R$5:$R$604,"<>Unavailable"),"⭐ Cheapest","")) | Y56: =IF(COUNTIFS($E$5:$E$604,E56,$G$5:$G$604,G56,$J$5:$J$604,"Booking.com")=0,"",_xlfn.MINIFS($M$5:$M$604,$E$5:$E$604,E56,$G$5:$G$604,G56,$J$5:$J$604,"Booking.com")) -> 928.61082 | Z56: =IF(OR(Y56="",M56="",J56="Booking.com"),"",Y56-M56) -> -8.3891835
A57: 53 | B57: Nuwara Eliya | C57: 46379 | D57: 2 | E57: The Golden Ridge Hotel | F57: 5 | G57: Deluxe Room DBL/SGL 23m2 | H57: HB | I57: 1 | J57: Direct | K57: USD | L57: 1010 | M57: =IF(L57="","",IFERROR(L57*INDEX(Trip!$E$5:$E$14,MATCH(K57,Trip!$D$5:$D$14,0))/INDEX(Trip!$E$5:$E$14,MATCH(Trip!$B$10,Trip!$D$5:$D$14,0)),"")) -> 1010 | N57: =IF(OR(M57="",D57=""),"",M57/D57) -> 505 | O57: =IF(M57="","",M57*I57) -> 1010 | P57: 50% NRF | Q57: =IF(ISNUMBER(P57),P57-TODAY(),IF(P57="","",P57)) -> 50% NRF | R57: Quote | V57: =IF(M57="","",M57*(1+IF(U57="",Trip!$B$11,U57))) -> 1161.5 | W57: =IF(V57="","",V57*I57) -> 1161.5 | X57: =IF(OR(M57="",R57="Unavailable"),"",IF(M57=_xlfn.MINIFS($M$5:$M$604,$E$5:$E$604,E57,$G$5:$G$604,G57,$H$5:$H$604,H57,$R$5:$R$604,"<>Unavailable"),"⭐ Cheapest","")) | Y57: =IF(COUNTIFS($E$5:$E$604,E57,$G$5:$G$604,G57,$J$5:$J$604,"Booking.com")=0,"",_xlfn.MINIFS($M$5:$M$604,$E$5:$E$604,E57,$G$5:$G$604,G57,$J$5:$J$604,"Booking.com")) -> 771.09226 | Z57: =IF(OR(Y57="",M57="",J57="Booking.com"),"",Y57-M57) -> -238.90774
A58: 54 | B58: Nuwara Eliya | C58: 46379 | D58: 2 | E58: The Golden Ridge Hotel | F58: 5 | G58: Deluxe Room SGL 23m2 | H58: HB | I58: 1 | J58: Helanka | K58: USD | L58: 548.55 | M58: =IF(L58="","",IFERROR(L58*INDEX(Trip!$E$5:$E$14,MATCH(K58,Trip!$D$5:$D$14,0))/INDEX(Trip!$E$5:$E$14,MATCH(Trip!$B$10,Trip!$D$5:$D$14,0)),"")) -> 548.55 | N58: =IF(OR(M58="",D58=""),"",M58/D58) -> 274.275 | O58: =IF(M58="","",M58*I58) -> 548.55 | P58: 46346 | Q58: =IF(ISNUMBER(P58),P58-TODAY(),IF(P58="","",P58)) -> 44 | R58: Blocked | U58: 0.6206 | V58: =IF(M58="","",M58*(1+IF(U58="",Trip!$B$11,U58))) -> 888.98013 | W58: =IF(V58="","",V58*I58) -> 888.98013 | X58: =IF(OR(M58="",R58="Unavailable"),"",IF(M58=_xlfn.MINIFS($M$5:$M$604,$E$5:$E$604,E58,$G$5:$G$604,G58,$H$5:$H$604,H58,$R$5:$R$604,"<>Unavailable"),"⭐ Cheapest","")) -> ⭐ Cheapest | Y58: =IF(COUNTIFS($E$5:$E$604,E58,$G$5:$G$604,G58,$J$5:$J$604,"Booking.com")=0,"",_xlfn.MINIFS($M$5:$M$604,$E$5:$E$604,E58,$G$5:$G$604,G58,$J$5:$J$604,"Booking.com")) | Z58: =IF(OR(Y58="",M58="",J58="Booking.com"),"",Y58-M58) | AB58: Y | AD58: 1 room blocked
A59: 55 | B59: Nuwara Eliya | C59: 46379 | D59: 2 | E59: The Golden Ridge Hotel | F59: 5 | G59: Deluxe Room DBL 23m2 | H59: HB | I59: 1 | J59: Helanka | K59: USD | L59: 550 | M59: =IF(L59="","",IFERROR(L59*INDEX(Trip!$E$5:$E$14,MATCH(K59,Trip!$D$5:$D$14,0))/INDEX(Trip!$E$5:$E$14,MATCH(Trip!$B$10,Trip!$D$5:$D$14,0)),"")) -> 550 | N59: =IF(OR(M59="",D59=""),"",M59/D59) -> 275 | O59: =IF(M59="","",M59*I59) -> 550 | P59: 46346 | Q59: =IF(ISNUMBER(P59),P59-TODAY(),IF(P59="","",P59)) -> 44 | R59: Blocked | U59: 0.6164 | V59: =IF(M59="","",M59*(1+IF(U59="",Trip!$B$11,U59))) -> 889.02 | W59: =IF(V59="","",V59*I59) -> 889.02 | X59: =IF(OR(M59="",R59="Unavailable"),"",IF(M59=_xlfn.MINIFS($M$5:$M$604,$E$5:$E$604,E59,$G$5:$G$604,G59,$H$5:$H$604,H59,$R$5:$R$604,"<>Unavailable"),"⭐ Cheapest","")) -> ⭐ Cheapest | Y59: =IF(COUNTIFS($E$5:$E$604,E59,$G$5:$G$604,G59,$J$5:$J$604,"Booking.com")=0,"",_xlfn.MINIFS($M$5:$M$604,$E$5:$E$604,E59,$G$5:$G$604,G59,$J$5:$J$604,"Booking.com")) | Z59: =IF(OR(Y59="",M59="",J59="Booking.com"),"",Y59-M59) | AA59: Y | AD59: 2 Rooms blocked
A60: 56 | B60: Nuwara Eliya | C60: 46379 | D60: 2 | E60: The Golden Ridge Hotel | F60: 5 | G60: Mountain view suite | H60: HB | I60: 1 | J60: Helanka | K60: USD | L60: 859.05 | M60: =IF(L60="","",IFERROR(L60*INDEX(Trip!$E$5:$E$14,MATCH(K60,Trip!$D$5:$D$14,0))/INDEX(Trip!$E$5:$E$14,MATCH(Trip!$B$10,Trip!$D$5:$D$14,0)),"")) -> 859.05 | N60: =IF(OR(M60="",D60=""),"",M60/D60) -> 429.525 | O60: =IF(M60="","",M60*I60) -> 859.05 | P60: 46346 | Q60: =IF(ISNUMBER(P60),P60-TODAY(),IF(P60="","",P60)) -> 44 | R60: Blocked | U60: 0.2747 | V60: =IF(M60="","",M60*(1+IF(U60="",Trip!$B$11,U60))) -> 1095.031 | W60: =IF(V60="","",V60*I60) -> 1095.031 | X60: =IF(OR(M60="",R60="Unavailable"),"",IF(M60=_xlfn.MINIFS($M$5:$M$604,$E$5:$E$604,E60,$G$5:$G$604,G60,$H$5:$H$604,H60,$R$5:$R$604,"<>Unavailable"),"⭐ Cheapest","")) -> ⭐ Cheapest | Y60: =IF(COUNTIFS($E$5:$E$604,E60,$G$5:$G$604,G60,$J$5:$J$604,"Booking.com")=0,"",_xlfn.MINIFS($M$5:$M$604,$E$5:$E$604,E60,$G$5:$G$604,G60,$J$5:$J$604,"Booking.com")) | Z60: =IF(OR(Y60="",M60="",J60="Booking.com"),"",Y60-M60) | AC60: Y | AD60: 2 Rooms blocked
A61: 57 | B61: Nuwara Eliya | C61: 46379 | D61: 2 | E61: The Golden Ridge Hotel | F61: 5 | G61: Family Room Standard 38sqm DBL/SGL | H61: — | I61: 1 | J61: Helanka | K61: USD | L61: 1000 | M61: =IF(L61="","",IFERROR(L61*INDEX(Trip!$E$5:$E$14,MATCH(K61,Trip!$D$5:$D$14,0))/INDEX(Trip!$E$5:$E$14,MATCH(Trip!$B$10,Trip!$D$5:$D$14,0)),"")) -> 1000 | N61: =IF(OR(M61="",D61=""),"",M61/D61) -> 500 | O61: =IF(M61="","",M61*I61) -> 1000 | Q61: =IF(ISNUMBER(P61),P61-TODAY(),IF(P61="","",P61)) | R61: Quote | V61: =IF(M61="","",M61*(1+IF(U61="",Trip!$B$11,U61))) -> 1150 | W61: =IF(V61="","",V61*I61) -> 1150 | X61: =IF(OR(M61="",R61="Unavailable"),"",IF(M61=_xlfn.MINIFS($M$5:$M$604,$E$5:$E$604,E61,$G$5:$G$604,G61,$H$5:$H$604,H61,$R$5:$R$604,"<>Unavailable"),"⭐ Cheapest","")) -> ⭐ Cheapest | Y61: =IF(COUNTIFS($E$5:$E$604,E61,$G$5:$G$604,G61,$J$5:$J$604,"Booking.com")=0,"",_xlfn.MINIFS($M$5:$M$604,$E$5:$E$604,E61,$G$5:$G$604,G61,$J$5:$J$604,"Booking.com")) -> 771.09226 | Z61: =IF(OR(Y61="",M61="",J61="Booking.com"),"",Y61-M61) -> -228.90774
A62: 58 | B62: Nuwara Eliya | C62: 46379 | D62: 2 | E62: The Golden Ridge Hotel | F62: 5 | G62: Mountain View Suite SGL | H62: HB | I62: 1 | J62: Helanka | K62: USD | L62: 838.35 | M62: =IF(L62="","",IFERROR(L62*INDEX(Trip!$E$5:$E$14,MATCH(K62,Trip!$D$5:$D$14,0))/INDEX(Trip!$E$5:$E$14,MATCH(Trip!$B$10,Trip!$D$5:$D$14,0)),"")) -> 838.35 | N62: =IF(OR(M62="",D62=""),"",M62/D62) -> 419.175 | O62: =IF(M62="","",M62*I62) -> 838.35 | Q62: =IF(ISNUMBER(P62),P62-TODAY(),IF(P62="","",P62)) | R62: Quote | V62: =IF(M62="","",M62*(1+IF(U62="",Trip!$B$11,U62))) -> 964.1025 | W62: =IF(V62="","",V62*I62) -> 964.1025 | X62: =IF(OR(M62="",R62="Unavailable"),"",IF(M62=_xlfn.MINIFS($M$5:$M$604,$E$5:$E$604,E62,$G$5:$G$604,G62,$H$5:$H$604,H62,$R$5:$R$604,"<>Unavailable"),"⭐ Cheapest","")) -> ⭐ Cheapest | Y62: =IF(COUNTIFS($E$5:$E$604,E62,$G$5:$G$604,G62,$J$5:$J$604,"Booking.com")=0,"",_xlfn.MINIFS($M$5:$M$604,$E$5:$E$604,E62,$G$5:$G$604,G62,$J$5:$J$604,"Booking.com")) | Z62: =IF(OR(Y62="",M62="",J62="Booking.com"),"",Y62-M62)
A63: 59 | B63: Nuwara Eliya | C63: 46379 | D63: 2 | E63: The Golden Ridge Hotel | F63: 5 | G63: Mountain View Suite SGL | H63: HB | I63: 1 | J63: Direct | K63: USD | L63: 1095 | M63: =IF(L63="","",IFERROR(L63*INDEX(Trip!$E$5:$E$14,MATCH(K63,Trip!$D$5:$D$14,0))/INDEX(Trip!$E$5:$E$14,MATCH(Trip!$B$10,Trip!$D$5:$D$14,0)),"")) -> 1095 | N63: =IF(OR(M63="",D63=""),"",M63/D63) -> 547.5 | O63: =IF(M63="","",M63*I63) -> 1095 | Q63: =IF(ISNUMBER(P63),P63-TODAY(),IF(P63="","",P63)) | R63: Quote | V63: =IF(M63="","",M63*(1+IF(U63="",Trip!$B$11,U63))) -> 1259.25 | W63: =IF(V63="","",V63*I63) -> 1259.25 | X63: =IF(OR(M63="",R63="Unavailable"),"",IF(M63=_xlfn.MINIFS($M$5:$M$604,$E$5:$E$604,E63,$G$5:$G$604,G63,$H$5:$H$604,H63,$R$5:$R$604,"<>Unavailable"),"⭐ Cheapest","")) | Y63: =IF(COUNTIFS($E$5:$E$604,E63,$G$5:$G$604,G63,$J$5:$J$604,"Booking.com")=0,"",_xlfn.MINIFS($M$5:$M$604,$E$5:$E$604,E63,$G$5:$G$604,G63,$J$5:$J$604,"Booking.com")) | Z63: =IF(OR(Y63="",M63="",J63="Booking.com"),"",Y63-M63)
A64: 60 | B64: Nuwara Eliya | C64: 46379 | D64: 2 | E64: The Golden Ridge Hotel | F64: 5 | G64: Mountain View Suite DBL | H64: HB | I64: 1 | J64: Helanka | K64: USD | L64: 859.05 | M64: =IF(L64="","",IFERROR(L64*INDEX(Trip!$E$5:$E$14,MATCH(K64,Trip!$D$5:$D$14,0))/INDEX(Trip!$E$5:$E$14,MATCH(Trip!$B$10,Trip!$D$5:$D$14,0)),"")) -> 859.05 | N64: =IF(OR(M64="",D64=""),"",M64/D64) -> 429.525 | O64: =IF(M64="","",M64*I64) -> 859.05 | Q64: =IF(ISNUMBER(P64),P64-TODAY(),IF(P64="","",P64)) | R64: Quote | V64: =IF(M64="","",M64*(1+IF(U64="",Trip!$B$11,U64))) -> 987.9075 | W64: =IF(V64="","",V64*I64) -> 987.9075 | X64: =IF(OR(M64="",R64="Unavailable"),"",IF(M64=_xlfn.MINIFS($M$5:$M$604,$E$5:$E$604,E64,$G$5:$G$604,G64,$H$5:$H$604,H64,$R$5:$R$604,"<>Unavailable"),"⭐ Cheapest","")) -> ⭐ Cheapest | Y64: =IF(COUNTIFS($E$5:$E$604,E64,$G$5:$G$604,G64,$J$5:$J$604,"Booking.com")=0,"",_xlfn.MINIFS($M$5:$M$604,$E$5:$E$604,E64,$G$5:$G$604,G64,$J$5:$J$604,"Booking.com")) | Z64: =IF(OR(Y64="",M64="",J64="Booking.com"),"",Y64-M64)
A65: 61 | B65: Nuwara Eliya | C65: 46379 | D65: 2 | E65: The Golden Ridge Hotel | F65: 5 | G65: Mountain View Suite DBL | H65: HB | I65: 1 | J65: Direct | K65: USD | L65: 1095 | M65: =IF(L65="","",IFERROR(L65*INDEX(Trip!$E$5:$E$14,MATCH(K65,Trip!$D$5:$D$14,0))/INDEX(Trip!$E$5:$E$14,MATCH(Trip!$B$10,Trip!$D$5:$D$14,0)),"")) -> 1095 | N65: =IF(OR(M65="",D65=""),"",M65/D65) -> 547.5 | O65: =IF(M65="","",M65*I65) -> 1095 | Q65: =IF(ISNUMBER(P65),P65-TODAY(),IF(P65="","",P65)) | R65: Quote | V65: =IF(M65="","",M65*(1+IF(U65="",Trip!$B$11,U65))) -> 1259.25 | W65: =IF(V65="","",V65*I65) -> 1259.25 | X65: =IF(OR(M65="",R65="Unavailable"),"",IF(M65=_xlfn.MINIFS($M$5:$M$604,$E$5:$E$604,E65,$G$5:$G$604,G65,$H$5:$H$604,H65,$R$5:$R$604,"<>Unavailable"),"⭐ Cheapest","")) | Y65: =IF(COUNTIFS($E$5:$E$604,E65,$G$5:$G$604,G65,$J$5:$J$604,"Booking.com")=0,"",_xlfn.MINIFS($M$5:$M$604,$E$5:$E$604,E65,$G$5:$G$604,G65,$J$5:$J$604,"Booking.com")) | Z65: =IF(OR(Y65="",M65="",J65="Booking.com"),"",Y65-M65)
A66: 62 | B66: Nuwara Eliya | C66: 46379 | D66: 2 | E66: The Golden Ridge Hotel | F66: 5 | G66: Junior Suite with Mountain View 32SQM | H66: HB | I66: 1 | J66: Helanka | K66: USD | L66: 724.5 | M66: =IF(L66="","",IFERROR(L66*INDEX(Trip!$E$5:$E$14,MATCH(K66,Trip!$D$5:$D$14,0))/INDEX(Trip!$E$5:$E$14,MATCH(Trip!$B$10,Trip!$D$5:$D$14,0)),"")) -> 724.5 | N66: =IF(OR(M66="",D66=""),"",M66/D66) -> 362.25 | O66: =IF(M66="","",M66*I66) -> 724.5 | Q66: =IF(ISNUMBER(P66),P66-TODAY(),IF(P66="","",P66)) | R66: Quote | S66: =1095*2 -> 2190 | V66: =IF(M66="","",M66*(1+IF(U66="",Trip!$B$11,U66))) -> 833.175 | W66: =IF(V66="","",V66*I66) -> 833.175 | X66: =IF(OR(M66="",R66="Unavailable"),"",IF(M66=_xlfn.MINIFS($M$5:$M$604,$E$5:$E$604,E66,$G$5:$G$604,G66,$H$5:$H$604,H66,$R$5:$R$604,"<>Unavailable"),"⭐ Cheapest","")) -> ⭐ Cheapest | Y66: =IF(COUNTIFS($E$5:$E$604,E66,$G$5:$G$604,G66,$J$5:$J$604,"Booking.com")=0,"",_xlfn.MINIFS($M$5:$M$604,$E$5:$E$604,E66,$G$5:$G$604,G66,$J$5:$J$604,"Booking.com")) | Z66: =IF(OR(Y66="",M66="",J66="Booking.com"),"",Y66-M66)
A67: 63 | B67: Nuwara Eliya | C67: 46379 | D67: 2 | E67: The Golden Ridge Hotel | F67: 5 | G67: Junior Suite with Mountain View 32SQM | H67: HB | I67: 1 | J67: Direct | K67: USD | L67: 1007 | M67: =IF(L67="","",IFERROR(L67*INDEX(Trip!$E$5:$E$14,MATCH(K67,Trip!$D$5:$D$14,0))/INDEX(Trip!$E$5:$E$14,MATCH(Trip!$B$10,Trip!$D$5:$D$14,0)),"")) -> 1007 | N67: =IF(OR(M67="",D67=""),"",M67/D67) -> 503.5 | O67: =IF(M67="","",M67*I67) -> 1007 | Q67: =IF(ISNUMBER(P67),P67-TODAY(),IF(P67="","",P67)) | R67: Quote | V67: =IF(M67="","",M67*(1+IF(U67="",Trip!$B$11,U67))) -> 1158.05 | W67: =IF(V67="","",V67*I67) -> 1158.05 | X67: =IF(OR(M67="",R67="Unavailable"),"",IF(M67=_xlfn.MINIFS($M$5:$M$604,$E$5:$E$604,E67,$G$5:$G$604,G67,$H$5:$H$604,H67,$R$5:$R$604,"<>Unavailable"),"⭐ Cheapest","")) | Y67: =IF(COUNTIFS($E$5:$E$604,E67,$G$5:$G$604,G67,$J$5:$J$604,"Booking.com")=0,"",_xlfn.MINIFS($M$5:$M$604,$E$5:$E$604,E67,$G$5:$G$604,G67,$J$5:$J$604,"Booking.com")) | Z67: =IF(OR(Y67="",M67="",J67="Booking.com"),"",Y67-M67)
A68: 64 | B68: Nuwara Eliya | C68: 46379 | D68: 2 | E68: The Golden Ridge Hotel | F68: 5 | G68: Deluxe Quadruple Room with Mountain View | H68: HB | I68: 1 | J68: Helanka | K68: USD | L68: 745.2 | M68: =IF(L68="","",IFERROR(L68*INDEX(Trip!$E$5:$E$14,MATCH(K68,Trip!$D$5:$D$14,0))/INDEX(Trip!$E$5:$E$14,MATCH(Trip!$B$10,Trip!$D$5:$D$14,0)),"")) -> 745.2 | N68: =IF(OR(M68="",D68=""),"",M68/D68) -> 372.6 | O68: =IF(M68="","",M68*I68) -> 745.2 | Q68: =IF(ISNUMBER(P68),P68-TODAY(),IF(P68="","",P68)) | R68: Quote | V68: =IF(M68="","",M68*(1+IF(U68="",Trip!$B$11,U68))) -> 856.98 | W68: =IF(V68="","",V68*I68) -> 856.98 | X68: =IF(OR(M68="",R68="Unavailable"),"",IF(M68=_xlfn.MINIFS($M$5:$M$604,$E$5:$E$604,E68,$G$5:$G$604,G68,$H$5:$H$604,H68,$R$5:$R$604,"<>Unavailable"),"⭐ Cheapest","")) -> ⭐ Cheapest | Y68: =IF(COUNTIFS($E$5:$E$604,E68,$G$5:$G$604,G68,$J$5:$J$604,"Booking.com")=0,"",_xlfn.MINIFS($M$5:$M$604,$E$5:$E$604,E68,$G$5:$G$604,G68,$J$5:$J$604,"Booking.com")) | Z68: =IF(OR(Y68="",M68="",J68="Booking.com"),"",Y68-M68)
A69: 65 | B69: Nuwara Eliya | C69: 46379 | D69: 2 | E69: The Golden Ridge Hotel | F69: 5 | G69: Deluxe Quadruple Room with Mountain View | H69: HB | I69: 1 | J69: Direct | K69: USD | L69: 1120 | M69: =IF(L69="","",IFERROR(L69*INDEX(Trip!$E$5:$E$14,MATCH(K69,Trip!$D$5:$D$14,0))/INDEX(Trip!$E$5:$E$14,MATCH(Trip!$B$10,Trip!$D$5:$D$14,0)),"")) -> 1120 | N69: =IF(OR(M69="",D69=""),"",M69/D69) -> 560 | O69: =IF(M69="","",M69*I69) -> 1120 | Q69: =IF(ISNUMBER(P69),P69-TODAY(),IF(P69="","",P69)) | R69: Quote | V69: =IF(M69="","",M69*(1+IF(U69="",Trip!$B$11,U69))) -> 1288 | W69: =IF(V69="","",V69*I69) -> 1288 | X69: =IF(OR(M69="",R69="Unavailable"),"",IF(M69=_xlfn.MINIFS($M$5:$M$604,$E$5:$E$604,E69,$G$5:$G$604,G69,$H$5:$H$604,H69,$R$5:$R$604,"<>Unavailable"),"⭐ Cheapest","")) | Y69: =IF(COUNTIFS($E$5:$E$604,E69,$G$5:$G$604,G69,$J$5:$J$604,"Booking.com")=0,"",_xlfn.MINIFS($M$5:$M$604,$E$5:$E$604,E69,$G$5:$G$604,G69,$J$5:$J$604,"Booking.com")) | Z69: =IF(OR(Y69="",M69="",J69="Booking.com"),"",Y69-M69)
A70: 66 | B70: Nuwara Eliya | C70: 46379 | D70: 2 | E70: Heritance Tea Factory | F70: 5 | G70: Superior Room DBL/SGL | H70: BB | I70: 1 | J70: Ottila | K70: INR | L70: 80648 | M70: =IF(L70="","",IFERROR(L70*INDEX(Trip!$E$5:$E$14,MATCH(K70,Trip!$D$5:$D$14,0))/INDEX(Trip!$E$5:$E$14,MATCH(Trip!$B$10,Trip!$D$5:$D$14,0)),"")) -> 855.228 | N70: =IF(OR(M70="",D70=""),"",M70/D70) -> 427.614 | O70: =IF(M70="","",M70*I70) -> 855.228 | P70: 46355 | Q70: =IF(ISNUMBER(P70),P70-TODAY(),IF(P70="","",P70)) -> 53 | R70: Quote | T70: Upg 1 | V70: =IF(M70="","",M70*(1+IF(U70="",Trip!$B$11,U70))) -> 983.5122 | W70: =IF(V70="","",V70*I70) -> 983.5122 | X70: =IF(OR(M70="",R70="Unavailable"),"",IF(M70=_xlfn.MINIFS($M$5:$M$604,$E$5:$E$604,E70,$G$5:$G$604,G70,$H$5:$H$604,H70,$R$5:$R$604,"<>Unavailable"),"⭐ Cheapest","")) -> ⭐ Cheapest | Y70: =IF(COUNTIFS($E$5:$E$604,E70,$G$5:$G$604,G70,$J$5:$J$604,"Booking.com")=0,"",_xlfn.MINIFS($M$5:$M$604,$E$5:$E$604,E70,$G$5:$G$604,G70,$J$5:$J$604,"Booking.com")) -> 875.13256 | Z70: =IF(OR(Y70="",M70="",J70="Booking.com"),"",Y70-M70) -> 19.90456
A71: 67 | B71: Nuwara Eliya | C71: 46379 | D71: 2 | E71: Heritance Tea Factory | F71: 5 | G71: Superior Room DBL/SGL | H71: BB | I71: 1 | J71: Booking.com | K71: INR | L71: 82525 | M71: =IF(L71="","",IFERROR(L71*INDEX(Trip!$E$5:$E$14,MATCH(K71,Trip!$D$5:$D$14,0))/INDEX(Trip!$E$5:$E$14,MATCH(Trip!$B$10,Trip!$D$5:$D$14,0)),"")) -> 875.13256 | N71: =IF(OR(M71="",D71=""),"",M71/D71) -> 437.56628 | O71: =IF(M71="","",M71*I71) -> 875.13256 | P71: 46371 | Q71: =IF(ISNUMBER(P71),P71-TODAY(),IF(P71="","",P71)) -> 69 | R71: Quote | V71: =IF(M71="","",M71*(1+IF(U71="",Trip!$B$11,U71))) -> 1006.4024 | W71: =IF(V71="","",V71*I71) -> 1006.4024 | X71: =IF(OR(M71="",R71="Unavailable"),"",IF(M71=_xlfn.MINIFS($M$5:$M$604,$E$5:$E$604,E71,$G$5:$G$604,G71,$H$5:$H$604,H71,$R$5:$R$604,"<>Unavailable"),"⭐ Cheapest","")) | Y71: =IF(COUNTIFS($E$5:$E$604,E71,$G$5:$G$604,G71,$J$5:$J$604,"Booking.com")=0,"",_xlfn.MINIFS($M$5:$M$604,$E$5:$E$604,E71,$G$5:$G$604,G71,$J$5:$J$604,"Booking.com")) -> 875.13256 | Z71: =IF(OR(Y71="",M71="",J71="Booking.com"),"",Y71-M71)
A72: 68 | B72: Nuwara Eliya | C72: 46379 | D72: 2 | E72: The Bellwood Manor | F72: 5 | G72: Deluxe Double Room, 1 King Bed, Fireplace, Garden View (1 King Bed) 31sqm DBL/SGL | H72: HB | I72: 1 | J72: Ottila | K72: INR | L72: 94994 | M72: =IF(L72="","",IFERROR(L72*INDEX(Trip!$E$5:$E$14,MATCH(K72,Trip!$D$5:$D$14,0))/INDEX(Trip!$E$5:$E$14,MATCH(Trip!$B$10,Trip!$D$5:$D$14,0)),"")) -> 1007.3595 | N72: =IF(OR(M72="",D72=""),"",M72/D72) -> 503.67975 | O72: =IF(M72="","",M72*I72) -> 1007.3595 | P72: 46372 | Q72: =IF(ISNUMBER(P72),P72-TODAY(),IF(P72="","",P72)) -> 70 | R72: Quote | T72: Upg 2 | V72: =IF(M72="","",M72*(1+IF(U72="",Trip!$B$11,U72))) -> 1158.4634 | W72: =IF(V72="","",V72*I72) -> 1158.4634 | X72: =IF(OR(M72="",R72="Unavailable"),"",IF(M72=_xlfn.MINIFS($M$5:$M$604,$E$5:$E$604,E72,$G$5:$G$604,G72,$H$5:$H$604,H72,$R$5:$R$604,"<>Unavailable"),"⭐ Cheapest","")) -> ⭐ Cheapest | Y72: =IF(COUNTIFS($E$5:$E$604,E72,$G$5:$G$604,G72,$J$5:$J$604,"Booking.com")=0,"",_xlfn.MINIFS($M$5:$M$604,$E$5:$E$604,E72,$G$5:$G$604,G72,$J$5:$J$604,"Booking.com")) -> 1126.5854 | Z72: =IF(OR(Y72="",M72="",J72="Booking.com"),"",Y72-M72) -> 119.22587
A73: 69 | B73: Nuwara Eliya | C73: 46379 | D73: 2 | E73: The Bellwood Manor | F73: 5 | G73: Deluxe Double Room, 1 King Bed, Fireplace, Garden View (1 King Bed) 31sqm DBL/SGL | H73: HB | I73: 1 | J73: Booking.com | K73: INR | L73: 106237 | M73: =IF(L73="","",IFERROR(L73*INDEX(Trip!$E$5:$E$14,MATCH(K73,Trip!$D$5:$D$14,0))/INDEX(Trip!$E$5:$E$14,MATCH(Trip!$B$10,Trip!$D$5:$D$14,0)),"")) -> 1126.5854 | N73: =IF(OR(M73="",D73=""),"",M73/D73) -> 563.29268 | O73: =IF(M73="","",M73*I73) -> 1126.5854 | P73: 46276 | Q73: =IF(ISNUMBER(P73),P73-TODAY(),IF(P73="","",P73)) -> -26 | R73: Quote | V73: =IF(M73="","",M73*(1+IF(U73="",Trip!$B$11,U73))) -> 1295.5732 | W73: =IF(V73="","",V73*I73) -> 1295.5732 | X73: =IF(OR(M73="",R73="Unavailable"),"",IF(M73=_xlfn.MINIFS($M$5:$M$604,$E$5:$E$604,E73,$G$5:$G$604,G73,$H$5:$H$604,H73,$R$5:$R$604,"<>Unavailable"),"⭐ Cheapest","")) | Y73: =IF(COUNTIFS($E$5:$E$604,E73,$G$5:$G$604,G73,$J$5:$J$604,"Booking.com")=0,"",_xlfn.MINIFS($M$5:$M$604,$E$5:$E$604,E73,$G$5:$G$604,G73,$J$5:$J$604,"Booking.com")) -> 1126.5854 | Z73: =IF(OR(Y73="",M73="",J73="Booking.com"),"",Y73-M73)
A74: 70 | B74: Nuwara Eliya | C74: 46379 | D74: 2 | E74: 1 Junior Double Room, 1 King Bed, Bathtub, Garden View | G74: — | H74: HB | I74: 1 | J74: Ottila | K74: USD | L74: 1362 | M74: =IF(L74="","",IFERROR(L74*INDEX(Trip!$E$5:$E$14,MATCH(K74,Trip!$D$5:$D$14,0))/INDEX(Trip!$E$5:$E$14,MATCH(Trip!$B$10,Trip!$D$5:$D$14,0)),"")) -> 1362 | N74: =IF(OR(M74="",D74=""),"",M74/D74) -> 681 | O74: =IF(M74="","",M74*I74) -> 1362 | Q74: =IF(ISNUMBER(P74),P74-TODAY(),IF(P74="","",P74)) | R74: Quote | T74: Upg 2 | V74: =IF(M74="","",M74*(1+IF(U74="",Trip!$B$11,U74))) -> 1566.3 | W74: =IF(V74="","",V74*I74) -> 1566.3 | X74: =IF(OR(M74="",R74="Unavailable"),"",IF(M74=_xlfn.MINIFS($M$5:$M$604,$E$5:$E$604,E74,$G$5:$G$604,G74,$H$5:$H$604,H74,$R$5:$R$604,"<>Unavailable"),"⭐ Cheapest","")) -> ⭐ Cheapest | Y74: =IF(COUNTIFS($E$5:$E$604,E74,$G$5:$G$604,G74,$J$5:$J$604,"Booking.com")=0,"",_xlfn.MINIFS($M$5:$M$604,$E$5:$E$604,E74,$G$5:$G$604,G74,$J$5:$J$604,"Booking.com")) -> 1447 | Z74: =IF(OR(Y74="",M74="",J74="Booking.com"),"",Y74-M74) -> 85
A75: 71 | B75: Nuwara Eliya | C75: 46379 | D75: 2 | E75: 1 Junior Double Room, 1 King Bed, Bathtub, Garden View | G75: — | H75: HB | I75: 1 | J75: Booking.com | K75: USD | L75: 1447 | M75: =IF(L75="","",IFERROR(L75*INDEX(Trip!$E$5:$E$14,MATCH(K75,Trip!$D$5:$D$14,0))/INDEX(Trip!$E$5:$E$14,MATCH(Trip!$B$10,Trip!$D$5:$D$14,0)),"")) -> 1447 | N75: =IF(OR(M75="",D75=""),"",M75/D75) -> 723.5 | O75: =IF(M75="","",M75*I75) -> 1447 | Q75: =IF(ISNUMBER(P75),P75-TODAY(),IF(P75="","",P75)) | R75: Quote | V75: =IF(M75="","",M75*(1+IF(U75="",Trip!$B$11,U75))) -> 1664.05 | W75: =IF(V75="","",V75*I75) -> 1664.05 | X75: =IF(OR(M75="",R75="Unavailable"),"",IF(M75=_xlfn.MINIFS($M$5:$M$604,$E$5:$E$604,E75,$G$5:$G$604,G75,$H$5:$H$604,H75,$R$5:$R$604,"<>Unavailable"),"⭐ Cheapest","")) | Y75: =IF(COUNTIFS($E$5:$E$604,E75,$G$5:$G$604,G75,$J$5:$J$604,"Booking.com")=0,"",_xlfn.MINIFS($M$5:$M$604,$E$5:$E$604,E75,$G$5:$G$604,G75,$J$5:$J$604,"Booking.com")) -> 1447 | Z75: =IF(OR(Y75="",M75="",J75="Booking.com"),"",Y75-M75)
A76: 72 | B76: Nuwara Eliya | C76: 46379 | D76: 2 | E76: Goatfell Nuwara Eliya | F76: 4 | G76: Concordia, Twin Beds DBL 42sqm | H76: AI | I76: 1 | J76: Ottila | K76: INR | L76: 253060 | M76: =IF(L76="","",IFERROR(L76*INDEX(Trip!$E$5:$E$14,MATCH(K76,Trip!$D$5:$D$14,0))/INDEX(Trip!$E$5:$E$14,MATCH(Trip!$B$10,Trip!$D$5:$D$14,0)),"")) -> 2683.5631 | N76: =IF(OR(M76="",D76=""),"",M76/D76) -> 1341.7815 | O76: =IF(M76="","",M76*I76) -> 2683.5631 | P76: 46318 | Q76: =IF(ISNUMBER(P76),P76-TODAY(),IF(P76="","",P76)) -> 16 | R76: Quote | T76: Upg 4 | V76: =IF(M76="","",M76*(1+IF(U76="",Trip!$B$11,U76))) -> 3086.0976 | W76: =IF(V76="","",V76*I76) -> 3086.0976 | X76: =IF(OR(M76="",R76="Unavailable"),"",IF(M76=_xlfn.MINIFS($M$5:$M$604,$E$5:$E$604,E76,$G$5:$G$604,G76,$H$5:$H$604,H76,$R$5:$R$604,"<>Unavailable"),"⭐ Cheapest","")) -> ⭐ Cheapest | Y76: =IF(COUNTIFS($E$5:$E$604,E76,$G$5:$G$604,G76,$J$5:$J$604,"Booking.com")=0,"",_xlfn.MINIFS($M$5:$M$604,$E$5:$E$604,E76,$G$5:$G$604,G76,$J$5:$J$604,"Booking.com")) -> 2981.9936 | Z76: =IF(OR(Y76="",M76="",J76="Booking.com"),"",Y76-M76) -> 298.43054
A77: 73 | B77: Nuwara Eliya | C77: 46379 | D77: 2 | E77: Goatfell Nuwara Eliya | F77: 4 | G77: Concordia, Twin Beds DBL 42sqm | H77: AI | I77: 1 | J77: Booking.com | K77: INR | L77: 281202 | M77: =IF(L77="","",IFERROR(L77*INDEX(Trip!$E$5:$E$14,MATCH(K77,Trip!$D$5:$D$14,0))/INDEX(Trip!$E$5:$E$14,MATCH(Trip!$B$10,Trip!$D$5:$D$14,0)),"")) -> 2981.9936 | N77: =IF(OR(M77="",D77=""),"",M77/D77) -> 1490.9968 | O77: =IF(M77="","",M77*I77) -> 2981.9936 | P77: 46348 | Q77: =IF(ISNUMBER(P77),P77-TODAY(),IF(P77="","",P77)) -> 46 | R77: Quote | V77: =IF(M77="","",M77*(1+IF(U77="",Trip!$B$11,U77))) -> 3429.2927 | W77: =IF(V77="","",V77*I77) -> 3429.2927 | X77: =IF(OR(M77="",R77="Unavailable"),"",IF(M77=_xlfn.MINIFS($M$5:$M$604,$E$5:$E$604,E77,$G$5:$G$604,G77,$H$5:$H$604,H77,$R$5:$R$604,"<>Unavailable"),"⭐ Cheapest","")) | Y77: =IF(COUNTIFS($E$5:$E$604,E77,$G$5:$G$604,G77,$J$5:$J$604,"Booking.com")=0,"",_xlfn.MINIFS($M$5:$M$604,$E$5:$E$604,E77,$G$5:$G$604,G77,$J$5:$J$604,"Booking.com")) -> 2981.9936 | Z77: =IF(OR(Y77="",M77="",J77="Booking.com"),"",Y77-M77)
A78: 74 | B78: Nuwara Eliya | C78: 46379 | D78: 2 | E78: Goatfell Nuwara Eliya | F78: 4 | G78: Concordia, Twin Beds SGL | H78: AI | I78: 1 | J78: Ottila | K78: INR | L78: 228431 | M78: =IF(L78="","",IFERROR(L78*INDEX(Trip!$E$5:$E$14,MATCH(K78,Trip!$D$5:$D$14,0))/INDEX(Trip!$E$5:$E$14,MATCH(Trip!$B$10,Trip!$D$5:$D$14,0)),"")) -> 2422.386 | N78: =IF(OR(M78="",D78=""),"",M78/D78) -> 1211.193 | O78: =IF(M78="","",M78*I78) -> 2422.386 | P78: 46318 | Q78: =IF(ISNUMBER(P78),P78-TODAY(),IF(P78="","",P78)) -> 16 | R78: Quote | V78: =IF(M78="","",M78*(1+IF(U78="",Trip!$B$11,U78))) -> 2785.7439 | W78: =IF(V78="","",V78*I78) -> 2785.7439 | X78: =IF(OR(M78="",R78="Unavailable"),"",IF(M78=_xlfn.MINIFS($M$5:$M$604,$E$5:$E$604,E78,$G$5:$G$604,G78,$H$5:$H$604,H78,$R$5:$R$604,"<>Unavailable"),"⭐ Cheapest","")) -> ⭐ Cheapest | Y78: =IF(COUNTIFS($E$5:$E$604,E78,$G$5:$G$604,G78,$J$5:$J$604,"Booking.com")=0,"",_xlfn.MINIFS($M$5:$M$604,$E$5:$E$604,E78,$G$5:$G$604,G78,$J$5:$J$604,"Booking.com")) -> 2691.7709 | Z78: =IF(OR(Y78="",M78="",J78="Booking.com"),"",Y78-M78) -> 269.38494
A79: 75 | B79: Nuwara Eliya | C79: 46379 | D79: 2 | E79: Goatfell Nuwara Eliya | F79: 4 | G79: Concordia, Twin Beds SGL | H79: AI | I79: 1 | J79: Booking.com | K79: INR | L79: 253834 | M79: =IF(L79="","",IFERROR(L79*INDEX(Trip!$E$5:$E$14,MATCH(K79,Trip!$D$5:$D$14,0))/INDEX(Trip!$E$5:$E$14,MATCH(Trip!$B$10,Trip!$D$5:$D$14,0)),"")) -> 2691.7709 | N79: =IF(OR(M79="",D79=""),"",M79/D79) -> 1345.8855 | O79: =IF(M79="","",M79*I79) -> 2691.7709 | P79: 46348 | Q79: =IF(ISNUMBER(P79),P79-TODAY(),IF(P79="","",P79)) -> 46 | R79: Quote | V79: =IF(M79="","",M79*(1+IF(U79="",Trip!$B$11,U79))) -> 3095.5366 | W79: =IF(V79="","",V79*I79) -> 3095.5366 | X79: =IF(OR(M79="",R79="Unavailable"),"",IF(M79=_xlfn.MINIFS($M$5:$M$604,$E$5:$E$604,E79,$G$5:$G$604,G79,$H$5:$H$604,H79,$R$5:$R$604,"<>Unavailable"),"⭐ Cheapest","")) | Y79: =IF(COUNTIFS($E$5:$E$604,E79,$G$5:$G$604,G79,$J$5:$J$604,"Booking.com")=0,"",_xlfn.MINIFS($M$5:$M$604,$E$5:$E$604,E79,$G$5:$G$604,G79,$J$5:$J$604,"Booking.com")) -> 2691.7709 | Z79: =IF(OR(Y79="",M79="",J79="Booking.com"),"",Y79-M79)
A80: 76 | B80: Nuwara Eliya | C80: 46379 | D80: 2 | E80: The Westbury Palace | G80: Prestige Deluxe Room 35sqmt | H80: BB | I80: 1 | J80: Ottila | K80: USD | L80: 752 | M80: =IF(L80="","",IFERROR(L80*INDEX(Trip!$E$5:$E$14,MATCH(K80,Trip!$D$5:$D$14,0))/INDEX(Trip!$E$5:$E$14,MATCH(Trip!$B$10,Trip!$D$5:$D$14,0)),"")) -> 752 | N80: =IF(OR(M80="",D80=""),"",M80/D80) -> 376 | O80: =IF(M80="","",M80*I80) -> 752 | P80: 46374 | Q80: =IF(ISNUMBER(P80),P80-TODAY(),IF(P80="","",P80)) -> 72 | R80: Quote | T80: Base | V80: =IF(M80="","",M80*(1+IF(U80="",Trip!$B$11,U80))) -> 864.8 | W80: =IF(V80="","",V80*I80) -> 864.8 | X80: =IF(OR(M80="",R80="Unavailable"),"",IF(M80=_xlfn.MINIFS($M$5:$M$604,$E$5:$E$604,E80,$G$5:$G$604,G80,$H$5:$H$604,H80,$R$5:$R$604,"<>Unavailable"),"⭐ Cheapest","")) -> ⭐ Cheapest | Y80: =IF(COUNTIFS($E$5:$E$604,E80,$G$5:$G$604,G80,$J$5:$J$604,"Booking.com")=0,"",_xlfn.MINIFS($M$5:$M$604,$E$5:$E$604,E80,$G$5:$G$604,G80,$J$5:$J$604,"Booking.com")) -> 923 | Z80: =IF(OR(Y80="",M80="",J80="Booking.com"),"",Y80-M80) -> 171
A81: 77 | B81: Nuwara Eliya | C81: 46379 | D81: 2 | E81: The Westbury Palace | G81: Prestige Deluxe Room 35sqmt | H81: BB | I81: 1 | J81: Booking.com | K81: USD | L81: 923 | M81: =IF(L81="","",IFERROR(L81*INDEX(Trip!$E$5:$E$14,MATCH(K81,Trip!$D$5:$D$14,0))/INDEX(Trip!$E$5:$E$14,MATCH(Trip!$B$10,Trip!$D$5:$D$14,0)),"")) -> 923 | N81: =IF(OR(M81="",D81=""),"",M81/D81) -> 461.5 | O81: =IF(M81="","",M81*I81) -> 923 | Q81: =IF(ISNUMBER(P81),P81-TODAY(),IF(P81="","",P81)) | R81: Quote | V81: =IF(M81="","",M81*(1+IF(U81="",Trip!$B$11,U81))) -> 1061.45 | W81: =IF(V81="","",V81*I81) -> 1061.45 | X81: =IF(OR(M81="",R81="Unavailable"),"",IF(M81=_xlfn.MINIFS($M$5:$M$604,$E$5:$E$604,E81,$G$5:$G$604,G81,$H$5:$H$604,H81,$R$5:$R$604,"<>Unavailable"),"⭐ Cheapest","")) | Y81: =IF(COUNTIFS($E$5:$E$604,E81,$G$5:$G$604,G81,$J$5:$J$604,"Booking.com")=0,"",_xlfn.MINIFS($M$5:$M$604,$E$5:$E$604,E81,$G$5:$G$604,G81,$J$5:$J$604,"Booking.com")) -> 923 | Z81: =IF(OR(Y81="",M81="",J81="Booking.com"),"",Y81-M81)
A82: 78 | B82: Nuwara Eliya | C82: 46379 | D82: 2 | E82: Oliphant Boutique Villa by Amaya | G82: Luxury Double Room 34sqmt | H82: — | I82: 1 | J82: Direct | K82: USD | L82: 766 | M82: =IF(L82="","",IFERROR(L82*INDEX(Trip!$E$5:$E$14,MATCH(K82,Trip!$D$5:$D$14,0))/INDEX(Trip!$E$5:$E$14,MATCH(Trip!$B$10,Trip!$D$5:$D$14,0)),"")) -> 766 | N82: =IF(OR(M82="",D82=""),"",M82/D82) -> 383 | O82: =IF(M82="","",M82*I82) -> 766 | Q82: =IF(ISNUMBER(P82),P82-TODAY(),IF(P82="","",P82)) | R82: Quote | V82: =IF(M82="","",M82*(1+IF(U82="",Trip!$B$11,U82))) -> 880.9 | W82: =IF(V82="","",V82*I82) -> 880.9 | X82: =IF(OR(M82="",R82="Unavailable"),"",IF(M82=_xlfn.MINIFS($M$5:$M$604,$E$5:$E$604,E82,$G$5:$G$604,G82,$H$5:$H$604,H82,$R$5:$R$604,"<>Unavailable"),"⭐ Cheapest","")) -> ⭐ Cheapest | Y82: =IF(COUNTIFS($E$5:$E$604,E82,$G$5:$G$604,G82,$J$5:$J$604,"Booking.com")=0,"",_xlfn.MINIFS($M$5:$M$604,$E$5:$E$604,E82,$G$5:$G$604,G82,$J$5:$J$604,"Booking.com")) | Z82: =IF(OR(Y82="",M82="",J82="Booking.com"),"",Y82-M82)
A83: 79 | B83: Ella | C83: 46381 | D83: 2 | E83: Ekho Ella | F83: 4 | G83: Premier Room 34m2 | H83: HB | I83: 1 | J83: Ottila | K83: INR | L83: 88523 | M83: =IF(L83="","",IFERROR(L83*INDEX(Trip!$E$5:$E$14,MATCH(K83,Trip!$D$5:$D$14,0))/INDEX(Trip!$E$5:$E$14,MATCH(Trip!$B$10,Trip!$D$5:$D$14,0)),"")) -> 938.73807 | N83: =IF(OR(M83="",D83=""),"",M83/D83) -> 469.36903 | O83: =IF(M83="","",M83*I83) -> 938.73807 | P83: 46373 | Q83: =IF(ISNUMBER(P83),P83-TODAY(),IF(P83="","",P83)) -> 71 | R83: Quote | T83: Base | V83: =IF(M83="","",M83*(1+IF(U83="",Trip!$B$11,U83))) -> 1079.5488 | W83: =IF(V83="","",V83*I83) -> 1079.5488 | X83: =IF(OR(M83="",R83="Unavailable"),"",IF(M83=_xlfn.MINIFS($M$5:$M$604,$E$5:$E$604,E83,$G$5:$G$604,G83,$H$5:$H$604,H83,$R$5:$R$604,"<>Unavailable"),"⭐ Cheapest","")) -> ⭐ Cheapest | Y83: =IF(COUNTIFS($E$5:$E$604,E83,$G$5:$G$604,G83,$J$5:$J$604,"Booking.com")=0,"",_xlfn.MINIFS($M$5:$M$604,$E$5:$E$604,E83,$G$5:$G$604,G83,$J$5:$J$604,"Booking.com")) -> 1461 | Z83: =IF(OR(Y83="",M83="",J83="Booking.com"),"",Y83-M83) -> 522.26193
A84: 80 | B84: Ella | C84: 46381 | D84: 2 | E84: Ekho Ella | F84: 4 | G84: Premier Room 34m2 | H84: HB | I84: 1 | J84: Booking.com | K84: USD | L84: 1461 | M84: =IF(L84="","",IFERROR(L84*INDEX(Trip!$E$5:$E$14,MATCH(K84,Trip!$D$5:$D$14,0))/INDEX(Trip!$E$5:$E$14,MATCH(Trip!$B$10,Trip!$D$5:$D$14,0)),"")) -> 1461 | N84: =IF(OR(M84="",D84=""),"",M84/D84) -> 730.5 | O84: =IF(M84="","",M84*I84) -> 1461 | P84: 46378 | Q84: =IF(ISNUMBER(P84),P84-TODAY(),IF(P84="","",P84)) -> 76 | R84: Quote | V84: =IF(M84="","",M84*(1+IF(U84="",Trip!$B$11,U84))) -> 1680.15 | W84: =IF(V84="","",V84*I84) -> 1680.15 | X84: =IF(OR(M84="",R84="Unavailable"),"",IF(M84=_xlfn.MINIFS($M$5:$M$604,$E$5:$E$604,E84,$G$5:$G$604,G84,$H$5:$H$604,H84,$R$5:$R$604,"<>Unavailable"),"⭐ Cheapest","")) | Y84: =IF(COUNTIFS($E$5:$E$604,E84,$G$5:$G$604,G84,$J$5:$J$604,"Booking.com")=0,"",_xlfn.MINIFS($M$5:$M$604,$E$5:$E$604,E84,$G$5:$G$604,G84,$J$5:$J$604,"Booking.com")) -> 1461 | Z84: =IF(OR(Y84="",M84="",J84="Booking.com"),"",Y84-M84)
A85: 81 | B85: Ella | C85: 46381 | D85: 2 | E85: 98 Acres Resort And Spa | F85: 5 | G85: Premium Room 46m2 | H85: BB | I85: 1 | J85: Ottila | K85: INR | L85: 175141 | M85: =IF(L85="","",IFERROR(L85*INDEX(Trip!$E$5:$E$14,MATCH(K85,Trip!$D$5:$D$14,0))/INDEX(Trip!$E$5:$E$14,MATCH(Trip!$B$10,Trip!$D$5:$D$14,0)),"")) -> 1857.2747 | N85: =IF(OR(M85="",D85=""),"",M85/D85) -> 928.63733 | O85: =IF(M85="","",M85*I85) -> 1857.2747 | P85: 46369 | Q85: =IF(ISNUMBER(P85),P85-TODAY(),IF(P85="","",P85)) -> 67 | R85: Quote | T85: Upg 2 | V85: =IF(M85="","",M85*(1+IF(U85="",Trip!$B$11,U85))) -> 2135.8659 | W85: =IF(V85="","",V85*I85) -> 2135.8659 | X85: =IF(OR(M85="",R85="Unavailable"),"",IF(M85=_xlfn.MINIFS($M$5:$M$604,$E$5:$E$604,E85,$G$5:$G$604,G85,$H$5:$H$604,H85,$R$5:$R$604,"<>Unavailable"),"⭐ Cheapest","")) -> ⭐ Cheapest | Y85: =IF(COUNTIFS($E$5:$E$604,E85,$G$5:$G$604,G85,$J$5:$J$604,"Booking.com")=0,"",_xlfn.MINIFS($M$5:$M$604,$E$5:$E$604,E85,$G$5:$G$604,G85,$J$5:$J$604,"Booking.com")) -> 2275.2492 | Z85: =IF(OR(Y85="",M85="",J85="Booking.com"),"",Y85-M85) -> 417.97455
A86: 82 | B86: Ella | C86: 46381 | D86: 2 | E86: 98 Acres Resort And Spa | F86: 5 | G86: Premium Room 46m2 | H86: BB | I86: 1 | J86: Booking.com | K86: INR | L86: 214556 | M86: =IF(L86="","",IFERROR(L86*INDEX(Trip!$E$5:$E$14,MATCH(K86,Trip!$D$5:$D$14,0))/INDEX(Trip!$E$5:$E$14,MATCH(Trip!$B$10,Trip!$D$5:$D$14,0)),"")) -> 2275.2492 | N86: =IF(OR(M86="",D86=""),"",M86/D86) -> 1137.6246 | O86: =IF(M86="","",M86*I86) -> 2275.2492 | P86: 46349 | Q86: =IF(ISNUMBER(P86),P86-TODAY(),IF(P86="","",P86)) -> 47 | R86: Quote | V86: =IF(M86="","",M86*(1+IF(U86="",Trip!$B$11,U86))) -> 2616.5366 | W86: =IF(V86="","",V86*I86) -> 2616.5366 | X86: =IF(OR(M86="",R86="Unavailable"),"",IF(M86=_xlfn.MINIFS($M$5:$M$604,$E$5:$E$604,E86,$G$5:$G$604,G86,$H$5:$H$604,H86,$R$5:$R$604,"<>Unavailable"),"⭐ Cheapest","")) | Y86: =IF(COUNTIFS($E$5:$E$604,E86,$G$5:$G$604,G86,$J$5:$J$604,"Booking.com")=0,"",_xlfn.MINIFS($M$5:$M$604,$E$5:$E$604,E86,$G$5:$G$604,G86,$J$5:$J$604,"Booking.com")) -> 2275.2492 | Z86: =IF(OR(Y86="",M86="",J86="Booking.com"),"",Y86-M86)
A87: 83 | B87: Ella | C87: 46381 | D87: 2 | E87: Newburgh Ella - The Tea Factory Resort | G87: Golden Tip Room 32M2 DBL/SGL | H87: BB | I87: 1 | J87: Direct | K87: USD | L87: 1283 | M87: =IF(L87="","",IFERROR(L87*INDEX(Trip!$E$5:$E$14,MATCH(K87,Trip!$D$5:$D$14,0))/INDEX(Trip!$E$5:$E$14,MATCH(Trip!$B$10,Trip!$D$5:$D$14,0)),"")) -> 1283 | N87: =IF(OR(M87="",D87=""),"",M87/D87) -> 641.5 | O87: =IF(M87="","",M87*I87) -> 1283 | P87: NRF | Q87: =IF(ISNUMBER(P87),P87-TODAY(),IF(P87="","",P87)) -> NRF | R87: Quote | V87: =IF(M87="","",M87*(1+IF(U87="",Trip!$B$11,U87))) -> 1475.45 | W87: =IF(V87="","",V87*I87) -> 1475.45 | X87: =IF(OR(M87="",R87="Unavailable"),"",IF(M87=_xlfn.MINIFS($M$5:$M$604,$E$5:$E$604,E87,$G$5:$G$604,G87,$H$5:$H$604,H87,$R$5:$R$604,"<>Unavailable"),"⭐ Cheapest","")) -> ⭐ Cheapest | Y87: =IF(COUNTIFS($E$5:$E$604,E87,$G$5:$G$604,G87,$J$5:$J$604,"Booking.com")=0,"",_xlfn.MINIFS($M$5:$M$604,$E$5:$E$604,E87,$G$5:$G$604,G87,$J$5:$J$604,"Booking.com")) -> 1359.8409 | Z87: =IF(OR(Y87="",M87="",J87="Booking.com"),"",Y87-M87) -> 76.840933
A88: 84 | B88: Ella | C88: 46381 | D88: 2 | E88: Newburgh Ella - The Tea Factory Resort | G88: Golden Tip Room 32M2 DBL/SGL | H88: BB | I88: 1 | J88: Booking.com | K88: INR | L88: 128233 | M88: =IF(L88="","",IFERROR(L88*INDEX(Trip!$E$5:$E$14,MATCH(K88,Trip!$D$5:$D$14,0))/INDEX(Trip!$E$5:$E$14,MATCH(Trip!$B$10,Trip!$D$5:$D$14,0)),"")) -> 1359.8409 | N88: =IF(OR(M88="",D88=""),"",M88/D88) -> 679.92047 | O88: =IF(M88="","",M88*I88) -> 1359.8409 | P88: 46373 | Q88: =IF(ISNUMBER(P88),P88-TODAY(),IF(P88="","",P88)) -> 71 | R88: Quote | V88: =IF(M88="","",M88*(1+IF(U88="",Trip!$B$11,U88))) -> 1563.8171 | W88: =IF(V88="","",V88*I88) -> 1563.8171 | X88: =IF(OR(M88="",R88="Unavailable"),"",IF(M88=_xlfn.MINIFS($M$5:$M$604,$E$5:$E$604,E88,$G$5:$G$604,G88,$H$5:$H$604,H88,$R$5:$R$604,"<>Unavailable"),"⭐ Cheapest","")) | Y88: =IF(COUNTIFS($E$5:$E$604,E88,$G$5:$G$604,G88,$J$5:$J$604,"Booking.com")=0,"",_xlfn.MINIFS($M$5:$M$604,$E$5:$E$604,E88,$G$5:$G$604,G88,$J$5:$J$604,"Booking.com")) -> 1359.8409 | Z88: =IF(OR(Y88="",M88="",J88="Booking.com"),"",Y88-M88)
A89: 85 | B89: Ella | C89: 46381 | D89: 2 | E89: Newburgh Ella - The Tea Factory Resort | G89: golden tip Single Room | H89: HB | I89: 1 | J89: Helanka | K89: USD | L89: 1019.88 | M89: =IF(L89="","",IFERROR(L89*INDEX(Trip!$E$5:$E$14,MATCH(K89,Trip!$D$5:$D$14,0))/INDEX(Trip!$E$5:$E$14,MATCH(Trip!$B$10,Trip!$D$5:$D$14,0)),"")) -> 1019.88 | N89: =IF(OR(M89="",D89=""),"",M89/D89) -> 509.94 | O89: =IF(M89="","",M89*I89) -> 1019.88 | P89: 46320 | Q89: =IF(ISNUMBER(P89),P89-TODAY(),IF(P89="","",P89)) -> 18 | R89: Blocked | S89: GTTE000799 | U89: 0.1511 | V89: =IF(M89="","",M89*(1+IF(U89="",Trip!$B$11,U89))) -> 1173.9839 | W89: =IF(V89="","",V89*I89) -> 1173.9839 | X89: =IF(OR(M89="",R89="Unavailable"),"",IF(M89=_xlfn.MINIFS($M$5:$M$604,$E$5:$E$604,E89,$G$5:$G$604,G89,$H$5:$H$604,H89,$R$5:$R$604,"<>Unavailable"),"⭐ Cheapest","")) -> ⭐ Cheapest | Y89: =IF(COUNTIFS($E$5:$E$604,E89,$G$5:$G$604,G89,$J$5:$J$604,"Booking.com")=0,"",_xlfn.MINIFS($M$5:$M$604,$E$5:$E$604,E89,$G$5:$G$604,G89,$J$5:$J$604,"Booking.com")) | Z89: =IF(OR(Y89="",M89="",J89="Booking.com"),"",Y89-M89) | AB89: Y
A90: 86 | B90: Ella | C90: 46381 | D90: 2 | E90: Newburgh Ella - The Tea Factory Resort | G90: golden tip dbl room | H90: HB | I90: 1 | J90: Helanka | K90: USD | L90: 1066 | M90: =IF(L90="","",IFERROR(L90*INDEX(Trip!$E$5:$E$14,MATCH(K90,Trip!$D$5:$D$14,0))/INDEX(Trip!$E$5:$E$14,MATCH(Trip!$B$10,Trip!$D$5:$D$14,0)),"")) -> 1066 | N90: =IF(OR(M90="",D90=""),"",M90/D90) -> 533 | O90: =IF(M90="","",M90*I90) -> 1066 | P90: 46320 | Q90: =IF(ISNUMBER(P90),P90-TODAY(),IF(P90="","",P90)) -> 18 | R90: Blocked | S90: GTTE000799 | U90: 0.151 | V90: =IF(M90="","",M90*(1+IF(U90="",Trip!$B$11,U90))) -> 1226.966 | W90: =IF(V90="","",V90*I90) -> 1226.966 | X90: =IF(OR(M90="",R90="Unavailable"),"",IF(M90=_xlfn.MINIFS($M$5:$M$604,$E$5:$E$604,E90,$G$5:$G$604,G90,$H$5:$H$604,H90,$R$5:$R$604,"<>Unavailable"),"⭐ Cheapest","")) -> ⭐ Cheapest | Y90: =IF(COUNTIFS($E$5:$E$604,E90,$G$5:$G$604,G90,$J$5:$J$604,"Booking.com")=0,"",_xlfn.MINIFS($M$5:$M$604,$E$5:$E$604,E90,$G$5:$G$604,G90,$J$5:$J$604,"Booking.com")) | Z90: =IF(OR(Y90="",M90="",J90="Booking.com"),"",Y90-M90) | AA90: Y | AC90: Y
A91: 87 | B91: Ella | C91: 46381 | D91: 2 | E91: Sliver Tip Room 32M2 DBL/SGL | G91: — | H91: BB | I91: 1 | J91: Direct | K91: USD | L91: 1385 | M91: =IF(L91="","",IFERROR(L91*INDEX(Trip!$E$5:$E$14,MATCH(K91,Trip!$D$5:$D$14,0))/INDEX(Trip!$E$5:$E$14,MATCH(Trip!$B$10,Trip!$D$5:$D$14,0)),"")) -> 1385 | N91: =IF(OR(M91="",D91=""),"",M91/D91) -> 692.5 | O91: =IF(M91="","",M91*I91) -> 1385 | P91: NRF | Q91: =IF(ISNUMBER(P91),P91-TODAY(),IF(P91="","",P91)) -> NRF | R91: Quote | V91: =IF(M91="","",M91*(1+IF(U91="",Trip!$B$11,U91))) -> 1592.75 | W91: =IF(V91="","",V91*I91) -> 1592.75 | X91: =IF(OR(M91="",R91="Unavailable"),"",IF(M91=_xlfn.MINIFS($M$5:$M$604,$E$5:$E$604,E91,$G$5:$G$604,G91,$H$5:$H$604,H91,$R$5:$R$604,"<>Unavailable"),"⭐ Cheapest","")) -> ⭐ Cheapest | Y91: =IF(COUNTIFS($E$5:$E$604,E91,$G$5:$G$604,G91,$J$5:$J$604,"Booking.com")=0,"",_xlfn.MINIFS($M$5:$M$604,$E$5:$E$604,E91,$G$5:$G$604,G91,$J$5:$J$604,"Booking.com")) -> 1467.4443 | Z91: =IF(OR(Y91="",M91="",J91="Booking.com"),"",Y91-M91) -> 82.444327
A92: 88 | B92: Ella | C92: 46381 | D92: 2 | E92: Sliver Tip Room 32M2 DBL/SGL | G92: — | H92: BB | I92: 1 | J92: Booking.com | K92: INR | L92: 138380 | M92: =IF(L92="","",IFERROR(L92*INDEX(Trip!$E$5:$E$14,MATCH(K92,Trip!$D$5:$D$14,0))/INDEX(Trip!$E$5:$E$14,MATCH(Trip!$B$10,Trip!$D$5:$D$14,0)),"")) -> 1467.4443 | N92: =IF(OR(M92="",D92=""),"",M92/D92) -> 733.72216 | O92: =IF(M92="","",M92*I92) -> 1467.4443 | P92: 46373 | Q92: =IF(ISNUMBER(P92),P92-TODAY(),IF(P92="","",P92)) -> 71 | R92: Quote | V92: =IF(M92="","",M92*(1+IF(U92="",Trip!$B$11,U92))) -> 1687.561 | W92: =IF(V92="","",V92*I92) -> 1687.561 | X92: =IF(OR(M92="",R92="Unavailable"),"",IF(M92=_xlfn.MINIFS($M$5:$M$604,$E$5:$E$604,E92,$G$5:$G$604,G92,$H$5:$H$604,H92,$R$5:$R$604,"<>Unavailable"),"⭐ Cheapest","")) | Y92: =IF(COUNTIFS($E$5:$E$604,E92,$G$5:$G$604,G92,$J$5:$J$604,"Booking.com")=0,"",_xlfn.MINIFS($M$5:$M$604,$E$5:$E$604,E92,$G$5:$G$604,G92,$J$5:$J$604,"Booking.com")) -> 1467.4443 | Z92: =IF(OR(Y92="",M92="",J92="Booking.com"),"",Y92-M92)
A93: 89 | B93: Galle | C93: 46383 | D93: 5 | E93: The Fort Bazaar | G93: Bazaar King Bedroom (1 King Bed) | H93: BB | I93: 1 | J93: Ottila | K93: INR | L93: 405176 | M93: =IF(L93="","",IFERROR(L93*INDEX(Trip!$E$5:$E$14,MATCH(K93,Trip!$D$5:$D$14,0))/INDEX(Trip!$E$5:$E$14,MATCH(Trip!$B$10,Trip!$D$5:$D$14,0)),"")) -> 4296.6702 | N93: =IF(OR(M93="",D93=""),"",M93/D93) -> 859.33404 | O93: =IF(M93="","",M93*I93) -> 4296.6702 | P93: NRF | Q93: =IF(ISNUMBER(P93),P93-TODAY(),IF(P93="","",P93)) -> NRF | R93: Quote | T93: Base | V93: =IF(M93="","",M93*(1+IF(U93="",Trip!$B$11,U93))) -> 4941.1707 | W93: =IF(V93="","",V93*I93) -> 4941.1707 | X93: =IF(OR(M93="",R93="Unavailable"),"",IF(M93=_xlfn.MINIFS($M$5:$M$604,$E$5:$E$604,E93,$G$5:$G$604,G93,$H$5:$H$604,H93,$R$5:$R$604,"<>Unavailable"),"⭐ Cheapest","")) -> ⭐ Cheapest | Y93: =IF(COUNTIFS($E$5:$E$604,E93,$G$5:$G$604,G93,$J$5:$J$604,"Booking.com")=0,"",_xlfn.MINIFS($M$5:$M$604,$E$5:$E$604,E93,$G$5:$G$604,G93,$J$5:$J$604,"Booking.com")) -> 4474 | Z93: =IF(OR(Y93="",M93="",J93="Booking.com"),"",Y93-M93) -> 177.3298
A94: 90 | B94: Galle | C94: 46383 | D94: 5 | E94: The Fort Bazaar | G94: Bazaar King Bedroom (1 King Bed) | H94: BB | I94: 1 | J94: Booking.com | K94: USD | L94: 4474 | M94: =IF(L94="","",IFERROR(L94*INDEX(Trip!$E$5:$E$14,MATCH(K94,Trip!$D$5:$D$14,0))/INDEX(Trip!$E$5:$E$14,MATCH(Trip!$B$10,Trip!$D$5:$D$14,0)),"")) -> 4474 | N94: =IF(OR(M94="",D94=""),"",M94/D94) -> 894.8 | O94: =IF(M94="","",M94*I94) -> 4474 | Q94: =IF(ISNUMBER(P94),P94-TODAY(),IF(P94="","",P94)) | R94: Quote | V94: =IF(M94="","",M94*(1+IF(U94="",Trip!$B$11,U94))) -> 5145.1 | W94: =IF(V94="","",V94*I94) -> 5145.1 | X94: =IF(OR(M94="",R94="Unavailable"),"",IF(M94=_xlfn.MINIFS($M$5:$M$604,$E$5:$E$604,E94,$G$5:$G$604,G94,$H$5:$H$604,H94,$R$5:$R$604,"<>Unavailable"),"⭐ Cheapest","")) | Y94: =IF(COUNTIFS($E$5:$E$604,E94,$G$5:$G$604,G94,$J$5:$J$604,"Booking.com")=0,"",_xlfn.MINIFS($M$5:$M$604,$E$5:$E$604,E94,$G$5:$G$604,G94,$J$5:$J$604,"Booking.com")) -> 4474 | Z94: =IF(OR(Y94="",M94="",J94="Booking.com"),"",Y94-M94)
A95: 91 | B95: Galle | C95: 46383 | D95: 5 | E95: Kahanda Kanda | G95: Kk Plantation Pool Villa - Hibiscus (1 King Bed) 80sqmt | H95: BB | I95: 1 | J95: Ottila | K95: INR | L95: 390001 | M95: =IF(L95="","",IFERROR(L95*INDEX(Trip!$E$5:$E$14,MATCH(K95,Trip!$D$5:$D$14,0))/INDEX(Trip!$E$5:$E$14,MATCH(Trip!$B$10,Trip!$D$5:$D$14,0)),"")) -> 4135.7476 | N95: =IF(OR(M95="",D95=""),"",M95/D95) -> 827.14952 | O95: =IF(M95="","",M95*I95) -> 4135.7476 | P95: 46319 | Q95: =IF(ISNUMBER(P95),P95-TODAY(),IF(P95="","",P95)) -> 17 | R95: Quote | V95: =IF(M95="","",M95*(1+IF(U95="",Trip!$B$11,U95))) -> 4756.1098 | W95: =IF(V95="","",V95*I95) -> 4756.1098 | X95: =IF(OR(M95="",R95="Unavailable"),"",IF(M95=_xlfn.MINIFS($M$5:$M$604,$E$5:$E$604,E95,$G$5:$G$604,G95,$H$5:$H$604,H95,$R$5:$R$604,"<>Unavailable"),"⭐ Cheapest","")) -> ⭐ Cheapest | Y95: =IF(COUNTIFS($E$5:$E$604,E95,$G$5:$G$604,G95,$J$5:$J$604,"Booking.com")=0,"",_xlfn.MINIFS($M$5:$M$604,$E$5:$E$604,E95,$G$5:$G$604,G95,$J$5:$J$604,"Booking.com")) | Z95: =IF(OR(Y95="",M95="",J95="Booking.com"),"",Y95-M95)
A96: 92 | B96: Galle | C96: 46383 | D96: 5 | E96: Weligama Bay Marriott Resort & Spa | F96: 5 | G96: Superior Ocean View | H96: HB | I96: 1 | J96: BTR | K96: USD | L96: 4100 | M96: =IF(L96="","",IFERROR(L96*INDEX(Trip!$E$5:$E$14,MATCH(K96,Trip!$D$5:$D$14,0))/INDEX(Trip!$E$5:$E$14,MATCH(Trip!$B$10,Trip!$D$5:$D$14,0)),"")) -> 4100 | N96: =IF(OR(M96="",D96=""),"",M96/D96) -> 820 | O96: =IF(M96="","",M96*I96) -> 4100 | Q96: =IF(ISNUMBER(P96),P96-TODAY(),IF(P96="","",P96)) | R96: Quote | T96: Upg 1 | V96: =IF(M96="","",M96*(1+IF(U96="",Trip!$B$11,U96))) -> 4715 | W96: =IF(V96="","",V96*I96) -> 4715 | X96: =IF(OR(M96="",R96="Unavailable"),"",IF(M96=_xlfn.MINIFS($M$5:$M$604,$E$5:$E$604,E96,$G$5:$G$604,G96,$H$5:$H$604,H96,$R$5:$R$604,"<>Unavailable"),"⭐ Cheapest","")) -> ⭐ Cheapest | Y96: =IF(COUNTIFS($E$5:$E$604,E96,$G$5:$G$604,G96,$J$5:$J$604,"Booking.com")=0,"",_xlfn.MINIFS($M$5:$M$604,$E$5:$E$604,E96,$G$5:$G$604,G96,$J$5:$J$604,"Booking.com")) -> 5020.4454 | Z96: =IF(OR(Y96="",M96="",J96="Booking.com"),"",Y96-M96) -> 920.44539
A97: 93 | B97: Galle | C97: 46383 | D97: 5 | E97: Weligama Bay Marriott Resort & Spa | F97: 5 | G97: Superior Ocean View | H97: HB | I97: 1 | J97: Booking.com | K97: INR | L97: 473428 | M97: =IF(L97="","",IFERROR(L97*INDEX(Trip!$E$5:$E$14,MATCH(K97,Trip!$D$5:$D$14,0))/INDEX(Trip!$E$5:$E$14,MATCH(Trip!$B$10,Trip!$D$5:$D$14,0)),"")) -> 5020.4454 | N97: =IF(OR(M97="",D97=""),"",M97/D97) -> 1004.0891 | O97: =IF(M97="","",M97*I97) -> 5020.4454 | P97: 46374 | Q97: =IF(ISNUMBER(P97),P97-TODAY(),IF(P97="","",P97)) -> 72 | R97: Quote | V97: =IF(M97="","",M97*(1+IF(U97="",Trip!$B$11,U97))) -> 5773.5122 | W97: =IF(V97="","",V97*I97) -> 5773.5122 | X97: =IF(OR(M97="",R97="Unavailable"),"",IF(M97=_xlfn.MINIFS($M$5:$M$604,$E$5:$E$604,E97,$G$5:$G$604,G97,$H$5:$H$604,H97,$R$5:$R$604,"<>Unavailable"),"⭐ Cheapest","")) | Y97: =IF(COUNTIFS($E$5:$E$604,E97,$G$5:$G$604,G97,$J$5:$J$604,"Booking.com")=0,"",_xlfn.MINIFS($M$5:$M$604,$E$5:$E$604,E97,$G$5:$G$604,G97,$J$5:$J$604,"Booking.com")) -> 5020.4454 | Z97: =IF(OR(Y97="",M97="",J97="Booking.com"),"",Y97-M97)
A98: 94 | B98: Galle | C98: 46383 | D98: 5 | E98: Kahanda Kanda | F98: 5 | G98: KK Plantation Pool Villa - Nelum,1 King Bed 80m2 | H98: BB | I98: 1 | J98: TBO | K98: INR | L98: 310680 | M98: =IF(L98="","",IFERROR(L98*INDEX(Trip!$E$5:$E$14,MATCH(K98,Trip!$D$5:$D$14,0))/INDEX(Trip!$E$5:$E$14,MATCH(Trip!$B$10,Trip!$D$5:$D$14,0)),"")) -> 3294.5917 | N98: =IF(OR(M98="",D98=""),"",M98/D98) -> 658.91835 | O98: =IF(M98="","",M98*I98) -> 3294.5917 | P98: 46321 | Q98: =IF(ISNUMBER(P98),P98-TODAY(),IF(P98="","",P98)) -> 19 | R98: Quote | V98: =IF(M98="","",M98*(1+IF(U98="",Trip!$B$11,U98))) -> 3788.7805 | W98: =IF(V98="","",V98*I98) -> 3788.7805 | X98: =IF(OR(M98="",R98="Unavailable"),"",IF(M98=_xlfn.MINIFS($M$5:$M$604,$E$5:$E$604,E98,$G$5:$G$604,G98,$H$5:$H$604,H98,$R$5:$R$604,"<>Unavailable"),"⭐ Cheapest","")) | Y98: =IF(COUNTIFS($E$5:$E$604,E98,$G$5:$G$604,G98,$J$5:$J$604,"Booking.com")=0,"",_xlfn.MINIFS($M$5:$M$604,$E$5:$E$604,E98,$G$5:$G$604,G98,$J$5:$J$604,"Booking.com")) -> 3186.6702 | Z98: =IF(OR(Y98="",M98="",J98="Booking.com"),"",Y98-M98) -> -107.92153
A99: 95 | B99: Galle | C99: 46383 | D99: 5 | E99: Kahanda Kanda | F99: 5 | G99: KK Plantation Pool Villa - Nelum,1 King Bed 80m2 | H99: BB | I99: 1 | J99: Booking.com | K99: INR | L99: 300503 | M99: =IF(L99="","",IFERROR(L99*INDEX(Trip!$E$5:$E$14,MATCH(K99,Trip!$D$5:$D$14,0))/INDEX(Trip!$E$5:$E$14,MATCH(Trip!$B$10,Trip!$D$5:$D$14,0)),"")) -> 3186.6702 | N99: =IF(OR(M99="",D99=""),"",M99/D99) -> 637.33404 | O99: =IF(M99="","",M99*I99) -> 3186.6702 | P99: 46322 | Q99: =IF(ISNUMBER(P99),P99-TODAY(),IF(P99="","",P99)) -> 20 | R99: Quote | V99: =IF(M99="","",M99*(1+IF(U99="",Trip!$B$11,U99))) -> 3664.6707 | W99: =IF(V99="","",V99*I99) -> 3664.6707 | X99: =IF(OR(M99="",R99="Unavailable"),"",IF(M99=_xlfn.MINIFS($M$5:$M$604,$E$5:$E$604,E99,$G$5:$G$604,G99,$H$5:$H$604,H99,$R$5:$R$604,"<>Unavailable"),"⭐ Cheapest","")) -> ⭐ Cheapest | Y99: =IF(COUNTIFS($E$5:$E$604,E99,$G$5:$G$604,G99,$J$5:$J$604,"Booking.com")=0,"",_xlfn.MINIFS($M$5:$M$604,$E$5:$E$604,E99,$G$5:$G$604,G99,$J$5:$J$604,"Booking.com")) -> 3186.6702 | Z99: =IF(OR(Y99="",M99="",J99="Booking.com"),"",Y99-M99)
A100: 96 | B100: Galle | C100: 46383 | D100: 5 | E100: Tri Tower Bedroom 25sqm | G100: — | H100: BB | I100: 1 | J100: Direct | K100: USD | L100: 1700 | M100: =IF(L100="","",IFERROR(L100*INDEX(Trip!$E$5:$E$14,MATCH(K100,Trip!$D$5:$D$14,0))/INDEX(Trip!$E$5:$E$14,MATCH(Trip!$B$10,Trip!$D$5:$D$14,0)),"")) -> 1700 | N100: =IF(OR(M100="",D100=""),"",M100/D100) -> 340 | O100: =IF(M100="","",M100*I100) -> 1700 | P100: 46352 | Q100: =IF(ISNUMBER(P100),P100-TODAY(),IF(P100="","",P100)) -> 50 | R100: Quote | V100: =IF(M100="","",M100*(1+IF(U100="",Trip!$B$11,U100))) -> 1955 | W100: =IF(V100="","",V100*I100) -> 1955 | X100: =IF(OR(M100="",R100="Unavailable"),"",IF(M100=_xlfn.MINIFS($M$5:$M$604,$E$5:$E$604,E100,$G$5:$G$604,G100,$H$5:$H$604,H100,$R$5:$R$604,"<>Unavailable"),"⭐ Cheapest","")) | Y100: =IF(COUNTIFS($E$5:$E$604,E100,$G$5:$G$604,G100,$J$5:$J$604,"Booking.com")=0,"",_xlfn.MINIFS($M$5:$M$604,$E$5:$E$604,E100,$G$5:$G$604,G100,$J$5:$J$604,"Booking.com")) -> 1674.2736 | Z100: =IF(OR(Y100="",M100="",J100="Booking.com"),"",Y100-M100) -> -25.726405
...

Sheet Compare
A1: Price comparison — cost per room for the whole stay (costing currency)
A2: Built from the Quotes tab. Green = cheapest. Add a row here (copy the one above) if you add a new hotel/room on Quotes.
A4: City | B4: Hotel | C4: Room type | D4: Meal | E4: Ottila | F4: TBO | G4: BTR | H4: Helanka | I4: Direct | J4: Hotel website | K4: Booking.com | L4: Best price | M4: Best source | N4: Booking.com vs best
A5: Negombo | B5: Regal Reseau Hotel And Spa | C5: Super, Deluxe, King Bed, Sea View 28m2 | D5: BB | E5: =IF(COUNTIFS(Quotes!$E$5:$E$604,$B5,Quotes!$G$5:$G$604,$C5,Quotes!$H$5:$H$604,$D5,Quotes!$J$5:$J$604,E$4,Quotes!$R$5:$R$604,"<>Unavailable")=0,"",_xlfn.MINIFS(Quotes!$M$5:$M$604,Quotes!$E$5:$E$604,$B5,Quotes!$G$5:$G$604,$C5,Quotes!$H$5:$H$604,$D5,Quotes!$J$5:$J$604,E$4,Quotes!$R$5:$R$604,"<>Unavailable")) -> 150.7211 | F5: =IF(COUNTIFS(Quotes!$E$5:$E$604,$B5,Quotes!$G$5:$G$604,$C5,Quotes!$H$5:$H$604,$D5,Quotes!$J$5:$J$604,F$4,Quotes!$R$5:$R$604,"<>Unavailable")=0,"",_xlfn.MINIFS(Quotes!$M$5:$M$604,Quotes!$E$5:$E$604,$B5,Quotes!$G$5:$G$604,$C5,Quotes!$H$5:$H$604,$D5,Quotes!$J$5:$J$604,F$4,Quotes!$R$5:$R$604,"<>Unavailable")) | G5: =IF(COUNTIFS(Quotes!$E$5:$E$604,$B5,Quotes!$G$5:$G$604,$C5,Quotes!$H$5:$H$604,$D5,Quotes!$J$5:$J$604,G$4,Quotes!$R$5:$R$604,"<>Unavailable")=0,"",_xlfn.MINIFS(Quotes!$M$5:$M$604,Quotes!$E$5:$E$604,$B5,Quotes!$G$5:$G$604,$C5,Quotes!$H$5:$H$604,$D5,Quotes!$J$5:$J$604,G$4,Quotes!$R$5:$R$604,"<>Unavailable")) | H5: =IF(COUNTIFS(Quotes!$E$5:$E$604,$B5,Quotes!$G$5:$G$604,$C5,Quotes!$H$5:$H$604,$D5,Quotes!$J$5:$J$604,H$4,Quotes!$R$5:$R$604,"<>Unavailable")=0,"",_xlfn.MINIFS(Quotes!$M$5:$M$604,Quotes!$E$5:$E$604,$B5,Quotes!$G$5:$G$604,$C5,Quotes!$H$5:$H$604,$D5,Quotes!$J$5:$J$604,H$4,Quotes!$R$5:$R$604,"<>Unavailable")) | I5: =IF(COUNTIFS(Quotes!$E$5:$E$604,$B5,Quotes!$G$5:$G$604,$C5,Quotes!$H$5:$H$604,$D5,Quotes!$J$5:$J$604,I$4,Quotes!$R$5:$R$604,"<>Unavailable")=0,"",_xlfn.MINIFS(Quotes!$M$5:$M$604,Quotes!$E$5:$E$604,$B5,Quotes!$G$5:$G$604,$C5,Quotes!$H$5:$H$604,$D5,Quotes!$J$5:$J$604,I$4,Quotes!$R$5:$R$604,"<>Unavailable")) | J5: =IF(COUNTIFS(Quotes!$E$5:$E$604,$B5,Quotes!$G$5:$G$604,$C5,Quotes!$H$5:$H$604,$D5,Quotes!$J$5:$J$604,J$4,Quotes!$R$5:$R$604,"<>Unavailable")=0,"",_xlfn.MINIFS(Quotes!$M$5:$M$604,Quotes!$E$5:$E$604,$B5,Quotes!$G$5:$G$604,$C5,Quotes!$H$5:$H$604,$D5,Quotes!$J$5:$J$604,J$4,Quotes!$R$5:$R$604,"<>Unavailable")) | K5: =IF(COUNTIFS(Quotes!$E$5:$E$604,$B5,Quotes!$G$5:$G$604,$C5,Quotes!$H$5:$H$604,$D5,Quotes!$J$5:$J$604,K$4,Quotes!$R$5:$R$604,"<>Unavailable")=0,"",_xlfn.MINIFS(Quotes!$M$5:$M$604,Quotes!$E$5:$E$604,$B5,Quotes!$G$5:$G$604,$C5,Quotes!$H$5:$H$604,$D5,Quotes!$J$5:$J$604,K$4,Quotes!$R$5:$R$604,"<>Unavailable")) -> 139.14104 | L5: =IF(COUNT(E5:K5)=0,"",MIN(E5:K5)) -> 139.14104 | M5: =IF(L5="","",INDEX($E$4:$K$4,MATCH(L5,E5:K5,0))) -> Booking.com | N5: =IF(OR(K5="",COUNT(E5:J5)=0),"",K5-MIN(E5:J5)) -> -11.580064
A6: Negombo | B6: Jetwing Sea Hotel | C6: Standard Double Sea View | D6: BB | E6: =IF(COUNTIFS(Quotes!$E$5:$E$604,$B6,Quotes!$G$5:$G$604,$C6,Quotes!$H$5:$H$604,$D6,Quotes!$J$5:$J$604,E$4,Quotes!$R$5:$R$604,"<>Unavailable")=0,"",_xlfn.MINIFS(Quotes!$M$5:$M$604,Quotes!$E$5:$E$604,$B6,Quotes!$G$5:$G$604,$C6,Quotes!$H$5:$H$604,$D6,Quotes!$J$5:$J$604,E$4,Quotes!$R$5:$R$604,"<>Unavailable")) -> 109.41676 | F6: =IF(COUNTIFS(Quotes!$E$5:$E$604,$B6,Quotes!$G$5:$G$604,$C6,Quotes!$H$5:$H$604,$D6,Quotes!$J$5:$J$604,F$4,Quotes!$R$5:$R$604,"<>Unavailable")=0,"",_xlfn.MINIFS(Quotes!$M$5:$M$604,Quotes!$E$5:$E$604,$B6,Quotes!$G$5:$G$604,$C6,Quotes!$H$5:$H$604,$D6,Quotes!$J$5:$J$604,F$4,Quotes!$R$5:$R$604,"<>Unavailable")) | G6: =IF(COUNTIFS(Quotes!$E$5:$E$604,$B6,Quotes!$G$5:$G$604,$C6,Quotes!$H$5:$H$604,$D6,Quotes!$J$5:$J$604,G$4,Quotes!$R$5:$R$604,"<>Unavailable")=0,"",_xlfn.MINIFS(Quotes!$M$5:$M$604,Quotes!$E$5:$E$604,$B6,Quotes!$G$5:$G$604,$C6,Quotes!$H$5:$H$604,$D6,Quotes!$J$5:$J$604,G$4,Quotes!$R$5:$R$604,"<>Unavailable")) | H6: =IF(COUNTIFS(Quotes!$E$5:$E$604,$B6,Quotes!$G$5:$G$604,$C6,Quotes!$H$5:$H$604,$D6,Quotes!$J$5:$J$604,H$4,Quotes!$R$5:$R$604,"<>Unavailable")=0,"",_xlfn.MINIFS(Quotes!$M$5:$M$604,Quotes!$E$5:$E$604,$B6,Quotes!$G$5:$G$604,$C6,Quotes!$H$5:$H$604,$D6,Quotes!$J$5:$J$604,H$4,Quotes!$R$5:$R$604,"<>Unavailable")) | I6: =IF(COUNTIFS(Quotes!$E$5:$E$604,$B6,Quotes!$G$5:$G$604,$C6,Quotes!$H$5:$H$604,$D6,Quotes!$J$5:$J$604,I$4,Quotes!$R$5:$R$604,"<>Unavailable")=0,"",_xlfn.MINIFS(Quotes!$M$5:$M$604,Quotes!$E$5:$E$604,$B6,Quotes!$G$5:$G$604,$C6,Quotes!$H$5:$H$604,$D6,Quotes!$J$5:$J$604,I$4,Quotes!$R$5:$R$604,"<>Unavailable")) | J6: =IF(COUNTIFS(Quotes!$E$5:$E$604,$B6,Quotes!$G$5:$G$604,$C6,Quotes!$H$5:$H$604,$D6,Quotes!$J$5:$J$604,J$4,Quotes!$R$5:$R$604,"<>Unavailable")=0,"",_xlfn.MINIFS(Quotes!$M$5:$M$604,Quotes!$E$5:$E$604,$B6,Quotes!$G$5:$G$604,$C6,Quotes!$H$5:$H$604,$D6,Quotes!$J$5:$J$604,J$4,Quotes!$R$5:$R$604,"<>Unavailable")) | K6: =IF(COUNTIFS(Quotes!$E$5:$E$604,$B6,Quotes!$G$5:$G$604,$C6,Quotes!$H$5:$H$604,$D6,Quotes!$J$5:$J$604,K$4,Quotes!$R$5:$R$604,"<>Unavailable")=0,"",_xlfn.MINIFS(Quotes!$M$5:$M$604,Quotes!$E$5:$E$604,$B6,Quotes!$G$5:$G$604,$C6,Quotes!$H$5:$H$604,$D6,Quotes!$J$5:$J$604,K$4,Quotes!$R$5:$R$604,"<>Unavailable")) | L6: =IF(COUNT(E6:K6)=0,"",MIN(E6:K6)) -> 109.41676 | M6: =IF(L6="","",INDEX($E$4:$K$4,MATCH(L6,E6:K6,0))) -> Ottila | N6: =IF(OR(K6="",COUNT(E6:J6)=0),"",K6-MIN(E6:J6))
A7: Negombo | B7: Jetwing Blue | C7: Deluxe Room | D7: BB | E7: =IF(COUNTIFS(Quotes!$E$5:$E$604,$B7,Quotes!$G$5:$G$604,$C7,Quotes!$H$5:$H$604,$D7,Quotes!$J$5:$J$604,E$4,Quotes!$R$5:$R$604,"<>Unavailable")=0,"",_xlfn.MINIFS(Quotes!$M$5:$M$604,Quotes!$E$5:$E$604,$B7,Quotes!$G$5:$G$604,$C7,Quotes!$H$5:$H$604,$D7,Quotes!$J$5:$J$604,E$4,Quotes!$R$5:$R$604,"<>Unavailable")) -> 160.74231 | F7: =IF(COUNTIFS(Quotes!$E$5:$E$604,$B7,Quotes!$G$5:$G$604,$C7,Quotes!$H$5:$H$604,$D7,Quotes!$J$5:$J$604,F$4,Quotes!$R$5:$R$604,"<>Unavailable")=0,"",_xlfn.MINIFS(Quotes!$M$5:$M$604,Quotes!$E$5:$E$604,$B7,Quotes!$G$5:$G$604,$C7,Quotes!$H$5:$H$604,$D7,Quotes!$J$5:$J$604,F$4,Quotes!$R$5:$R$604,"<>Unavailable")) | G7: =IF(COUNTIFS(Quotes!$E$5:$E$604,$B7,Quotes!$G$5:$G$604,$C7,Quotes!$H$5:$H$604,$D7,Quotes!$J$5:$J$604,G$4,Quotes!$R$5:$R$604,"<>Unavailable")=0,"",_xlfn.MINIFS(Quotes!$M$5:$M$604,Quotes!$E$5:$E$604,$B7,Quotes!$G$5:$G$604,$C7,Quotes!$H$5:$H$604,$D7,Quotes!$J$5:$J$604,G$4,Quotes!$R$5:$R$604,"<>Unavailable")) | H7: =IF(COUNTIFS(Quotes!$E$5:$E$604,$B7,Quotes!$G$5:$G$604,$C7,Quotes!$H$5:$H$604,$D7,Quotes!$J$5:$J$604,H$4,Quotes!$R$5:$R$604,"<>Unavailable")=0,"",_xlfn.MINIFS(Quotes!$M$5:$M$604,Quotes!$E$5:$E$604,$B7,Quotes!$G$5:$G$604,$C7,Quotes!$H$5:$H$604,$D7,Quotes!$J$5:$J$604,H$4,Quotes!$R$5:$R$604,"<>Unavailable")) | I7: =IF(COUNTIFS(Quotes!$E$5:$E$604,$B7,Quotes!$G$5:$G$604,$C7,Quotes!$H$5:$H$604,$D7,Quotes!$J$5:$J$604,I$4,Quotes!$R$5:$R$604,"<>Unavailable")=0,"",_xlfn.MINIFS(Quotes!$M$5:$M$604,Quotes!$E$5:$E$604,$B7,Quotes!$G$5:$G$604,$C7,Quotes!$H$5:$H$604,$D7,Quotes!$J$5:$J$604,I$4,Quotes!$R$5:$R$604,"<>Unavailable")) | J7: =IF(COUNTIFS(Quotes!$E$5:$E$604,$B7,Quotes!$G$5:$G$604,$C7,Quotes!$H$5:$H$604,$D7,Quotes!$J$5:$J$604,J$4,Quotes!$R$5:$R$604,"<>Unavailable")=0,"",_xlfn.MINIFS(Quotes!$M$5:$M$604,Quotes!$E$5:$E$604,$B7,Quotes!$G$5:$G$604,$C7,Quotes!$H$5:$H$604,$D7,Quotes!$J$5:$J$604,J$4,Quotes!$R$5:$R$604,"<>Unavailable")) | K7: =IF(COUNTIFS(Quotes!$E$5:$E$604,$B7,Quotes!$G$5:$G$604,$C7,Quotes!$H$5:$H$604,$D7,Quotes!$J$5:$J$604,K$4,Quotes!$R$5:$R$604,"<>Unavailable")=0,"",_xlfn.MINIFS(Quotes!$M$5:$M$604,Quotes!$E$5:$E$604,$B7,Quotes!$G$5:$G$604,$C7,Quotes!$H$5:$H$604,$D7,Quotes!$J$5:$J$604,K$4,Quotes!$R$5:$R$604,"<>Unavailable")) -> 179 | L7: =IF(COUNT(E7:K7)=0,"",MIN(E7:K7)) -> 160.74231 | M7: =IF(L7="","",INDEX($E$4:$K$4,MATCH(L7,E7:K7,0))) -> Ottila | N7: =IF(OR(K7="",COUNT(E7:J7)=0),"",K7-MIN(E7:J7)) -> 18.257688
A8: Negombo | B8: The Wallawwa | C8: Walawwa Bedrom (1 King Bed) 35sqmr | D8: BB | E8: =IF(COUNTIFS(Quotes!$E$5:$E$604,$B8,Quotes!$G$5:$G$604,$C8,Quotes!$H$5:$H$604,$D8,Quotes!$J$5:$J$604,E$4,Quotes!$R$5:$R$604,"<>Unavailable")=0,"",_xlfn.MINIFS(Quotes!$M$5:$M$604,Quotes!$E$5:$E$604,$B8,Quotes!$G$5:$G$604,$C8,Quotes!$H$5:$H$604,$D8,Quotes!$J$5:$J$604,E$4,Quotes!$R$5:$R$604,"<>Unavailable")) -> 533.18134 | F8: =IF(COUNTIFS(Quotes!$E$5:$E$604,$B8,Quotes!$G$5:$G$604,$C8,Quotes!$H$5:$H$604,$D8,Quotes!$J$5:$J$604,F$4,Quotes!$R$5:$R$604,"<>Unavailable")=0,"",_xlfn.MINIFS(Quotes!$M$5:$M$604,Quotes!$E$5:$E$604,$B8,Quotes!$G$5:$G$604,$C8,Quotes!$H$5:$H$604,$D8,Quotes!$J$5:$J$604,F$4,Quotes!$R$5:$R$604,"<>Unavailable")) | G8: =IF(COUNTIFS(Quotes!$E$5:$E$604,$B8,Quotes!$G$5:$G$604,$C8,Quotes!$H$5:$H$604,$D8,Quotes!$J$5:$J$604,G$4,Quotes!$R$5:$R$604,"<>Unavailable")=0,"",_xlfn.MINIFS(Quotes!$M$5:$M$604,Quotes!$E$5:$E$604,$B8,Quotes!$G$5:$G$604,$C8,Quotes!$H$5:$H$604,$D8,Quotes!$J$5:$J$604,G$4,Quotes!$R$5:$R$604,"<>Unavailable")) | H8: =IF(COUNTIFS(Quotes!$E$5:$E$604,$B8,Quotes!$G$5:$G$604,$C8,Quotes!$H$5:$H$604,$D8,Quotes!$J$5:$J$604,H$4,Quotes!$R$5:$R$604,"<>Unavailable")=0,"",_xlfn.MINIFS(Quotes!$M$5:$M$604,Quotes!$E$5:$E$604,$B8,Quotes!$G$5:$G$604,$C8,Quotes!$H$5:$H$604,$D8,Quotes!$J$5:$J$604,H$4,Quotes!$R$5:$R$604,"<>Unavailable")) | I8: =IF(COUNTIFS(Quotes!$E$5:$E$604,$B8,Quotes!$G$5:$G$604,$C8,Quotes!$H$5:$H$604,$D8,Quotes!$J$5:$J$604,I$4,Quotes!$R$5:$R$604,"<>Unavailable")=0,"",_xlfn.MINIFS(Quotes!$M$5:$M$604,Quotes!$E$5:$E$604,$B8,Quotes!$G$5:$G$604,$C8,Quotes!$H$5:$H$604,$D8,Quotes!$J$5:$J$604,I$4,Quotes!$R$5:$R$604,"<>Unavailable")) | J8: =IF(COUNTIFS(Quotes!$E$5:$E$604,$B8,Quotes!$G$5:$G$604,$C8,Quotes!$H$5:$H$604,$D8,Quotes!$J$5:$J$604,J$4,Quotes!$R$5:$R$604,"<>Unavailable")=0,"",_xlfn.MINIFS(Quotes!$M$5:$M$604,Quotes!$E$5:$E$604,$B8,Quotes!$G$5:$G$604,$C8,Quotes!$H$5:$H$604,$D8,Quotes!$J$5:$J$604,J$4,Quotes!$R$5:$R$604,"<>Unavailable")) | K8: =IF(COUNTIFS(Quotes!$E$5:$E$604,$B8,Quotes!$G$5:$G$604,$C8,Quotes!$H$5:$H$604,$D8,Quotes!$J$5:$J$604,K$4,Quotes!$R$5:$R$604,"<>Unavailable")=0,"",_xlfn.MINIFS(Quotes!$M$5:$M$604,Quotes!$E$5:$E$604,$B8,Quotes!$G$5:$G$604,$C8,Quotes!$H$5:$H$604,$D8,Quotes!$J$5:$J$604,K$4,Quotes!$R$5:$R$604,"<>Unavailable")) -> 580 | L8: =IF(COUNT(E8:K8)=0,"",MIN(E8:K8)) -> 533.18134 | M8: =IF(L8="","",INDEX($E$4:$K$4,MATCH(L8,E8:K8,0))) -> Ottila | N8: =IF(OR(K8="",COUNT(E8:J8)=0),"",K8-MIN(E8:J8)) -> 46.818664
A9: Negombo | B9: Wattura Resort And Spa | C9: Suite With River View (1 King Bed) 72sqmt | D9: BB | E9: =IF(COUNTIFS(Quotes!$E$5:$E$604,$B9,Quotes!$G$5:$G$604,$C9,Quotes!$H$5:$H$604,$D9,Quotes!$J$5:$J$604,E$4,Quotes!$R$5:$R$604,"<>Unavailable")=0,"",_xlfn.MINIFS(Quotes!$M$5:$M$604,Quotes!$E$5:$E$604,$B9,Quotes!$G$5:$G$604,$C9,Quotes!$H$5:$H$604,$D9,Quotes!$J$5:$J$604,E$4,Quotes!$R$5:$R$604,"<>Unavailable")) -> 236.38388 | F9: =IF(COUNTIFS(Quotes!$E$5:$E$604,$B9,Quotes!$G$5:$G$604,$C9,Quotes!$H$5:$H$604,$D9,Quotes!$J$5:$J$604,F$4,Quotes!$R$5:$R$604,"<>Unavailable")=0,"",_xlfn.MINIFS(Quotes!$M$5:$M$604,Quotes!$E$5:$E$604,$B9,Quotes!$G$5:$G$604,$C9,Quotes!$H$5:$H$604,$D9,Quotes!$J$5:$J$604,F$4,Quotes!$R$5:$R$604,"<>Unavailable")) | G9: =IF(COUNTIFS(Quotes!$E$5:$E$604,$B9,Quotes!$G$5:$G$604,$C9,Quotes!$H$5:$H$604,$D9,Quotes!$J$5:$J$604,G$4,Quotes!$R$5:$R$604,"<>Unavailable")=0,"",_xlfn.MINIFS(Quotes!$M$5:$M$604,Quotes!$E$5:$E$604,$B9,Quotes!$G$5:$G$604,$C9,Quotes!$H$5:$H$604,$D9,Quotes!$J$5:$J$604,G$4,Quotes!$R$5:$R$604,"<>Unavailable")) | H9: =IF(COUNTIFS(Quotes!$E$5:$E$604,$B9,Quotes!$G$5:$G$604,$C9,Quotes!$H$5:$H$604,$D9,Quotes!$J$5:$J$604,H$4,Quotes!$R$5:$R$604,"<>Unavailable")=0,"",_xlfn.MINIFS(Quotes!$M$5:$M$604,Quotes!$E$5:$E$604,$B9,Quotes!$G$5:$G$604,$C9,Quotes!$H$5:$H$604,$D9,Quotes!$J$5:$J$604,H$4,Quotes!$R$5:$R$604,"<>Unavailable")) | I9: =IF(COUNTIFS(Quotes!$E$5:$E$604,$B9,Quotes!$G$5:$G$604,$C9,Quotes!$H$5:$H$604,$D9,Quotes!$J$5:$J$604,I$4,Quotes!$R$5:$R$604,"<>Unavailable")=0,"",_xlfn.MINIFS(Quotes!$M$5:$M$604,Quotes!$E$5:$E$604,$B9,Quotes!$G$5:$G$604,$C9,Quotes!$H$5:$H$604,$D9,Quotes!$J$5:$J$604,I$4,Quotes!$R$5:$R$604,"<>Unavailable")) | J9: =IF(COUNTIFS(Quotes!$E$5:$E$604,$B9,Quotes!$G$5:$G$604,$C9,Quotes!$H$5:$H$604,$D9,Quotes!$J$5:$J$604,J$4,Quotes!$R$5:$R$604,"<>Unavailable")=0,"",_xlfn.MINIFS(Quotes!$M$5:$M$604,Quotes!$E$5:$E$604,$B9,Quotes!$G$5:$G$604,$C9,Quotes!$H$5:$H$604,$D9,Quotes!$J$5:$J$604,J$4,Quotes!$R$5:$R$604,"<>Unavailable")) | K9: =IF(COUNTIFS(Quotes!$E$5:$E$604,$B9,Quotes!$G$5:$G$604,$C9,Quotes!$H$5:$H$604,$D9,Quotes!$J$5:$J$604,K$4,Quotes!$R$5:$R$604,"<>Unavailable")=0,"",_xlfn.MINIFS(Quotes!$M$5:$M$604,Quotes!$E$5:$E$604,$B9,Quotes!$G$5:$G$604,$C9,Quotes!$H$5:$H$604,$D9,Quotes!$J$5:$J$604,K$4,Quotes!$R$5:$R$604,"<>Unavailable")) -> 250 | L9: =IF(COUNT(E9:K9)=0,"",MIN(E9:K9)) -> 236.38388 | M9: =IF(L9="","",INDEX($E$4:$K$4,MATCH(L9,E9:K9,0))) -> Ottila | N9: =IF(OR(K9="",COUNT(E9:J9)=0),"",K9-MIN(E9:J9)) -> 13.616119
A10: Negombo | B10: Sentido Heritance Negombo | C10: Deluxe King 40sqmt | D10: BB | E10: =IF(COUNTIFS(Quotes!$E$5:$E$604,$B10,Quotes!$G$5:$G$604,$C10,Quotes!$H$5:$H$604,$D10,Quotes!$J$5:$J$604,E$4,Quotes!$R$5:$R$604,"<>Unavailable")=0,"",_xlfn.MINIFS(Quotes!$M$5:$M$604,Quotes!$E$5:$E$604,$B10,Quotes!$G$5:$G$604,$C10,Quotes!$H$5:$H$604,$D10,Quotes!$J$5:$J$604,E$4,Quotes!$R$5:$R$604,"<>Unavailable")) -> 182.27996 | F10: =IF(COUNTIFS(Quotes!$E$5:$E$604,$B10,Quotes!$G$5:$G$604,$C10,Quotes!$H$5:$H$604,$D10,Quotes!$J$5:$J$604,F$4,Quotes!$R$5:$R$604,"<>Unavailable")=0,"",_xlfn.MINIFS(Quotes!$M$5:$M$604,Quotes!$E$5:$E$604,$B10,Quotes!$G$5:$G$604,$C10,Quotes!$H$5:$H$604,$D10,Quotes!$J$5:$J$604,F$4,Quotes!$R$5:$R$604,"<>Unavailable")) | G10: =IF(COUNTIFS(Quotes!$E$5:$E$604,$B10,Quotes!$G$5:$G$604,$C10,Quotes!$H$5:$H$604,$D10,Quotes!$J$5:$J$604,G$4,Quotes!$R$5:$R$604,"<>Unavailable")=0,"",_xlfn.MINIFS(Quotes!$M$5:$M$604,Quotes!$E$5:$E$604,$B10,Quotes!$G$5:$G$604,$C10,Quotes!$H$5:$H$604,$D10,Quotes!$J$5:$J$604,G$4,Quotes!$R$5:$R$604,"<>Unavailable")) | H10: =IF(COUNTIFS(Quotes!$E$5:$E$604,$B10,Quotes!$G$5:$G$604,$C10,Quotes!$H$5:$H$604,$D10,Quotes!$J$5:$J$604,H$4,Quotes!$R$5:$R$604,"<>Unavailable")=0,"",_xlfn.MINIFS(Quotes!$M$5:$M$604,Quotes!$E$5:$E$604,$B10,Quotes!$G$5:$G$604,$C10,Quotes!$H$5:$H$604,$D10,Quotes!$J$5:$J$604,H$4,Quotes!$R$5:$R$604,"<>Unavailable")) | I10: =IF(COUNTIFS(Quotes!$E$5:$E$604,$B10,Quotes!$G$5:$G$604,$C10,Quotes!$H$5:$H$604,$D10,Quotes!$J$5:$J$604,I$4,Quotes!$R$5:$R$604,"<>Unavailable")=0,"",_xlfn.MINIFS(Quotes!$M$5:$M$604,Quotes!$E$5:$E$604,$B10,Quotes!$G$5:$G$604,$C10,Quotes!$H$5:$H$604,$D10,Quotes!$J$5:$J$604,I$4,Quotes!$R$5:$R$604,"<>Unavailable")) | J10: =IF(COUNTIFS(Quotes!$E$5:$E$604,$B10,Quotes!$G$5:$G$604,$C10,Quotes!$H$5:$H$604,$D10,Quotes!$J$5:$J$604,J$4,Quotes!$R$5:$R$604,"<>Unavailable")=0,"",_xlfn.MINIFS(Quotes!$M$5:$M$604,Quotes!$E$5:$E$604,$B10,Quotes!$G$5:$G$604,$C10,Quotes!$H$5:$H$604,$D10,Quotes!$J$5:$J$604,J$4,Quotes!$R$5:$R$604,"<>Unavailable")) | K10: =IF(COUNTIFS(Quotes!$E$5:$E$604,$B10,Quotes!$G$5:$G$604,$C10,Quotes!$H$5:$H$604,$D10,Quotes!$J$5:$J$604,K$4,Quotes!$R$5:$R$604,"<>Unavailable")=0,"",_xlfn.MINIFS(Quotes!$M$5:$M$604,Quotes!$E$5:$E$604,$B10,Quotes!$G$5:$G$604,$C10,Quotes!$H$5:$H$604,$D10,Quotes!$J$5:$J$604,K$4,Quotes!$R$5:$R$604,"<>Unavailable")) -> 329 | L10: =IF(COUNT(E10:K10)=0,"",MIN(E10:K10)) -> 182.27996 | M10: =IF(L10="","",INDEX($E$4:$K$4,MATCH(L10,E10:K10,0))) -> Ottila | N10: =IF(OR(K10="",COUNT(E10:J10)=0),"",K10-MIN(E10:J10)) -> 146.72004
A11: Negombo | B11: Jetwing Blue | C11: TWIN DELUXE SEA VIEW( 2 Adults ) 59sqmt | D11: BB | E11: =IF(COUNTIFS(Quotes!$E$5:$E$604,$B11,Quotes!$G$5:$G$604,$C11,Quotes!$H$5:$H$604,$D11,Quotes!$J$5:$J$604,E$4,Quotes!$R$5:$R$604,"<>Unavailable")=0,"",_xlfn.MINIFS(Quotes!$M$5:$M$604,Quotes!$E$5:$E$604,$B11,Quotes!$G$5:$G$604,$C11,Quotes!$H$5:$H$604,$D11,Quotes!$J$5:$J$604,E$4,Quotes!$R$5:$R$604,"<>Unavailable")) -> 170.20148 | F11: =IF(COUNTIFS(Quotes!$E$5:$E$604,$B11,Quotes!$G$5:$G$604,$C11,Quotes!$H$5:$H$604,$D11,Quotes!$J$5:$J$604,F$4,Quotes!$R$5:$R$604,"<>Unavailable")=0,"",_xlfn.MINIFS(Quotes!$M$5:$M$604,Quotes!$E$5:$E$604,$B11,Quotes!$G$5:$G$604,$C11,Quotes!$H$5:$H$604,$D11,Quotes!$J$5:$J$604,F$4,Quotes!$R$5:$R$604,"<>Unavailable")) | G11: =IF(COUNTIFS(Quotes!$E$5:$E$604,$B11,Quotes!$G$5:$G$604,$C11,Quotes!$H$5:$H$604,$D11,Quotes!$J$5:$J$604,G$4,Quotes!$R$5:$R$604,"<>Unavailable")=0,"",_xlfn.MINIFS(Quotes!$M$5:$M$604,Quotes!$E$5:$E$604,$B11,Quotes!$G$5:$G$604,$C11,Quotes!$H$5:$H$604,$D11,Quotes!$J$5:$J$604,G$4,Quotes!$R$5:$R$604,"<>Unavailable")) | H11: =IF(COUNTIFS(Quotes!$E$5:$E$604,$B11,Quotes!$G$5:$G$604,$C11,Quotes!$H$5:$H$604,$D11,Quotes!$J$5:$J$604,H$4,Quotes!$R$5:$R$604,"<>Unavailable")=0,"",_xlfn.MINIFS(Quotes!$M$5:$M$604,Quotes!$E$5:$E$604,$B11,Quotes!$G$5:$G$604,$C11,Quotes!$H$5:$H$604,$D11,Quotes!$J$5:$J$604,H$4,Quotes!$R$5:$R$604,"<>Unavailable")) | I11: =IF(COUNTIFS(Quotes!$E$5:$E$604,$B11,Quotes!$G$5:$G$604,$C11,Quotes!$H$5:$H$604,$D11,Quotes!$J$5:$J$604,I$4,Quotes!$R$5:$R$604,"<>Unavailable")=0,"",_xlfn.MINIFS(Quotes!$M$5:$M$604,Quotes!$E$5:$E$604,$B11,Quotes!$G$5:$G$604,$C11,Quotes!$H$5:$H$604,$D11,Quotes!$J$5:$J$604,I$4,Quotes!$R$5:$R$604,"<>Unavailable")) | J11: =IF(COUNTIFS(Quotes!$E$5:$E$604,$B11,Quotes!$G$5:$G$604,$C11,Quotes!$H$5:$H$604,$D11,Quotes!$J$5:$J$604,J$4,Quotes!$R$5:$R$604,"<>Unavailable")=0,"",_xlfn.MINIFS(Quotes!$M$5:$M$604,Quotes!$E$5:$E$604,$B11,Quotes!$G$5:$G$604,$C11,Quotes!$H$5:$H$604,$D11,Quotes!$J$5:$J$604,J$4,Quotes!$R$5:$R$604,"<>Unavailable")) | K11: =IF(COUNTIFS(Quotes!$E$5:$E$604,$B11,Quotes!$G$5:$G$604,$C11,Quotes!$H$5:$H$604,$D11,Quotes!$J$5:$J$604,K$4,Quotes!$R$5:$R$604,"<>Unavailable")=0,"",_xlfn.MINIFS(Quotes!$M$5:$M$604,Quotes!$E$5:$E$604,$B11,Quotes!$G$5:$G$604,$C11,Quotes!$H$5:$H$604,$D11,Quotes!$J$5:$J$604,K$4,Quotes!$R$5:$R$604,"<>Unavailable")) | L11: =IF(COUNT(E11:K11)=0,"",MIN(E11:K11)) -> 170.20148 | M11: =IF(L11="","",INDEX($E$4:$K$4,MATCH(L11,E11:K11,0))) -> Ottila | N11: =IF(OR(K11="",COUNT(E11:J11)=0),"",K11-MIN(E11:J11))
A12: Dambulla / Sigiriya | B12: Habarana Village By Cinnamon | C12: Superior Room 30m2 | D12: BB | E12: =IF(COUNTIFS(Quotes!$E$5:$E$604,$B12,Quotes!$G$5:$G$604,$C12,Quotes!$H$5:$H$604,$D12,Quotes!$J$5:$J$604,E$4,Quotes!$R$5:$R$604,"<>Unavailable")=0,"",_xlfn.MINIFS(Quotes!$M$5:$M$604,Quotes!$E$5:$E$604,$B12,Quotes!$G$5:$G$604,$C12,Quotes!$H$5:$H$604,$D12,Quotes!$J$5:$J$604,E$4,Quotes!$R$5:$R$604,"<>Unavailable")) -> 272.6193 | F12: =IF(COUNTIFS(Quotes!$E$5:$E$604,$B12,Quotes!$G$5:$G$604,$C12,Quotes!$H$5:$H$604,$D12,Quotes!$J$5:$J$604,F$4,Quotes!$R$5:$R$604,"<>Unavailable")=0,"",_xlfn.MINIFS(Quotes!$M$5:$M$604,Quotes!$E$5:$E$604,$B12,Quotes!$G$5:$G$604,$C12,Quotes!$H$5:$H$604,$D12,Quotes!$J$5:$J$604,F$4,Quotes!$R$5:$R$604,"<>Unavailable")) | G12: =IF(COUNTIFS(Quotes!$E$5:$E$604,$B12,Quotes!$G$5:$G$604,$C12,Quotes!$H$5:$H$604,$D12,Quotes!$J$5:$J$604,G$4,Quotes!$R$5:$R$604,"<>Unavailable")=0,"",_xlfn.MINIFS(Quotes!$M$5:$M$604,Quotes!$E$5:$E$604,$B12,Quotes!$G$5:$G$604,$C12,Quotes!$H$5:$H$604,$D12,Quotes!$J$5:$J$604,G$4,Quotes!$R$5:$R$604,"<>Unavailable")) | H12: =IF(COUNTIFS(Quotes!$E$5:$E$604,$B12,Quotes!$G$5:$G$604,$C12,Quotes!$H$5:$H$604,$D12,Quotes!$J$5:$J$604,H$4,Quotes!$R$5:$R$604,"<>Unavailable")=0,"",_xlfn.MINIFS(Quotes!$M$5:$M$604,Quotes!$E$5:$E$604,$B12,Quotes!$G$5:$G$604,$C12,Quotes!$H$5:$H$604,$D12,Quotes!$J$5:$J$604,H$4,Quotes!$R$5:$R$604,"<>Unavailable")) | I12: =IF(COUNTIFS(Quotes!$E$5:$E$604,$B12,Quotes!$G$5:$G$604,$C12,Quotes!$H$5:$H$604,$D12,Quotes!$J$5:$J$604,I$4,Quotes!$R$5:$R$604,"<>Unavailable")=0,"",_xlfn.MINIFS(Quotes!$M$5:$M$604,Quotes!$E$5:$E$604,$B12,Quotes!$G$5:$G$604,$C12,Quotes!$H$5:$H$604,$D12,Quotes!$J$5:$J$604,I$4,Quotes!$R$5:$R$604,"<>Unavailable")) | J12: =IF(COUNTIFS(Quotes!$E$5:$E$604,$B12,Quotes!$G$5:$G$604,$C12,Quotes!$H$5:$H$604,$D12,Quotes!$J$5:$J$604,J$4,Quotes!$R$5:$R$604,"<>Unavailable")=0,"",_xlfn.MINIFS(Quotes!$M$5:$M$604,Quotes!$E$5:$E$604,$B12,Quotes!$G$5:$G$604,$C12,Quotes!$H$5:$H$604,$D12,Quotes!$J$5:$J$604,J$4,Quotes!$R$5:$R$604,"<>Unavailable")) | K12: =IF(COUNTIFS(Quotes!$E$5:$E$604,$B12,Quotes!$G$5:$G$604,$C12,Quotes!$H$5:$H$604,$D12,Quotes!$J$5:$J$604,K$4,Quotes!$R$5:$R$604,"<>Unavailable")=0,"",_xlfn.MINIFS(Quotes!$M$5:$M$604,Quotes!$E$5:$E$604,$B12,Quotes!$G$5:$G$604,$C12,Quotes!$H$5:$H$604,$D12,Quotes!$J$5:$J$604,K$4,Quotes!$R$5:$R$604,"<>Unavailable")) -> 347.40191 | L12: =IF(COUNT(E12:K12)=0,"",MIN(E12:K12)) -> 272.6193 | M12: =IF(L12="","",INDEX($E$4:$K$4,MATCH(L12,E12:K12,0))) -> Ottila | N12: =IF(OR(K12="",COUNT(E12:J12)=0),"",K12-MIN(E12:J12)) -> 74.782609
A13: Dambulla / Sigiriya | B13: Sigiriya Jungles Resort & Spa | C13: Deluxe room | D13: BB | E13: =IF(COUNTIFS(Quotes!$E$5:$E$604,$B13,Quotes!$G$5:$G$604,$C13,Quotes!$H$5:$H$604,$D13,Quotes!$J$5:$J$604,E$4,Quotes!$R$5:$R$604,"<>Unavailable")=0,"",_xlfn.MINIFS(Quotes!$M$5:$M$604,Quotes!$E$5:$E$604,$B13,Quotes!$G$5:$G$604,$C13,Quotes!$H$5:$H$604,$D13,Quotes!$J$5:$J$604,E$4,Quotes!$R$5:$R$604,"<>Unavailable")) -> 415.73913 | F13: =IF(COUNTIFS(Quotes!$E$5:$E$604,$B13,Quotes!$G$5:$G$604,$C13,Quotes!$H$5:$H$604,$D13,Quotes!$J$5:$J$604,F$4,Quotes!$R$5:$R$604,"<>Unavailable")=0,"",_xlfn.MINIFS(Quotes!$M$5:$M$604,Quotes!$E$5:$E$604,$B13,Quotes!$G$5:$G$604,$C13,Quotes!$H$5:$H$604,$D13,Quotes!$J$5:$J$604,F$4,Quotes!$R$5:$R$604,"<>Unavailable")) | G13: =IF(COUNTIFS(Quotes!$E$5:$E$604,$B13,Quotes!$G$5:$G$604,$C13,Quotes!$H$5:$H$604,$D13,Quotes!$J$5:$J$604,G$4,Quotes!$R$5:$R$604,"<>Unavailable")=0,"",_xlfn.MINIFS(Quotes!$M$5:$M$604,Quotes!$E$5:$E$604,$B13,Quotes!$G$5:$G$604,$C13,Quotes!$H$5:$H$604,$D13,Quotes!$J$5:$J$604,G$4,Quotes!$R$5:$R$604,"<>Unavailable")) | H13: =IF(COUNTIFS(Quotes!$E$5:$E$604,$B13,Quotes!$G$5:$G$604,$C13,Quotes!$H$5:$H$604,$D13,Quotes!$J$5:$J$604,H$4,Quotes!$R$5:$R$604,"<>Unavailable")=0,"",_xlfn.MINIFS(Quotes!$M$5:$M$604,Quotes!$E$5:$E$604,$B13,Quotes!$G$5:$G$604,$C13,Quotes!$H$5:$H$604,$D13,Quotes!$J$5:$J$604,H$4,Quotes!$R$5:$R$604,"<>Unavailable")) | I13: =IF(COUNTIFS(Quotes!$E$5:$E$604,$B13,Quotes!$G$5:$G$604,$C13,Quotes!$H$5:$H$604,$D13,Quotes!$J$5:$J$604,I$4,Quotes!$R$5:$R$604,"<>Unavailable")=0,"",_xlfn.MINIFS(Quotes!$M$5:$M$604,Quotes!$E$5:$E$604,$B13,Quotes!$G$5:$G$604,$C13,Quotes!$H$5:$H$604,$D13,Quotes!$J$5:$J$604,I$4,Quotes!$R$5:$R$604,"<>Unavailable")) | J13: =IF(COUNTIFS(Quotes!$E$5:$E$604,$B13,Quotes!$G$5:$G$604,$C13,Quotes!$H$5:$H$604,$D13,Quotes!$J$5:$J$604,J$4,Quotes!$R$5:$R$604,"<>Unavailable")=0,"",_xlfn.MINIFS(Quotes!$M$5:$M$604,Quotes!$E$5:$E$604,$B13,Quotes!$G$5:$G$604,$C13,Quotes!$H$5:$H$604,$D13,Quotes!$J$5:$J$604,J$4,Quotes!$R$5:$R$604,"<>Unavailable")) -> 416 | K13: =IF(COUNTIFS(Quotes!$E$5:$E$604,$B13,Quotes!$G$5:$G$604,$C13,Quotes!$H$5:$H$604,$D13,Quotes!$J$5:$J$604,K$4,Quotes!$R$5:$R$604,"<>Unavailable")=0,"",_xlfn.MINIFS(Quotes!$M$5:$M$604,Quotes!$E$5:$E$604,$B13,Quotes!$G$5:$G$604,$C13,Quotes!$H$5:$H$604,$D13,Quotes!$J$5:$J$604,K$4,Quotes!$R$5:$R$604,"<>Unavailable")) | L13: =IF(COUNT(E13:K13)=0,"",MIN(E13:K13)) -> 415.73913 | M13: =IF(L13="","",INDEX($E$4:$K$4,MATCH(L13,E13:K13,0))) -> Ottila | N13: =IF(OR(K13="",COUNT(E13:J13)=0),"",K13-MIN(E13:J13))
A14: Dambulla / Sigiriya | B14: Cinnamon Lodge -Habarana | C14: Superior room | D14: HB | E14: =IF(COUNTIFS(Quotes!$E$5:$E$604,$B14,Quotes!$G$5:$G$604,$C14,Quotes!$H$5:$H$604,$D14,Quotes!$J$5:$J$604,E$4,Quotes!$R$5:$R$604,"<>Unavailable")=0,"",_xlfn.MINIFS(Quotes!$M$5:$M$604,Quotes!$E$5:$E$604,$B14,Quotes!$G$5:$G$604,$C14,Quotes!$H$5:$H$604,$D14,Quotes!$J$5:$J$604,E$4,Quotes!$R$5:$R$604,"<>Unavailable")) | F14: =IF(COUNTIFS(Quotes!$E$5:$E$604,$B14,Quotes!$G$5:$G$604,$C14,Quotes!$H$5:$H$604,$D14,Quotes!$J$5:$J$604,F$4,Quotes!$R$5:$R$604,"<>Unavailable")=0,"",_xlfn.MINIFS(Quotes!$M$5:$M$604,Quotes!$E$5:$E$604,$B14,Quotes!$G$5:$G$604,$C14,Quotes!$H$5:$H$604,$D14,Quotes!$J$5:$J$604,F$4,Quotes!$R$5:$R$604,"<>Unavailable")) | G14: =IF(COUNTIFS(Quotes!$E$5:$E$604,$B14,Quotes!$G$5:$G$604,$C14,Quotes!$H$5:$H$604,$D14,Quotes!$J$5:$J$604,G$4,Quotes!$R$5:$R$604,"<>Unavailable")=0,"",_xlfn.MINIFS(Quotes!$M$5:$M$604,Quotes!$E$5:$E$604,$B14,Quotes!$G$5:$G$604,$C14,Quotes!$H$5:$H$604,$D14,Quotes!$J$5:$J$604,G$4,Quotes!$R$5:$R$604,"<>Unavailable")) -> 340 | H14: =IF(COUNTIFS(Quotes!$E$5:$E$604,$B14,Quotes!$G$5:$G$604,$C14,Quotes!$H$5:$H$604,$D14,Quotes!$J$5:$J$604,H$4,Quotes!$R$5:$R$604,"<>Unavailable")=0,"",_xlfn.MINIFS(Quotes!$M$5:$M$604,Quotes!$E$5:$E$604,$B14,Quotes!$G$5:$G$604,$C14,Quotes!$H$5:$H$604,$D14,Quotes!$J$5:$J$604,H$4,Quotes!$R$5:$R$604,"<>Unavailable")) | I14: =IF(COUNTIFS(Quotes!$E$5:$E$604,$B14,Quotes!$G$5:$G$604,$C14,Quotes!$H$5:$H$604,$D14,Quotes!$J$5:$J$604,I$4,Quotes!$R$5:$R$604,"<>Unavailable")=0,"",_xlfn.MINIFS(Quotes!$M$5:$M$604,Quotes!$E$5:$E$604,$B14,Quotes!$G$5:$G$604,$C14,Quotes!$H$5:$H$604,$D14,Quotes!$J$5:$J$604,I$4,Quotes!$R$5:$R$604,"<>Unavailable")) | J14: =IF(COUNTIFS(Quotes!$E$5:$E$604,$B14,Quotes!$G$5:$G$604,$C14,Quotes!$H$5:$H$604,$D14,Quotes!$J$5:$J$604,J$4,Quotes!$R$5:$R$604,"<>Unavailable")=0,"",_xlfn.MINIFS(Quotes!$M$5:$M$604,Quotes!$E$5:$E$604,$B14,Quotes!$G$5:$G$604,$C14,Quotes!$H$5:$H$604,$D14,Quotes!$J$5:$J$604,J$4,Quotes!$R$5:$R$604,"<>Unavailable")) | K14: =IF(COUNTIFS(Quotes!$E$5:$E$604,$B14,Quotes!$G$5:$G$604,$C14,Quotes!$H$5:$H$604,$D14,Quotes!$J$5:$J$604,K$4,Quotes!$R$5:$R$604,"<>Unavailable")=0,"",_xlfn.MINIFS(Quotes!$M$5:$M$604,Quotes!$E$5:$E$604,$B14,Quotes!$G$5:$G$604,$C14,Quotes!$H$5:$H$604,$D14,Quotes!$J$5:$J$604,K$4,Quotes!$R$5:$R$604,"<>Unavailable")) -> 438.17603 | L14: =IF(COUNT(E14:K14)=0,"",MIN(E14:K14)) -> 340 | M14: =IF(L14="","",INDEX($E$4:$K$4,MATCH(L14,E14:K14,0))) -> BTR | N14: =IF(OR(K14="",COUNT(E14:J14)=0),"",K14-MIN(E14:J14)) -> 98.176034
A15: Dambulla / Sigiriya | B15: EKHO Sigiriya | C15: Deluxe Room 22 SQM | D15: BB | E15: =IF(COUNTIFS(Quotes!$E$5:$E$604,$B15,Quotes!$G$5:$G$604,$C15,Quotes!$H$5:$H$604,$D15,Quotes!$J$5:$J$604,E$4,Quotes!$R$5:$R$604,"<>Unavailable")=0,"",_xlfn.MINIFS(Quotes!$M$5:$M$604,Quotes!$E$5:$E$604,$B15,Quotes!$G$5:$G$604,$C15,Quotes!$H$5:$H$604,$D15,Quotes!$J$5:$J$604,E$4,Quotes!$R$5:$R$604,"<>Unavailable")) -> 284.37964 | F15: =IF(COUNTIFS(Quotes!$E$5:$E$604,$B15,Quotes!$G$5:$G$604,$C15,Quotes!$H$5:$H$604,$D15,Quotes!$J$5:$J$604,F$4,Quotes!$R$5:$R$604,"<>Unavailable")=0,"",_xlfn.MINIFS(Quotes!$M$5:$M$604,Quotes!$E$5:$E$604,$B15,Quotes!$G$5:$G$604,$C15,Quotes!$H$5:$H$604,$D15,Quotes!$J$5:$J$604,F$4,Quotes!$R$5:$R$604,"<>Unavailable")) | G15: =IF(COUNTIFS(Quotes!$E$5:$E$604,$B15,Quotes!$G$5:$G$604,$C15,Quotes!$H$5:$H$604,$D15,Quotes!$J$5:$J$604,G$4,Quotes!$R$5:$R$604,"<>Unavailable")=0,"",_xlfn.MINIFS(Quotes!$M$5:$M$604,Quotes!$E$5:$E$604,$B15,Quotes!$G$5:$G$604,$C15,Quotes!$H$5:$H$604,$D15,Quotes!$J$5:$J$604,G$4,Quotes!$R$5:$R$604,"<>Unavailable")) | H15: =IF(COUNTIFS(Quotes!$E$5:$E$604,$B15,Quotes!$G$5:$G$604,$C15,Quotes!$H$5:$H$604,$D15,Quotes!$J$5:$J$604,H$4,Quotes!$R$5:$R$604,"<>Unavailable")=0,"",_xlfn.MINIFS(Quotes!$M$5:$M$604,Quotes!$E$5:$E$604,$B15,Quotes!$G$5:$G$604,$C15,Quotes!$H$5:$H$604,$D15,Quotes!$J$5:$J$604,H$4,Quotes!$R$5:$R$604,"<>Unavailable")) | I15: =IF(COUNTIFS(Quotes!$E$5:$E$604,$B15,Quotes!$G$5:$G$604,$C15,Quotes!$H$5:$H$604,$D15,Quotes!$J$5:$J$604,I$4,Quotes!$R$5:$R$604,"<>Unavailable")=0,"",_xlfn.MINIFS(Quotes!$M$5:$M$604,Quotes!$E$5:$E$604,$B15,Quotes!$G$5:$G$604,$C15,Quotes!$H$5:$H$604,$D15,Quotes!$J$5:$J$604,I$4,Quotes!$R$5:$R$604,"<>Unavailable")) | J15: =IF(COUNTIFS(Quotes!$E$5:$E$604,$B15,Quotes!$G$5:$G$604,$C15,Quotes!$H$5:$H$604,$D15,Quotes!$J$5:$J$604,J$4,Quotes!$R$5:$R$604,"<>Unavailable")=0,"",_xlfn.MINIFS(Quotes!$M$5:$M$604,Quotes!$E$5:$E$604,$B15,Quotes!$G$5:$G$604,$C15,Quotes!$H$5:$H$604,$D15,Quotes!$J$5:$J$604,J$4,Quotes!$R$5:$R$604,"<>Unavailable")) | K15: =IF(COUNTIFS(Quotes!$E$5:$E$604,$B15,Quotes!$G$5:$G$604,$C15,Quotes!$H$5:$H$604,$D15,Quotes!$J$5:$J$604,K$4,Quotes!$R$5:$R$604,"<>Unavailable")=0,"",_xlfn.MINIFS(Quotes!$M$5:$M$604,Quotes!$E$5:$E$604,$B15,Quotes!$G$5:$G$604,$C15,Quotes!$H$5:$H$604,$D15,Quotes!$J$5:$J$604,K$4,Quotes!$R$5:$R$604,"<>Unavailable")) | L15: =IF(COUNT(E15:K15)=0,"",MIN(E15:K15)) -> 284.37964 | M15: =IF(L15="","",INDEX($E$4:$K$4,MATCH(L15,E15:K15,0))) -> Ottila | N15: =IF(OR(K15="",COUNT(E15:J15)=0),"",K15-MIN(E15:J15))
A16: Dambulla / Sigiriya | B16: EKHO Sigiriya | C16: suite room | D16: HB | E16: =IF(COUNTIFS(Quotes!$E$5:$E$604,$B16,Quotes!$G$5:$G$604,$C16,Quotes!$H$5:$H$604,$D16,Quotes!$J$5:$J$604,E$4,Quotes!$R$5:$R$604,"<>Unavailable")=0,"",_xlfn.MINIFS(Quotes!$M$5:$M$604,Quotes!$E$5:$E$604,$B16,Quotes!$G$5:$G$604,$C16,Quotes!$H$5:$H$604,$D16,Quotes!$J$5:$J$604,E$4,Quotes!$R$5:$R$604,"<>Unavailable")) | F16: =IF(COUNTIFS(Quotes!$E$5:$E$604,$B16,Quotes!$G$5:$G$604,$C16,Quotes!$H$5:$H$604,$D16,Quotes!$J$5:$J$604,F$4,Quotes!$R$5:$R$604,"<>Unavailable")=0,"",_xlfn.MINIFS(Quotes!$M$5:$M$604,Quotes!$E$5:$E$604,$B16,Quotes!$G$5:$G$604,$C16,Quotes!$H$5:$H$604,$D16,Quotes!$J$5:$J$604,F$4,Quotes!$R$5:$R$604,"<>Unavailable")) | G16: =IF(COUNTIFS(Quotes!$E$5:$E$604,$B16,Quotes!$G$5:$G$604,$C16,Quotes!$H$5:$H$604,$D16,Quotes!$J$5:$J$604,G$4,Quotes!$R$5:$R$604,"<>Unavailable")=0,"",_xlfn.MINIFS(Quotes!$M$5:$M$604,Quotes!$E$5:$E$604,$B16,Quotes!$G$5:$G$604,$C16,Quotes!$H$5:$H$604,$D16,Quotes!$J$5:$J$604,G$4,Quotes!$R$5:$R$604,"<>Unavailable")) | H16: =IF(COUNTIFS(Quotes!$E$5:$E$604,$B16,Quotes!$G$5:$G$604,$C16,Quotes!$H$5:$H$604,$D16,Quotes!$J$5:$J$604,H$4,Quotes!$R$5:$R$604,"<>Unavailable")=0,"",_xlfn.MINIFS(Quotes!$M$5:$M$604,Quotes!$E$5:$E$604,$B16,Quotes!$G$5:$G$604,$C16,Quotes!$H$5:$H$604,$D16,Quotes!$J$5:$J$604,H$4,Quotes!$R$5:$R$604,"<>Unavailable")) | I16: =IF(COUNTIFS(Quotes!$E$5:$E$604,$B16,Quotes!$G$5:$G$604,$C16,Quotes!$H$5:$H$604,$D16,Quotes!$J$5:$J$604,I$4,Quotes!$R$5:$R$604,"<>Unavailable")=0,"",_xlfn.MINIFS(Quotes!$M$5:$M$604,Quotes!$E$5:$E$604,$B16,Quotes!$G$5:$G$604,$C16,Quotes!$H$5:$H$604,$D16,Quotes!$J$5:$J$604,I$4,Quotes!$R$5:$R$604,"<>Unavailable")) -> 520.76352 | J16: =IF(COUNTIFS(Quotes!$E$5:$E$604,$B16,Quotes!$G$5:$G$604,$C16,Quotes!$H$5:$H$604,$D16,Quotes!$J$5:$J$604,J$4,Quotes!$R$5:$R$604,"<>Unavailable")=0,"",_xlfn.MINIFS(Quotes!$M$5:$M$604,Quotes!$E$5:$E$604,$B16,Quotes!$G$5:$G$604,$C16,Quotes!$H$5:$H$604,$D16,Quotes!$J$5:$J$604,J$4,Quotes!$R$5:$R$604,"<>Unavailable")) | K16: =IF(COUNTIFS(Quotes!$E$5:$E$604,$B16,Quotes!$G$5:$G$604,$C16,Quotes!$H$5:$H$604,$D16,Quotes!$J$5:$J$604,K$4,Quotes!$R$5:$R$604,"<>Unavailable")=0,"",_xlfn.MINIFS(Quotes!$M$5:$M$604,Quotes!$E$5:$E$604,$B16,Quotes!$G$5:$G$604,$C16,Quotes!$H$5:$H$604,$D16,Quotes!$J$5:$J$604,K$4,Quotes!$R$5:$R$604,"<>Unavailable")) | L16: =IF(COUNT(E16:K16)=0,"",MIN(E16:K16)) -> 520.76352 | M16: =IF(L16="","",INDEX($E$4:$K$4,MATCH(L16,E16:K16,0))) -> Direct | N16: =IF(OR(K16="",COUNT(E16:J16)=0),"",K16-MIN(E16:J16))
... A75: Colombo | B75: colombo international airport hotel | C75: Deluxe Double Room, City View,1 Double Bed DBL/SGL29m2 | D75: N/A | E75: =IF(COUNTIFS(Quotes!$E$5:$E$604,$B75,Quotes!$G$5:$G$604,$C75,Quotes!$H$5:$H$604,$D75,Quotes!$J$5:$J$604,E$4,Quotes!$R$5:$R$604,"<>Unavailable")=0,"",_xlfn.MINIFS(Quotes!$M$5:$M$604,Quotes!$E$5:$E$604,$B75,Quotes!$G$5:$G$604,$C75,Quotes!$H$5:$H$604,$D75,Quotes!$J$5:$J$604,E$4,Quotes!$R$5:$R$604,"<>Unavailable")) | F75: =IF(COUNTIFS(Quotes!$E$5:$E$604,$B75,Quotes!$G$5:$G$604,$C75,Quotes!$H$5:$H$604,$D75,Quotes!$J$5:$J$604,F$4,Quotes!$R$5:$R$604,"<>Unavailable")=0,"",_xlfn.MINIFS(Quotes!$M$5:$M$604,Quotes!$E$5:$E$604,$B75,Quotes!$G$5:$G$604,$C75,Quotes!$H$5:$H$604,$D75,Quotes!$J$5:$J$604,F$4,Quotes!$R$5:$R$604,"<>Unavailable")) -> 92.725345 | G75: =IF(COUNTIFS(Quotes!$E$5:$E$604,$B75,Quotes!$G$5:$G$604,$C75,Quotes!$H$5:$H$604,$D75,Quotes!$J$5:$J$604,G$4,Quotes!$R$5:$R$604,"<>Unavailable")=0,"",_xlfn.MINIFS(Quotes!$M$5:$M$604,Quotes!$E$5:$E$604,$B75,Quotes!$G$5:$G$604,$C75,Quotes!$H$5:$H$604,$D75,Quotes!$J$5:$J$604,G$4,Quotes!$R$5:$R$604,"<>Unavailable")) | H75: =IF(COUNTIFS(Quotes!$E$5:$E$604,$B75,Quotes!$G$5:$G$604,$C75,Quotes!$H$5:$H$604,$D75,Quotes!$J$5:$J$604,H$4,Quotes!$R$5:$R$604,"<>Unavailable")=0,"",_xlfn.MINIFS(Quotes!$M$5:$M$604,Quotes!$E$5:$E$604,$B75,Quotes!$G$5:$G$604,$C75,Quotes!$H$5:$H$604,$D75,Quotes!$J$5:$J$604,H$4,Quotes!$R$5:$R$604,"<>Unavailable")) | I75: =IF(COUNTIFS(Quotes!$E$5:$E$604,$B75,Quotes!$G$5:$G$604,$C75,Quotes!$H$5:$H$604,$D75,Quotes!$J$5:$J$604,I$4,Quotes!$R$5:$R$604,"<>Unavailable")=0,"",_xlfn.MINIFS(Quotes!$M$5:$M$604,Quotes!$E$5:$E$604,$B75,Quotes!$G$5:$G$604,$C75,Quotes!$H$5:$H$604,$D75,Quotes!$J$5:$J$604,I$4,Quotes!$R$5:$R$604,"<>Unavailable")) -> 142 | J75: =IF(COUNTIFS(Quotes!$E$5:$E$604,$B75,Quotes!$G$5:$G$604,$C75,Quotes!$H$5:$H$604,$D75,Quotes!$J$5:$J$604,J$4,Quotes!$R$5:$R$604,"<>Unavailable")=0,"",_xlfn.MINIFS(Quotes!$M$5:$M$604,Quotes!$E$5:$E$604,$B75,Quotes!$G$5:$G$604,$C75,Quotes!$H$5:$H$604,$D75,Quotes!$J$5:$J$604,J$4,Quotes!$R$5:$R$604,"<>Unavailable")) | K75: =IF(COUNTIFS(Quotes!$E$5:$E$604,$B75,Quotes!$G$5:$G$604,$C75,Quotes!$H$5:$H$604,$D75,Quotes!$J$5:$J$604,K$4,Quotes!$R$5:$R$604,"<>Unavailable")=0,"",_xlfn.MINIFS(Quotes!$M$5:$M$604,Quotes!$E$5:$E$604,$B75,Quotes!$G$5:$G$604,$C75,Quotes!$H$5:$H$604,$D75,Quotes!$J$5:$J$604,K$4,Quotes!$R$5:$R$604,"<>Unavailable")) -> 115.62036 | L75: =IF(COUNT(E75:K75)=0,"",MIN(E75:K75)) -> 92.725345 | M75: =IF(L75="","",INDEX($E$4:$K$4,MATCH(L75,E75:K75,0))) -> TBO | N75: =IF(OR(K75="",COUNT(E75:J75)=0),"",K75-MIN(E75:J75)) -> 22.895016

Sheet Land
A1: Land, transport & other services
A2: Basis 'Total' = amount is for the whole group; 'Per pax' = amount × Pax/Qty.
A4: # | B4: Date | C4: Service | D4: Type | E4: Source | F4: Currency | G4: Amount | H4: Basis | I4: Pax / Qty | J4: Total cost (costing ccy) | K4: Markup % (blank = default) | L4: Sell total | M4: Pkg A | N4: Pkg B | O4: Pkg C | P4: Notes
A5: 1 | B5: 46375 | C5: Minibus with English-speaking National Guide & driver (full tour) | D5: Transport | E5: Helanka | F5: USD | G5: 2725 | H5: Total | I5: 1 | J5: =IF(G5="","",IFERROR(G5*INDEX(Trip!$E$5:$E$14,MATCH(F5,Trip!$D$5:$D$14,0))/INDEX(Trip!$E$5:$E$14,MATCH(Trip!$B$10,Trip!$D$5:$D$14,0))*IF(H5="Per pax",I5,1),"")) -> 2725 | K5: 0.1017 | L5: =IF(J5="","",J5*(1+IF(K5="",Trip!$B$11,K5))) -> 3002.1325
A6: 2 | B6: 46375 | C6: Two Toyota vans with English-speaking chauffeurs (full tour) | D6: Transport | E6: Helanka | F6: USD | G6: 2695 | H6: Total | I6: 1 | J6: =IF(G6="","",IFERROR(G6*INDEX(Trip!$E$5:$E$14,MATCH(F6,Trip!$D$5:$D$14,0))/INDEX(Trip!$E$5:$E$14,MATCH(Trip!$B$10,Trip!$D$5:$D$14,0))*IF(H6="Per pax",I6,1),"")) -> 2695 | K6: 0.1013 | L6: =IF(J6="","",J6*(1+IF(K6="",Trip!$B$11,K6))) -> 2968.0035
A7: 3 | B7: 46375 | C7: 2 Toyota KDH vans for arrival + mini coach with guide | D7: Transport | E7: Helanka | F7: USD | G7: 2535 | H7: Total | I7: 1 | J7: =IF(G7="","",IFERROR(G7*INDEX(Trip!$E$5:$E$14,MATCH(F7,Trip!$D$5:$D$14,0))/INDEX(Trip!$E$5:$E$14,MATCH(Trip!$B$10,Trip!$D$5:$D$14,0))*IF(H7="Per pax",I7,1),"")) -> 2535 | K7: 0.13 | L7: =IF(J7="","",J7*(1+IF(K7="",Trip!$B$11,K7))) -> 2864.55
A8: 4 | B8: 46381 | C8: Train journey Nanu Oya to Ella | D8: Train | E8: Online | F8: USD | G8: 30 | H8: Per pax | I8: 9 | J8: =IF(G8="","",IFERROR(G8*INDEX(Trip!$E$5:$E$14,MATCH(F8,Trip!$D$5:$D$14,0))/INDEX(Trip!$E$5:$E$14,MATCH(Trip!$B$10,Trip!$D$5:$D$14,0))*IF(H8="Per pax",I8,1),"")) -> 270 | K8: 0.15 | L8: =IF(J8="","",J8*(1+IF(K8="",Trip!$B$11,K8))) -> 310.5

Sheet Final
A1: Final costing
A2: Adds up every Quotes / Land row marked Y for each package. Change the package names and pax freely.
B4: Pkg A | C4: Pkg B | D4: Pkg C | E4: How it's calculated
A5: Package name | B5: Per couple (DBL) | C5: Single (SGL) | D5: Per couple – upgraded room | E5: Type your own name
A6: Pax covered by this price | B6: 2 | C6: 1 | D6: 2 | E6: e.g. 2 for a couple, 1 for a single
A7: Price basis | B7: Per room | C7: Per room | D7: Per room | E7: Per room = 1 room of each hotel row (per couple / per single quote). All rooms = whole group (uses the Rooms column)
A8: Hotels — cost to us | B8: =IF(B7="All rooms",SUMIFS(Quotes!$O$5:$O$604,Quotes!$AA$5:$AA$604,"Y"),SUMIFS(Quotes!$M$5:$M$604,Quotes!$AA$5:$AA$604,"Y")) -> 2535.0106 | C8: =IF(C7="All rooms",SUMIFS(Quotes!$O$5:$O$604,Quotes!$AB$5:$AB$604,"Y"),SUMIFS(Quotes!$M$5:$M$604,Quotes!$AB$5:$AB$604,"Y")) -> 2437.4406 | D8: =IF(D7="All rooms",SUMIFS(Quotes!$O$5:$O$604,Quotes!$AC$5:$AC$604,"Y"),SUMIFS(Quotes!$M$5:$M$604,Quotes!$AC$5:$AC$604,"Y")) -> 2844.0606 | E8: Quotes rows with Y
A9: Land & other — cost to us | B9: =SUMIFS(Land!$J$5:$J$204,Land!$M$5:$M$204,"Y") -> 0 | C9: =SUMIFS(Land!$J$5:$J$204,Land!$N$5:$N$204,"Y") -> 0 | D9: =SUMIFS(Land!$J$5:$J$204,Land!$O$5:$O$204,"Y") -> 0 | E9: Land rows with Y
A10: Total cost to us | B10: =B8+B9 -> 2535.0106 | C10: =C8+C9 -> 2437.4406 | D10: =D8+D9 -> 2844.0606 | E10: Hotels + land
A11: Markup | B11: =IF(B7="All rooms",SUMIFS(Quotes!$W$5:$W$604,Quotes!$AA$5:$AA$604,"Y"),SUMIFS(Quotes!$V$5:$V$604,Quotes!$AA$5:$AA$604,"Y"))+SUMIFS(Land!$L$5:$L$204,Land!$M$5:$M$204,"Y")-B10 -> 577.9716 | C11: =IF(C7="All rooms",SUMIFS(Quotes!$W$5:$W$604,Quotes!$AB$5:$AB$604,"Y"),SUMIFS(Quotes!$V$5:$V$604,Quotes!$AB$5:$AB$604,"Y"))+SUMIFS(Land!$L$5:$L$204,Land!$N$5:$N$204,"Y")-C10 -> 580.5021 | D11: =IF(D7="All rooms",SUMIFS(Quotes!$W$5:$W$604,Quotes!$AC$5:$AC$604,"Y"),SUMIFS(Quotes!$V$5:$V$604,Quotes!$AC$5:$AC$604,"Y"))+SUMIFS(Land!$L$5:$L$204,Land!$O$5:$O$204,"Y")-D10 -> 474.93264 | E11: Sell price − cost (row-level markups)
A12: Cost to client | B12: =B10+B11 -> 3112.9822 | C12: =C10+C11 -> 3017.9427 | D12: =D10+D11 -> 3318.9932 | E12: Cost + markup
A13: GST | B13: =B12*Trip!$B$12 -> 155.64911 | C13: =C12*Trip!$B$12 -> 150.89714 | D13: =D12*Trip!$B$12 -> 165.94966 | E13: GST % from Trip tab × cost to client
A14: TCS | B14: =(B12+B13)*Trip!$B$13 -> 65.372626 | C14: =(C12+C13)*Trip!$B$13 -> 63.376797 | D14: =(D12+D13)*Trip!$B$13 -> 69.698858 | E14: TCS % from Trip tab × (client cost + GST)
A15: Payable (costing currency) | B15: =B12+B13+B14 -> 3334.0039 | C15: =C12+C13+C14 -> 3232.2166 | D15: =D12+D13+D14 -> 3554.6418 | E15: Client cost + GST + TCS
A16: Exchange rate (₹ per 1 unit) | B16: =IFERROR(INDEX(Trip!$E$5:$E$14,MATCH(Trip!$B$10,Trip!$D$5:$D$14,0)),0) -> 94.3 | C16: =IFERROR(INDEX(Trip!$E$5:$E$14,MATCH(Trip!$B$10,Trip!$D$5:$D$14,0)),0) -> 94.3 | D16: =IFERROR(INDEX(Trip!$E$5:$E$14,MATCH(Trip!$B$10,Trip!$D$5:$D$14,0)),0) -> 94.3 | E16: From Trip tab
A17: Payable in ₹ | B17: =B15*B16 -> 314396.57 | C17: =C15*C16 -> 304798.03 | D17: =D15*D16 -> 335202.72 | E17: Payable × rate
A18: Payable in ₹ — rounded up | B18: =ROUNDUP(B17,-2) -> 314400 | C18: =ROUNDUP(C17,-2) -> 304800 | D18: =ROUNDUP(D17,-2) -> 335300 | E18: Rounded up to the next ₹100
A19: Per pax in ₹ | B19: =IF(B6>0,B18/B6,"") -> 157200 | C19: =IF(C6>0,C18/C6,"") -> 304800 | D19: =IF(D6>0,D18/D6,"") -> 167650 | E19: Rounded payable ÷ pax covered
A20: Markup % on cost | B20: =IF(B10>0,B11/B10,"") -> 0.22799573 | C20: =IF(C10>0,C11/C10,"") -> 0.23816051 | D20: =IF(D10>0,D11/D10,"") -> 0.16699104 | E20: Check: is the margin right?
A21: Earliest free-cancel deadline | B21: =IF(COUNTIFS(Quotes!$AA$5:$AA$604,"Y",Quotes!$P$5:$P$604,">0")=0,"—",_xlfn.MINIFS(Quotes!$P$5:$P$604,Quotes!$AA$5:$AA$604,"Y")) -> 46287 | C21: =IF(COUNTIFS(Quotes!$AB$5:$AB$604,"Y",Quotes!$P$5:$P$604,">0")=0,"—",_xlfn.MINIFS(Quotes!$P$5:$P$604,Quotes!$AB$5:$AB$604,"Y")) -> 46287 | D21: =IF(COUNTIFS(Quotes!$AC$5:$AC$604,"Y",Quotes!$P$5:$P$604,">0")=0,"—",_xlfn.MINIFS(Quotes!$P$5:$P$604,Quotes!$AC$5:$AC$604,"Y")) -> 46287 | E21: Book or cancel before this date
A22: Rows included (hotels / land) | B22: =COUNTIF(Quotes!$AA$5:$AA$604,"Y")&" / "&COUNTIF(Land!$M$5:$M$204,"Y") -> 5 / 0 | C22: =COUNTIF(Quotes!$AB$5:$AB$604,"Y")&" / "&COUNTIF(Land!$N$5:$N$204,"Y") -> 5 / 0 | D22: =COUNTIF(Quotes!$AC$5:$AC$604,"Y")&" / "&COUNTIF(Land!$O$5:$O$204,"Y") -> 5 / 0 | E22: Quick check nothing is missing
A24: Costing currency: | B24: =Trip!$B$10 -> USD

Sheet Lists
A1: Sources | B1: Meal | C1: Status | D1: LandType | E1: Basis | F1: YN
A2: Ottila | B2: RO | C2: Quote | D2: Transport | E2: Total | F2: Y
A3: TBO | B3: BB | C3: Requested | D3: Transfer | E3: Per pax
A4: BTR | B4: HB | C4: Blocked | D4: Tour
A5: Helanka | B5: FB | C5: Booked | D5: Activity
A6: Direct | B6: AI | C6: Unavailable | D6: Train
A7: DMC | B7: N/A | D7: Pass
A8: Booking.com | D8: Guide
A9: Hotel website | D9: Flight
A10: Agoda | D10: Visa
A11: Expedia | D11: Insurance
A12: Tourfox | D12: Other
A13: Weshare
A14: Online
A15: Other
